Workbook

Sheet AMM PIK 2024-2025
A1: PIC CONTROL | C1: : HANDRE ADITYA PUTRA | F1: NOTE : ISI SESUAI YANG BERSANGKUTAN DAN ISI LANGSUNG DI SPREADSHEET JIKA EMANG AKAN DITARIK KE EXCELL PASTIKAN FORMAT DAN TABEL SESUAI. | AA1: NOTE : AUXILIARY TABLE ( AUTOMATIC FORMULA ) | AO1: NOTE : AUXILIARY TABLE ( AUTOMATIC FORMULA & CHART )
A2: LOCATION | C2: : AMM BENGALON KPC
A3: PERIODE | C3: : 2023 | F3: MONITORING CONTROL SPB-PO-DO-IT-INVOICE GMI AMM BENGALON KPC
A4: NOTE | C4: : | AO4: =NOW() -> 46301.766
AB5: DATA TABLE DASHBOARD SPB | AO5: DASHBOARD SPB GMI AMM PIK
D6: WAREHOUSE | Q6: MARKETING | U6: LOGISTICS | W6: FINANCE
A7: NO | B7: TANGGAL SPB | C7: NO SPB | D7: PART NUMBER | E7: PART NAME | F7: QTY | G7: UOM | H7: UNIT CODE | I7: TYPE UNIT | J7: BRAND | K7: PROBLEM | L7: PIC GMI | M7: PIC PPA | N7: NO WO | O7: STATUS WO | P7: WO DATE | Q7: NO PO | R7: PO DATE | S7: NO SO | T7: SO DATE | U7: NO DO | V7: DO DATE | W7: NO INVOICE | X7: TANGGAL KIRIM | Y7: STATUS PAYMENT | AA7: NO | AB7: NO SPB | AC7: TGL SPB | AD7: NO DO | AE7: TGL DO | AF7: NO WO | AG7: NO PO | AH7: NO SO | AI7: TGL so | AJ7: NO INVOICE | AK7: TANGAL INVOICE | AL7: STATUS SPB | AM7: STATUS PAYMENT | AO7: NO | AP7: DESCRIPTION | AQ7: DONE | AR7: WAITING | AS7: TOTAL
A8: 1 | B8: 45323 | C8: GMIAMMPIK/2024/01/001 | D8: 11L-3024 | E8: =VLOOKUP(D8,MP!$A$1:$C$14184,2,0) -> LED FLood Light 6 Eyes 18 Watt 10-30 VDC | F8: 5 | G8: PCS | H8: LOGISTIK | I8: =IFERROR(INDEX(POP!$I:$I,MATCH(H8,POP!$G:$G,0)),"general") -> general | J8: =IFERROR(INDEX(POP!$E:$E,MATCH(H8,POP!$G:$G,0)),"general") -> general | K8: KEBUTUHAN PIK | L8: FANDY | M8: RESTU | N8: REFF PO | O8: DONE FROM BC | P8: =B8 -> 45323 | Q8: 7000142922 | R8: 45313 | U8: DO 21865 | V8: 45293 | W8: GMI-0018033 | X8: 45328 | Y8: 45370 | AA8: 1 | AB8: GMIAMMPIK/2024/01/001 | AC8: =IFERROR(INDEX($B:$B,MATCH(AB8,$C:$C,FALSE)),"") -> 45323 | AD8: =INDEX($U:$U,MATCH(AB8,$C:$C,FALSE)) -> DO 21865 | AE8: =IFERROR(INDEX($V:$V,MATCH(AB8,$C:$C,FALSE)),"") -> 45293 | AF8: =IFERROR(INDEX($N:$N,MATCH(AB8,$C:$C,FALSE)),"") -> REFF PO | AG8: =INDEX($Q:$Q,MATCH(AB8,$C:$C,FALSE)) -> 7000142922 | AH8: =IFERROR(INDEX($S:$S,MATCH(AB8,$C:$C,FALSE)),"") | AI8: =IFERROR(INDEX($T:$T,MATCH(AB8,$C:$C,FALSE)),"") | AJ8: =INDEX($W:$W,MATCH(AB8,$C:$C,FALSE)) -> GMI-0018033 | AK8: =IFERROR(INDEX($X:$X,MATCH(AB8,$C:$C,FALSE)),"") -> 45328 | AL8: =INDEX($O:$O,MATCH(AF8,$N:$N,FALSE),"") -> DONE FROM BC | AM8: =INDEX($Y:$Y,MATCH(AB8,$C:$C,FALSE)) -> 45370 | AO8: 1 | AP8: SPB | AQ8: =COUNTIF($AL:$AL,"DONE FROM BC") -> 192 | AR8: =COUNTIF($AL:$AL,"WAITING") -> 0 | AS8: =SUM(AQ8:AR8) -> 192
A9: 2 | B9: 45336 | C9: GMIAMMPIK/2024/02/003 | D9: 11L-1290-ARW | E9: =VLOOKUP(D9,MP!$A$1:$C$14184,2,0) -> LED Combination Lamp Amber Red White | F9: 2 | G9: PCS | H9: PLTAM15 | I9: =IFERROR(INDEX(POP!$I:$I,MATCH(H9,POP!$G:$G,0)),"general") -> general | J9: =IFERROR(INDEX(POP!$E:$E,MATCH(H9,POP!$G:$G,0)),"general") -> general | K9: COMMISIONING UNIT | L9: FANDY | M9: RESTU | N9: 200000661855 | O9: DONE FROM BC | P9: =B9 -> 45336 | Q9: 9200006866 | R9: 45341 | U9: DO 22477 | V9: 29/2/2024 | W9: GMI-0018575 | X9: 45358 | Y9: 45412 | AA9: 2 | AB9: GMIAMMPIK/2024/02/003 | AC9: =IFERROR(INDEX($B:$B,MATCH(AB9,$C:$C,FALSE)),"") -> 45336 | AD9: =INDEX($U:$U,MATCH(AB9,$C:$C,FALSE)) -> DO 22477 | AE9: =IFERROR(INDEX($V:$V,MATCH(AB9,$C:$C,FALSE)),"") -> 29/2/2024 | AF9: =IFERROR(INDEX($N:$N,MATCH(AB9,$C:$C,FALSE)),"") -> 200000661855 | AG9: =INDEX($Q:$Q,MATCH(AB9,$C:$C,FALSE)) -> 9200006866 | AH9: =IFERROR(INDEX($S:$S,MATCH(AB9,$C:$C,FALSE)),"") | AI9: =IFERROR(INDEX($T:$T,MATCH(AB9,$C:$C,FALSE)),"") | AJ9: =INDEX($W:$W,MATCH(AB9,$C:$C,FALSE)) -> GMI-0018575 | AK9: =IFERROR(INDEX($X:$X,MATCH(AB9,$C:$C,FALSE)),"") -> 45358 | AL9: =INDEX($O:$O,MATCH(AF9,$N:$N,FALSE),"") -> DONE FROM BC | AM9: =INDEX($Y:$Y,MATCH(AB9,$C:$C,FALSE)) -> 45412 | AO9: 2 | AP9: DO | AQ9: =COUNTA($AD$8:$AD$277) -> 270 | AR9: =COUNTBLANK($AD$8:$AD$105) -> 1 | AS9: =SUM(AQ9:AR9) -> 271
A10: 3 | B10: 45336 | C10: GMIAMMPIK/2024/02/004 | D10: 11L-1290-ARW | E10: =VLOOKUP(D10,MP!$A$1:$C$14184,2,0) -> LED Combination Lamp Amber Red White | F10: 2 | G10: PCS | H10: PLTAM15 | I10: =IFERROR(INDEX(POP!$I:$I,MATCH(H10,POP!$G:$G,0)),"general") -> general | J10: =IFERROR(INDEX(POP!$E:$E,MATCH(H10,POP!$G:$G,0)),"general") -> general | K10: COMMISIONING UNIT | L10: FANDY | M10: RESTU | N10: 200000661851 | O10: DONE FROM BC | P10: =B10 -> 45336 | Q10: 9200006867 | U10: DO 22476 | V10: 29/2/2024 | W10: GMI-0018574 | X10: 45358 | Y10: 45412 | AA10: 3 | AB10: GMIAMMPIK/2024/02/004 | AC10: =IFERROR(INDEX($B:$B,MATCH(AB10,$C:$C,FALSE)),"") -> 45336 | AD10: =INDEX($U:$U,MATCH(AB10,$C:$C,FALSE)) -> DO 22476 | AE10: =IFERROR(INDEX($V:$V,MATCH(AB10,$C:$C,FALSE)),"") -> 29/2/2024 | AF10: =IFERROR(INDEX($N:$N,MATCH(AB10,$C:$C,FALSE)),"") -> 200000661851 | AG10: =INDEX($Q:$Q,MATCH(AB10,$C:$C,FALSE)) -> 9200006867 | AH10: =IFERROR(INDEX($S:$S,MATCH(AB10,$C:$C,FALSE)),"") | AI10: =IFERROR(INDEX($T:$T,MATCH(AB10,$C:$C,FALSE)),"") | AJ10: =INDEX($W:$W,MATCH(AB10,$C:$C,FALSE)) -> GMI-0018574 | AK10: =IFERROR(INDEX($X:$X,MATCH(AB10,$C:$C,FALSE)),"") -> 45358 | AL10: =INDEX($O:$O,MATCH(AF10,$N:$N,FALSE),"") -> DONE FROM BC | AM10: =INDEX($Y:$Y,MATCH(AB10,$C:$C,FALSE)) -> 45412 | AO10: 3 | AP10: PO | AQ10: =COUNTIF($AG:$AG,">0") -> 270 | AR10: =COUNTBLANK($AG$8:$AG$105) -> 0 | AS10: =SUM(AQ10:AR10) -> 270
A11: 4 | B11: 45336 | C11: GMIAMMPIK/2024/02/005 | D11: 11L-1290-ARW | E11: =VLOOKUP(D11,MP!$A$1:$C$14184,2,0) -> LED Combination Lamp Amber Red White | F11: 2 | G11: PCS | H11: PLTAM15 | I11: =IFERROR(INDEX(POP!$I:$I,MATCH(H11,POP!$G:$G,0)),"general") -> general | J11: =IFERROR(INDEX(POP!$E:$E,MATCH(H11,POP!$G:$G,0)),"general") -> general | K11: COMMISIONING UNIT | L11: FANDY | M11: RESTU | N11: 200000661847 | O11: DONE FROM BC | P11: =B11 -> 45336 | Q11: 9200006868 | U11: DO 22475 | V11: 29/2/2024 | W11: GMI-0018573 | X11: 45358 | Y11: 45412 | AA11: 4 | AB11: GMIAMMPIK/2024/02/005 | AC11: =IFERROR(INDEX($B:$B,MATCH(AB11,$C:$C,FALSE)),"") -> 45336 | AD11: =INDEX($U:$U,MATCH(AB11,$C:$C,FALSE)) -> DO 22475 | AE11: =IFERROR(INDEX($V:$V,MATCH(AB11,$C:$C,FALSE)),"") -> 29/2/2024 | AF11: =IFERROR(INDEX($N:$N,MATCH(AB11,$C:$C,FALSE)),"") -> 200000661847 | AG11: =INDEX($Q:$Q,MATCH(AB11,$C:$C,FALSE)) -> 9200006868 | AH11: =IFERROR(INDEX($S:$S,MATCH(AB11,$C:$C,FALSE)),"") | AI11: =IFERROR(INDEX($T:$T,MATCH(AB11,$C:$C,FALSE)),"") | AJ11: =INDEX($W:$W,MATCH(AB11,$C:$C,FALSE)) -> GMI-0018573 | AK11: =IFERROR(INDEX($X:$X,MATCH(AB11,$C:$C,FALSE)),"") -> 45358 | AL11: =INDEX($O:$O,MATCH(AF11,$N:$N,FALSE),"") -> DONE FROM BC | AM11: =INDEX($Y:$Y,MATCH(AB11,$C:$C,FALSE)) -> 45412 | AO11: 4 | AP11: INVOICE | AQ11: =COUNTA(AJ8:AJ277) -> 269 | AR11: =COUNTBLANK($AJ$8:$AJ$105) -> 1 | AS11: =SUM(AQ11:AR11) -> 270
A12: 5 | B12: 45336 | C12: GMIAMMPIK/2024/02/006 | D12: 11L-1290-ARW | E12: =VLOOKUP(D12,MP!$A$1:$C$14184,2,0) -> LED Combination Lamp Amber Red White | F12: 2 | G12: PCS | H12: PLTAM15 | I12: =IFERROR(INDEX(POP!$I:$I,MATCH(H12,POP!$G:$G,0)),"general") -> general | J12: =IFERROR(INDEX(POP!$E:$E,MATCH(H12,POP!$G:$G,0)),"general") -> general | K12: COMMISIONING UNIT | L12: FANDY | M12: RESTU | N12: 200000661838 | O12: DONE FROM BC | P12: =B12 -> 45336 | Q12: 9200006869 | U12: DO 22431 | V12: 29/2/2024 | W12: GMI-0018572 | X12: 45358 | Y12: 45412 | AA12: 5 | AB12: GMIAMMPIK/2024/02/006 | AC12: =IFERROR(INDEX($B:$B,MATCH(AB12,$C:$C,FALSE)),"") -> 45336 | AD12: =INDEX($U:$U,MATCH(AB12,$C:$C,FALSE)) -> DO 22431 | AE12: =IFERROR(INDEX($V:$V,MATCH(AB12,$C:$C,FALSE)),"") -> 29/2/2024 | AF12: =IFERROR(INDEX($N:$N,MATCH(AB12,$C:$C,FALSE)),"") -> 200000661838 | AG12: =INDEX($Q:$Q,MATCH(AB12,$C:$C,FALSE)) -> 9200006869 | AH12: =IFERROR(INDEX($S:$S,MATCH(AB12,$C:$C,FALSE)),"") | AI12: =IFERROR(INDEX($T:$T,MATCH(AB12,$C:$C,FALSE)),"") | AJ12: =INDEX($W:$W,MATCH(AB12,$C:$C,FALSE)) -> GMI-0018572 | AK12: =IFERROR(INDEX($X:$X,MATCH(AB12,$C:$C,FALSE)),"") -> 45358 | AL12: =INDEX($O:$O,MATCH(AF12,$N:$N,FALSE),"") -> DONE FROM BC | AM12: =INDEX($Y:$Y,MATCH(AB12,$C:$C,FALSE)) -> 45412
A13: 6 | B13: 45340 | C13: GMIAMMPIK/2024/02/007 | D13: 11L-3024 | E13: =VLOOKUP(D13,MP!$A$1:$C$14184,2,0) -> LED FLood Light 6 Eyes 18 Watt 10-30 VDC | F13: 2 | G13: PCS | H13: PLTAM15 | I13: =IFERROR(INDEX(POP!$I:$I,MATCH(H13,POP!$G:$G,0)),"general") -> general | J13: =IFERROR(INDEX(POP!$E:$E,MATCH(H13,POP!$G:$G,0)),"general") -> general | K13: COMMISIONING UNIT | L13: FANDY | M13: RESTU | N13: 200000661838 | O13: DONE FROM BC | P13: =B13 -> 45340 | Q13: 9200007063 | U13: DO 22394 | V13: 45325 | W13: GMI-0018571 | X13: 45358 | Y13: 45412 | AA13: 6 | AB13: GMIAMMPIK/2024/02/007 | AC13: =IFERROR(INDEX($B:$B,MATCH(AB13,$C:$C,FALSE)),"") -> 45340 | AD13: =INDEX($U:$U,MATCH(AB13,$C:$C,FALSE)) -> DO 22394 | AE13: =IFERROR(INDEX($V:$V,MATCH(AB13,$C:$C,FALSE)),"") -> 45325 | AF13: =IFERROR(INDEX($N:$N,MATCH(AB13,$C:$C,FALSE)),"") -> 200000661838 | AG13: =INDEX($Q:$Q,MATCH(AB13,$C:$C,FALSE)) -> 9200007063 | AH13: =IFERROR(INDEX($S:$S,MATCH(AB13,$C:$C,FALSE)),"") | AI13: =IFERROR(INDEX($T:$T,MATCH(AB13,$C:$C,FALSE)),"") | AJ13: =INDEX($W:$W,MATCH(AB13,$C:$C,FALSE)) -> GMI-0018571 | AK13: =IFERROR(INDEX($X:$X,MATCH(AB13,$C:$C,FALSE)),"") -> 45358 | AL13: =INDEX($O:$O,MATCH(AF13,$N:$N,FALSE),"") -> DONE FROM BC | AM13: =INDEX($Y:$Y,MATCH(AB13,$C:$C,FALSE)) -> 45412
A14: =A13+1 -> 7 | B14: 45340 | C14: GMIAMMPIK/2024/02/008 | D14: 11L-3024 | E14: =VLOOKUP(D14,MP!$A$1:$C$14184,2,0) -> LED FLood Light 6 Eyes 18 Watt 10-30 VDC | F14: 2 | G14: PCS | H14: PLTAM15 | I14: =IFERROR(INDEX(POP!$I:$I,MATCH(H14,POP!$G:$G,0)),"general") -> general | J14: =IFERROR(INDEX(POP!$E:$E,MATCH(H14,POP!$G:$G,0)),"general") -> general | K14: COMMISIONING UNIT | L14: FANDY | M14: RESTU | N14: 200000661851 | O14: DONE FROM BC | P14: =B14 -> 45340 | Q14: 9200007064 | U14: DO 22384 | V14: 45325 | W14: GMI-0018570 | X14: 45358 | Y14: 45412 | AA14: 7 | AB14: GMIAMMPIK/2024/02/008 | AC14: =IFERROR(INDEX($B:$B,MATCH(AB14,$C:$C,FALSE)),"") -> 45340 | AD14: =INDEX($U:$U,MATCH(AB14,$C:$C,FALSE)) -> DO 22384 | AE14: =IFERROR(INDEX($V:$V,MATCH(AB14,$C:$C,FALSE)),"") -> 45325 | AF14: =IFERROR(INDEX($N:$N,MATCH(AB14,$C:$C,FALSE)),"") -> 200000661851 | AG14: =INDEX($Q:$Q,MATCH(AB14,$C:$C,FALSE)) -> 9200007064 | AH14: =IFERROR(INDEX($S:$S,MATCH(AB14,$C:$C,FALSE)),"") | AI14: =IFERROR(INDEX($T:$T,MATCH(AB14,$C:$C,FALSE)),"") | AJ14: =INDEX($W:$W,MATCH(AB14,$C:$C,FALSE)) -> GMI-0018570 | AK14: =IFERROR(INDEX($X:$X,MATCH(AB14,$C:$C,FALSE)),"") -> 45358 | AL14: =INDEX($O:$O,MATCH(AF14,$N:$N,FALSE),"") -> DONE FROM BC | AM14: =INDEX($Y:$Y,MATCH(AB14,$C:$C,FALSE)) -> 45412
A15: =A14+1 -> 8 | B15: 45340 | C15: GMIAMMPIK/2024/02/009 | D15: 11L-3024 | E15: =VLOOKUP(D15,MP!$A$1:$C$14184,2,0) -> LED FLood Light 6 Eyes 18 Watt 10-30 VDC | F15: 2 | G15: PCS | H15: PLTAM15 | I15: =IFERROR(INDEX(POP!$I:$I,MATCH(H15,POP!$G:$G,0)),"general") -> general | J15: =IFERROR(INDEX(POP!$E:$E,MATCH(H15,POP!$G:$G,0)),"general") -> general | K15: COMMISIONING UNIT | L15: FANDY | M15: RESTU | N15: 200000661857 | O15: DONE FROM BC | P15: =B15 -> 45340 | Q15: 9200007065 | U15: DO 22382 | V15: 45325 | W15: GMI-0018569 | X15: 45358 | Y15: 45412 | AA15: 8 | AB15: GMIAMMPIK/2024/02/009 | AC15: =IFERROR(INDEX($B:$B,MATCH(AB15,$C:$C,FALSE)),"") -> 45340 | AD15: =INDEX($U:$U,MATCH(AB15,$C:$C,FALSE)) -> DO 22382 | AE15: =IFERROR(INDEX($V:$V,MATCH(AB15,$C:$C,FALSE)),"") -> 45325 | AF15: =IFERROR(INDEX($N:$N,MATCH(AB15,$C:$C,FALSE)),"") -> 200000661857 | AG15: =INDEX($Q:$Q,MATCH(AB15,$C:$C,FALSE)) -> 9200007065 | AH15: =IFERROR(INDEX($S:$S,MATCH(AB15,$C:$C,FALSE)),"") | AI15: =IFERROR(INDEX($T:$T,MATCH(AB15,$C:$C,FALSE)),"") | AJ15: =INDEX($W:$W,MATCH(AB15,$C:$C,FALSE)) -> GMI-0018569 | AK15: =IFERROR(INDEX($X:$X,MATCH(AB15,$C:$C,FALSE)),"") -> 45358 | AL15: =INDEX($O:$O,MATCH(AF15,$N:$N,FALSE),"") -> DONE FROM BC | AM15: =INDEX($Y:$Y,MATCH(AB15,$C:$C,FALSE)) -> 45412
A16: =A15+1 -> 9 | B16: 45345 | C16: GMIAMMPIK/2024/02/010 | D16: 14L-0160 | E16: =VLOOKUP(D16,MP!$A$1:$C$14184,2,0) -> Compressor Assy CAT 24V | F16: 1 | G16: PCS | H16: PLTAM15 | I16: =IFERROR(INDEX(POP!$I:$I,MATCH(H16,POP!$G:$G,0)),"general") -> general | J16: =IFERROR(INDEX(POP!$E:$E,MATCH(H16,POP!$G:$G,0)),"general") -> general | K16: CONSUMABLE PIK | L16: FANDY | M16: RESTU | N16: 200000665434 | O16: DONE FROM BC | P16: =B16 -> 45345 | Q16: 9200007301 | U16: DO 22381 | V16: 45325 | W16: GMI-0018568 | X16: 45358 | Y16: 45412 | AA16: 9 | AB16: GMIAMMPIK/2024/02/010 | AC16: =IFERROR(INDEX($B:$B,MATCH(AB16,$C:$C,FALSE)),"") -> 45345 | AD16: =INDEX($U:$U,MATCH(AB16,$C:$C,FALSE)) -> DO 22381 | AE16: =IFERROR(INDEX($V:$V,MATCH(AB16,$C:$C,FALSE)),"") -> 45325 | AF16: =IFERROR(INDEX($N:$N,MATCH(AB16,$C:$C,FALSE)),"") -> 200000665434 | AG16: =INDEX($Q:$Q,MATCH(AB16,$C:$C,FALSE)) -> 9200007301 | AH16: =IFERROR(INDEX($S:$S,MATCH(AB16,$C:$C,FALSE)),"") | AI16: =IFERROR(INDEX($T:$T,MATCH(AB16,$C:$C,FALSE)),"") | AJ16: =INDEX($W:$W,MATCH(AB16,$C:$C,FALSE)) -> GMI-0018568 | AK16: =IFERROR(INDEX($X:$X,MATCH(AB16,$C:$C,FALSE)),"") -> 45358 | AL16: =INDEX($O:$O,MATCH(AF16,$N:$N,FALSE),"") -> DONE FROM BC | AM16: =INDEX($Y:$Y,MATCH(AB16,$C:$C,FALSE)) -> 45412
A17: =A16+1 -> 10 | B17: 01 Maret 2024 | C17: GMIAMMPIK/2024/03/011 | D17: 11L-3024 | E17: =VLOOKUP(D17,MP!$A$1:$C$14184,2,0) -> LED FLood Light 6 Eyes 18 Watt 10-30 VDC | F17: 2 | G17: PCS | H17: PLTAM15 | I17: =IFERROR(INDEX(POP!$I:$I,MATCH(H17,POP!$G:$G,0)),"general") -> general | J17: =IFERROR(INDEX(POP!$E:$E,MATCH(H17,POP!$G:$G,0)),"general") -> general | K17: CONSUMABLE PIK | L17: FANDY | M17: RESTU | N17: 260000019088 | O17: DONE FROM BC | P17: =B17 -> 01 Maret 2024 | Q17: 9200007625 | R17: 44992 | U17: DO 22814 | V17: 16/3/2024 | W17: GMI-0018838 | X17: 45370 | Y17: 45412 | AA17: 10 | AB17: GMIAMMPIK/2024/03/011 | AC17: =IFERROR(INDEX($B:$B,MATCH(AB17,$C:$C,FALSE)),"") -> 01 Maret 2024 | AD17: =INDEX($U:$U,MATCH(AB17,$C:$C,FALSE)) -> DO 22814 | AE17: =IFERROR(INDEX($V:$V,MATCH(AB17,$C:$C,FALSE)),"") -> 16/3/2024 | AF17: =IFERROR(INDEX($N:$N,MATCH(AB17,$C:$C,FALSE)),"") -> 260000019088 | AG17: =INDEX($Q:$Q,MATCH(AB17,$C:$C,FALSE)) -> 9200007625 | AH17: =IFERROR(INDEX($S:$S,MATCH(AB17,$C:$C,FALSE)),"") | AI17: =IFERROR(INDEX($T:$T,MATCH(AB17,$C:$C,FALSE)),"") | AJ17: =INDEX($W:$W,MATCH(AB17,$C:$C,FALSE)) -> GMI-0018838 | AK17: =IFERROR(INDEX($X:$X,MATCH(AB17,$C:$C,FALSE)),"") -> 45370 | AL17: =INDEX($O:$O,MATCH(AF17,$N:$N,FALSE),"") -> DONE FROM BC | AM17: =INDEX($Y:$Y,MATCH(AB17,$C:$C,FALSE)) -> 45412
A18: =A17+1 -> 11 | B18: 01 Maret 2024 | C18: GMIAMMPIK/2024/03/012 | D18: 11L-3024 | E18: =VLOOKUP(D18,MP!$A$1:$C$14184,2,0) -> LED FLood Light 6 Eyes 18 Watt 10-30 VDC | F18: 6 | G18: PCS | H18: PLTAM15 | I18: =IFERROR(INDEX(POP!$I:$I,MATCH(H18,POP!$G:$G,0)),"general") -> general | J18: =IFERROR(INDEX(POP!$E:$E,MATCH(H18,POP!$G:$G,0)),"general") -> general | K18: CONSUMABLE PIK | L18: FANDY | M18: RESTU | N18: 200000667740 | O18: DONE FROM BC | P18: =B18 -> 01 Maret 2024 | Q18: 9200007626 | R18: 44992 | U18: DO 22815 | V18: 16/3/2024 | W18: GMI-0018837 | X18: 45370 | Y18: 45412 | AA18: 11 | AB18: GMIAMMPIK/2024/03/012 | AC18: =IFERROR(INDEX($B:$B,MATCH(AB18,$C:$C,FALSE)),"") -> 01 Maret 2024 | AD18: =INDEX($U:$U,MATCH(AB18,$C:$C,FALSE)) -> DO 22815 | AE18: =IFERROR(INDEX($V:$V,MATCH(AB18,$C:$C,FALSE)),"") -> 16/3/2024 | AF18: =IFERROR(INDEX($N:$N,MATCH(AB18,$C:$C,FALSE)),"") -> 200000667740 | AG18: =INDEX($Q:$Q,MATCH(AB18,$C:$C,FALSE)) -> 9200007626 | AH18: =IFERROR(INDEX($S:$S,MATCH(AB18,$C:$C,FALSE)),"") | AI18: =IFERROR(INDEX($T:$T,MATCH(AB18,$C:$C,FALSE)),"") | AJ18: =INDEX($W:$W,MATCH(AB18,$C:$C,FALSE)) -> GMI-0018837 | AK18: =IFERROR(INDEX($X:$X,MATCH(AB18,$C:$C,FALSE)),"") -> 45370 | AL18: =INDEX($O:$O,MATCH(AF18,$N:$N,FALSE),"") -> DONE FROM BC | AM18: =INDEX($Y:$Y,MATCH(AB18,$C:$C,FALSE)) -> 45412
A19: =A18+1 -> 12 | B19: 03 Maret 2024 | C19: GMIAMMPIK/2024/03/013 | D19: 11L-3024 | E19: =VLOOKUP(D19,MP!$A$1:$C$14184,2,0) -> LED FLood Light 6 Eyes 18 Watt 10-30 VDC | F19: 2 | G19: PCS | H19: PLTAM15 | I19: =IFERROR(INDEX(POP!$I:$I,MATCH(H19,POP!$G:$G,0)),"general") -> general | J19: =IFERROR(INDEX(POP!$E:$E,MATCH(H19,POP!$G:$G,0)),"general") -> general | K19: CONSUMABLE PIK | L19: FANDY | M19: RESTU | N19: 200000668254 | O19: DONE FROM BC | P19: =B19 -> 03 Maret 2024 | Q19: 7000146638 | R19: 44992 | U19: DO 22816 | V19: 16/3/2024 | W19: GMI-0018836 | X19: 45370 | Y19: 45412 | AA19: 12 | AB19: GMIAMMPIK/2024/03/013 | AC19: =IFERROR(INDEX($B:$B,MATCH(AB19,$C:$C,FALSE)),"") -> 03 Maret 2024 | AD19: =INDEX($U:$U,MATCH(AB19,$C:$C,FALSE)) -> DO 22816 | AE19: =IFERROR(INDEX($V:$V,MATCH(AB19,$C:$C,FALSE)),"") -> 16/3/2024 | AF19: =IFERROR(INDEX($N:$N,MATCH(AB19,$C:$C,FALSE)),"") -> 200000668254 | AG19: =INDEX($Q:$Q,MATCH(AB19,$C:$C,FALSE)) -> 7000146638 | AH19: =IFERROR(INDEX($S:$S,MATCH(AB19,$C:$C,FALSE)),"") | AI19: =IFERROR(INDEX($T:$T,MATCH(AB19,$C:$C,FALSE)),"") | AJ19: =INDEX($W:$W,MATCH(AB19,$C:$C,FALSE)) -> GMI-0018836 | AK19: =IFERROR(INDEX($X:$X,MATCH(AB19,$C:$C,FALSE)),"") -> 45370 | AL19: =INDEX($O:$O,MATCH(AF19,$N:$N,FALSE),"") -> DONE FROM BC | AM19: =INDEX($Y:$Y,MATCH(AB19,$C:$C,FALSE)) -> 45412
A20: =A19+1 -> 13 | B20: 4 Maret 2024 | C20: GMIAMMPIK/2024/03/014 | D20: 11L-3024 | E20: =VLOOKUP(D20,MP!$A$1:$C$14184,2,0) -> LED FLood Light 6 Eyes 18 Watt 10-30 VDC | F20: 4 | G20: PCS | H20: PLTAM15 | I20: =IFERROR(INDEX(POP!$I:$I,MATCH(H20,POP!$G:$G,0)),"general") -> general | J20: =IFERROR(INDEX(POP!$E:$E,MATCH(H20,POP!$G:$G,0)),"general") -> general | K20: CONSUMABLE PIK | L20: FANDY | M20: RESTU | N20: 200000668717 | O20: DONE FROM BC | P20: =B20 -> 4 Maret 2024 | Q20: 7000146657 | R20: 44992 | U20: DO 22817 | V20: 16/3/2024 | W20: GMI-0018835 | X20: 45370 | Y20: 45412 | AA20: 13 | AB20: GMIAMMPIK/2024/03/014 | AC20: =IFERROR(INDEX($B:$B,MATCH(AB20,$C:$C,FALSE)),"") -> 4 Maret 2024 | AD20: =INDEX($U:$U,MATCH(AB20,$C:$C,FALSE)) -> DO 22817 | AE20: =IFERROR(INDEX($V:$V,MATCH(AB20,$C:$C,FALSE)),"") -> 16/3/2024 | AF20: =IFERROR(INDEX($N:$N,MATCH(AB20,$C:$C,FALSE)),"") -> 200000668717 | AG20: =INDEX($Q:$Q,MATCH(AB20,$C:$C,FALSE)) -> 7000146657 | AH20: =IFERROR(INDEX($S:$S,MATCH(AB20,$C:$C,FALSE)),"") | AI20: =IFERROR(INDEX($T:$T,MATCH(AB20,$C:$C,FALSE)),"") | AJ20: =INDEX($W:$W,MATCH(AB20,$C:$C,FALSE)) -> GMI-0018835 | AK20: =IFERROR(INDEX($X:$X,MATCH(AB20,$C:$C,FALSE)),"") -> 45370 | AL20: =INDEX($O:$O,MATCH(AF20,$N:$N,FALSE),"") -> DONE FROM BC | AM20: =INDEX($Y:$Y,MATCH(AB20,$C:$C,FALSE)) -> 45412
A21: =A20+1 -> 14 | B21: 07 Maret 2024 | C21: GMIAMMPIK/2024/03/015 | D21: 11L-3024 | E21: =VLOOKUP(D21,MP!$A$1:$C$14184,2,0) -> LED FLood Light 6 Eyes 18 Watt 10-30 VDC | F21: 2 | G21: PCS | H21: PLTAM15 | I21: =IFERROR(INDEX(POP!$I:$I,MATCH(#REF!,POP!$G:$G,0)),"general") -> general | J21: =IFERROR(INDEX(POP!$E:$E,MATCH(#REF!,POP!$G:$G,0)),"general") -> general | K21: CONSUMABLE PIK | L21: FANDY | M21: NUGROHO | N21: 200000669795 | O21: DONE FROM BC | P21: =B21 -> 07 Maret 2024 | Q21: 9200007868 | R21: 45370 | U21: DO 23013 | V21: 25/3/2024 | W21: GMI-0019168 | X21: 45381 | Y21: 45429 | AA21: 14 | AB21: GMIAMMPIK/2024/03/015 | AC21: =IFERROR(INDEX($B:$B,MATCH(AB21,$C:$C,FALSE)),"") -> 07 Maret 2024 | AD21: =INDEX($U:$U,MATCH(AB21,$C:$C,FALSE)) -> DO 23013 | AE21: =IFERROR(INDEX($V:$V,MATCH(AB21,$C:$C,FALSE)),"") -> 25/3/2024 | AF21: =IFERROR(INDEX($N:$N,MATCH(AB21,$C:$C,FALSE)),"") -> 200000669795 | AG21: =INDEX($Q:$Q,MATCH(AB21,$C:$C,FALSE)) -> 9200007868 | AH21: =IFERROR(INDEX($S:$S,MATCH(AB21,$C:$C,FALSE)),"") | AI21: =IFERROR(INDEX($T:$T,MATCH(AB21,$C:$C,FALSE)),"") | AJ21: =INDEX($W:$W,MATCH(AB21,$C:$C,FALSE)) -> GMI-0019168 | AK21: =IFERROR(INDEX($X:$X,MATCH(AB21,$C:$C,FALSE)),"") -> 45381 | AL21: =INDEX($O:$O,MATCH(AF21,$N:$N,FALSE),"") -> DONE FROM BC | AM21: =INDEX($Y:$Y,MATCH(AB21,$C:$C,FALSE)) -> 45429
A22: =A21+1 -> 15 | B22: 07 Maret 2024 | C22: GMIAMMPIK/2024/03/016 | D22: 11L-3024 | E22: =VLOOKUP(D22,MP!$A$1:$C$14184,2,0) -> LED FLood Light 6 Eyes 18 Watt 10-30 VDC | F22: 1 | G22: PCS | H22: PLTAM15 | I22: =IFERROR(INDEX(POP!$I:$I,MATCH(#REF!,POP!$G:$G,0)),"general") -> general | J22: =IFERROR(INDEX(POP!$E:$E,MATCH(#REF!,POP!$G:$G,0)),"general") -> general | K22: CONSUMABLE PIK | L22: FANDY | M22: NUGROHO | N22: 200000669870 | O22: DONE FROM BC | P22: =B22 -> 07 Maret 2024 | Q22: 9200007887 | R22: 45370 | U22: DO 23010 | V22: 25/3/2024 | W22: GMI-0019165 | X22: 45381 | Y22: 45429 | AA22: 15 | AB22: GMIAMMPIK/2024/03/016 | AC22: =IFERROR(INDEX($B:$B,MATCH(AB22,$C:$C,FALSE)),"") -> 07 Maret 2024 | AD22: =INDEX($U:$U,MATCH(AB22,$C:$C,FALSE)) -> DO 23010 | AE22: =IFERROR(INDEX($V:$V,MATCH(AB22,$C:$C,FALSE)),"") -> 25/3/2024 | AF22: =IFERROR(INDEX($N:$N,MATCH(AB22,$C:$C,FALSE)),"") -> 200000669870 | AG22: =INDEX($Q:$Q,MATCH(AB22,$C:$C,FALSE)) -> 9200007887 | AH22: =IFERROR(INDEX($S:$S,MATCH(AB22,$C:$C,FALSE)),"") | AI22: =IFERROR(INDEX($T:$T,MATCH(AB22,$C:$C,FALSE)),"") | AJ22: =INDEX($W:$W,MATCH(AB22,$C:$C,FALSE)) -> GMI-0019165 | AK22: =IFERROR(INDEX($X:$X,MATCH(AB22,$C:$C,FALSE)),"") -> 45381 | AL22: =INDEX($O:$O,MATCH(AF22,$N:$N,FALSE),"") -> DONE FROM BC | AM22: =INDEX($Y:$Y,MATCH(AB22,$C:$C,FALSE)) -> 45429
A23: =A22+1 -> 16 | B23: 16 Maret 2024 | C23: GMIAMMPIK/2024/03/017 | D23: 11L-3024 | E23: =VLOOKUP(D23,MP!$A$1:$C$14184,2,0) -> LED FLood Light 6 Eyes 18 Watt 10-30 VDC | F23: 1 | G23: PCS | H23: WP509 | I23: =IFERROR(INDEX(POP!$I:$I,MATCH(#REF!,POP!$G:$G,0)),"general") -> general | J23: =IFERROR(INDEX(POP!$E:$E,MATCH(#REF!,POP!$G:$G,0)),"general") -> general | K23: CONSUMABLE PIK | L23: FANDY | M23: NUGROHO | N23: 200000672951 | O23: DONE FROM BC | P23: =B23 -> 16 Maret 2024 | Q23: 7000147720 | R23: 45370 | U23: DO 23011 | V23: 25/3/2024 | W23: GMI-0019166 | X23: 45381 | Y23: 45429 | AA23: =AA22+1 -> 16 | AB23: GMIAMMPIK/2024/03/017 | AC23: =IFERROR(INDEX($B:$B,MATCH(AB23,$C:$C,FALSE)),"") -> 16 Maret 2024 | AD23: =INDEX($U:$U,MATCH(AB23,$C:$C,FALSE)) -> DO 23011 | AE23: =IFERROR(INDEX($V:$V,MATCH(AB23,$C:$C,FALSE)),"") -> 25/3/2024 | AF23: =IFERROR(INDEX($N:$N,MATCH(AB23,$C:$C,FALSE)),"") -> 200000672951 | AG23: =INDEX($Q:$Q,MATCH(AB23,$C:$C,FALSE)) -> 7000147720 | AH23: =IFERROR(INDEX($S:$S,MATCH(AB23,$C:$C,FALSE)),"") | AI23: =IFERROR(INDEX($T:$T,MATCH(AB23,$C:$C,FALSE)),"") | AJ23: =INDEX($W:$W,MATCH(AB23,$C:$C,FALSE)) -> GMI-0019166 | AK23: =IFERROR(INDEX($X:$X,MATCH(AB23,$C:$C,FALSE)),"") -> 45381 | AL23: =INDEX($O:$O,MATCH(AF23,$N:$N,FALSE),"") -> DONE FROM BC | AM23: =INDEX($Y:$Y,MATCH(AB23,$C:$C,FALSE)) -> 45429
A24: =A23+1 -> 17 | B24: 18 Maret 2024 | C24: GMIAMMPIK/2024/03/018 | D24: 11L-3024 | E24: =VLOOKUP(D24,MP!$A$1:$C$14184,2,0) -> LED FLood Light 6 Eyes 18 Watt 10-30 VDC | F24: 2 | G24: PCS | H24: PLTAM15 | I24: =IFERROR(INDEX(POP!$I:$I,MATCH(#REF!,POP!$G:$G,0)),"general") -> general | J24: =IFERROR(INDEX(POP!$E:$E,MATCH(#REF!,POP!$G:$G,0)),"general") -> general | K24: REPLACE WORKLAMP | L24: FANDY | M24: RESTU | N24: 200000673701 | O24: DONE FROM BC | P24: =B24 -> 18 Maret 2024 | Q24: 9200008333 | R24: 45370 | U24: DO 23012 | V24: 25/3/2024 | W24: GMI-0019167 | X24: 45381 | Y24: 45429 | AA24: =AA23+1 -> 17 | AB24: GMIAMMPIK/2024/03/018 | AC24: =IFERROR(INDEX($B:$B,MATCH(AB24,$C:$C,FALSE)),"") -> 18 Maret 2024 | AD24: =INDEX($U:$U,MATCH(AB24,$C:$C,FALSE)) -> DO 23012 | AE24: =IFERROR(INDEX($V:$V,MATCH(AB24,$C:$C,FALSE)),"") -> 25/3/2024 | AF24: =IFERROR(INDEX($N:$N,MATCH(AB24,$C:$C,FALSE)),"") -> 200000673701 | AG24: =INDEX($Q:$Q,MATCH(AB24,$C:$C,FALSE)) -> 9200008333 | AH24: =IFERROR(INDEX($S:$S,MATCH(AB24,$C:$C,FALSE)),"") | AI24: =IFERROR(INDEX($T:$T,MATCH(AB24,$C:$C,FALSE)),"") | AJ24: =INDEX($W:$W,MATCH(AB24,$C:$C,FALSE)) -> GMI-0019167 | AK24: =IFERROR(INDEX($X:$X,MATCH(AB24,$C:$C,FALSE)),"") -> 45381 | AL24: =INDEX($O:$O,MATCH(AF24,$N:$N,FALSE),"") -> DONE FROM BC | AM24: =INDEX($Y:$Y,MATCH(AB24,$C:$C,FALSE)) -> 45429
A25: =A24+1 -> 18 | B25: 19 Maret 2024 | C25: GMIAMMPIK/2024/03/019 | D25: 11L-3024 | E25: =VLOOKUP(D25,MP!$A$1:$C$14184,2,0) -> LED FLood Light 6 Eyes 18 Watt 10-30 VDC | F25: 1 | G25: PCS | H25: PLTAM15 | I25: =IFERROR(INDEX(POP!$I:$I,MATCH(H25,POP!$G:$G,0)),"general") -> general | J25: =IFERROR(INDEX(POP!$E:$E,MATCH(H25,POP!$G:$G,0)),"general") -> general | K25: CONSUMABLE PIK | L25: FANDY | M25: RESTU | N25: 200000671011 | O25: DONE FROM BC | P25: =B25 -> 19 Maret 2024 | Q25: 7000147258 | R25: 45370 | U25: DO 23014 | V25: 25/3/2024 | W25: GMI-0019169 | X25: 45381 | Y25: 45429 | AA25: =AA24+1 -> 18 | AB25: GMIAMMPIK/2024/03/019 | AC25: =IFERROR(INDEX($B:$B,MATCH(AB25,$C:$C,FALSE)),"") -> 19 Maret 2024 | AD25: =INDEX($U:$U,MATCH(AB25,$C:$C,FALSE)) -> DO 23014 | AE25: =IFERROR(INDEX($V:$V,MATCH(AB25,$C:$C,FALSE)),"") -> 25/3/2024 | AF25: =IFERROR(INDEX($N:$N,MATCH(AB25,$C:$C,FALSE)),"") -> 200000671011 | AG25: =INDEX($Q:$Q,MATCH(AB25,$C:$C,FALSE)) -> 7000147258 | AH25: =IFERROR(INDEX($S:$S,MATCH(AB25,$C:$C,FALSE)),"") | AI25: =IFERROR(INDEX($T:$T,MATCH(AB25,$C:$C,FALSE)),"") | AJ25: =INDEX($W:$W,MATCH(AB25,$C:$C,FALSE)) -> GMI-0019169 | AK25: =IFERROR(INDEX($X:$X,MATCH(AB25,$C:$C,FALSE)),"") -> 45381 | AL25: =INDEX($O:$O,MATCH(AF25,$N:$N,FALSE),"") -> DONE FROM BC | AM25: =INDEX($Y:$Y,MATCH(AB25,$C:$C,FALSE)) -> 45429
A26: =A25+1 -> 19 | B26: 19 Maret 2024 | C26: GMIAMMPIK/2024/03/020 | D26: 11L-3024 | E26: =VLOOKUP(D26,MP!$A$1:$C$14184,2,0) -> LED FLood Light 6 Eyes 18 Watt 10-30 VDC | F26: 2 | G26: PCS | H26: D5834 | I26: =IFERROR(INDEX(POP!$I:$I,MATCH(H26,POP!$G:$G,0)),"general") -> general | J26: =IFERROR(INDEX(POP!$E:$E,MATCH(H26,POP!$G:$G,0)),"general") -> general | K26: REPLACE WORKLAMP | L26: FANDY | M26: FAUZI | N26: 200000673952 | O26: DONE FROM BC | P26: =B26 -> 19 Maret 2024 | Q26: 9200008360 | R26: 45378 | U26: DO 23085 | V26: 28/3/2024 | W26: GMI-0019268 | X26: 45386 | Y26: 45429 | AA26: =AA25+1 -> 19 | AB26: GMIAMMPIK/2024/03/020 | AC26: =IFERROR(INDEX($B:$B,MATCH(AB26,$C:$C,FALSE)),"") -> 19 Maret 2024 | AD26: =INDEX($U:$U,MATCH(AB26,$C:$C,FALSE)) -> DO 23085 | AE26: =IFERROR(INDEX($V:$V,MATCH(AB26,$C:$C,FALSE)),"") -> 28/3/2024 | AF26: =IFERROR(INDEX($N:$N,MATCH(AB26,$C:$C,FALSE)),"") -> 200000673952 | AG26: =INDEX($Q:$Q,MATCH(AB26,$C:$C,FALSE)) -> 9200008360 | AH26: =IFERROR(INDEX($S:$S,MATCH(AB26,$C:$C,FALSE)),"") | AI26: =IFERROR(INDEX($T:$T,MATCH(AB26,$C:$C,FALSE)),"") | AJ26: =INDEX($W:$W,MATCH(AB26,$C:$C,FALSE)) -> GMI-0019268 | AK26: =IFERROR(INDEX($X:$X,MATCH(AB26,$C:$C,FALSE)),"") -> 45386 | AL26: =INDEX($O:$O,MATCH(AF26,$N:$N,FALSE),"") -> DONE FROM BC | AM26: =INDEX($Y:$Y,MATCH(AB26,$C:$C,FALSE)) -> 45429
A27: =A26+1 -> 20 | B27: 21 Maret 2024 | C27: GMIAMMPIK/2024/03/021 | D27: 11L-3024 | E27: =VLOOKUP(D27,MP!$A$1:$C$14184,2,0) -> LED FLood Light 6 Eyes 18 Watt 10-30 VDC | F27: 1 | G27: PCS | H27: PLTAM15 | I27: =IFERROR(INDEX(POP!$I:$I,MATCH(H27,POP!$G:$G,0)),"general") -> general | J27: =IFERROR(INDEX(POP!$E:$E,MATCH(H27,POP!$G:$G,0)),"general") -> general | K27: REPLACE WORKLAMP | L27: FANDY | M27: FAUZI | N27: 200000674807 | O27: DONE FROM BC | P27: =B27 -> 21 Maret 2024 | Q27: 9200008514 | R27: 45378 | U27: DO 23079 | V27: 28/3/2024 | W27: GMI-0019266 | X27: 45386 | Y27: 45429 | AA27: =AA26+1 -> 20 | AB27: GMIAMMPIK/2024/03/021 | AC27: =IFERROR(INDEX($B:$B,MATCH(AB27,$C:$C,FALSE)),"") -> 21 Maret 2024 | AD27: =INDEX($U:$U,MATCH(AB27,$C:$C,FALSE)) -> DO 23079 | AE27: =IFERROR(INDEX($V:$V,MATCH(AB27,$C:$C,FALSE)),"") -> 28/3/2024 | AF27: =IFERROR(INDEX($N:$N,MATCH(AB27,$C:$C,FALSE)),"") -> 200000674807 | AG27: =INDEX($Q:$Q,MATCH(AB27,$C:$C,FALSE)) -> 9200008514 | AH27: =IFERROR(INDEX($S:$S,MATCH(AB27,$C:$C,FALSE)),"") | AI27: =IFERROR(INDEX($T:$T,MATCH(AB27,$C:$C,FALSE)),"") | AJ27: =INDEX($W:$W,MATCH(AB27,$C:$C,FALSE)) -> GMI-0019266 | AK27: =IFERROR(INDEX($X:$X,MATCH(AB27,$C:$C,FALSE)),"") -> 45386 | AL27: =INDEX($O:$O,MATCH(AF27,$N:$N,FALSE),"") -> DONE FROM BC | AM27: =INDEX($Y:$Y,MATCH(AB27,$C:$C,FALSE)) -> 45429
A28: =A27+1 -> 21 | B28: 25 Maret 2024 | C28: GMIAMMPIK/2024/03/022 | D28: 11L-3024 | E28: =VLOOKUP(D28,MP!$A$1:$C$14184,2,0) -> LED FLood Light 6 Eyes 18 Watt 10-30 VDC | F28: 1 | G28: PCS | H28: G5816 | I28: =IFERROR(INDEX(POP!$I:$I,MATCH(H28,POP!$G:$G,0)),"general") -> general | J28: =IFERROR(INDEX(POP!$E:$E,MATCH(H28,POP!$G:$G,0)),"general") -> general | K28: REPLACE WORKLAMP | L28: FANDY | M28: FAUZI | N28: 200000676203 | O28: DONE FROM BC | P28: =B28 -> 25 Maret 2024 | Q28: 9200008672 | R28: 45378 | U28: DO 23083 | V28: 28/3/2024 | W28: GMI-0019267 | X28: 45386 | Y28: 45429 | AA28: =AA27+1 -> 21 | AB28: GMIAMMPIK/2024/03/022 | AC28: =IFERROR(INDEX($B:$B,MATCH(AB28,$C:$C,FALSE)),"") -> 25 Maret 2024 | AD28: =INDEX($U:$U,MATCH(AB28,$C:$C,FALSE)) -> DO 23083 | AE28: =IFERROR(INDEX($V:$V,MATCH(AB28,$C:$C,FALSE)),"") -> 28/3/2024 | AF28: =IFERROR(INDEX($N:$N,MATCH(AB28,$C:$C,FALSE)),"") -> 200000676203 | AG28: =INDEX($Q:$Q,MATCH(AB28,$C:$C,FALSE)) -> 9200008672 | AH28: =IFERROR(INDEX($S:$S,MATCH(AB28,$C:$C,FALSE)),"") | AI28: =IFERROR(INDEX($T:$T,MATCH(AB28,$C:$C,FALSE)),"") | AJ28: =INDEX($W:$W,MATCH(AB28,$C:$C,FALSE)) -> GMI-0019267 | AK28: =IFERROR(INDEX($X:$X,MATCH(AB28,$C:$C,FALSE)),"") -> 45386 | AL28: =INDEX($O:$O,MATCH(AF28,$N:$N,FALSE),"") -> DONE FROM BC | AM28: =INDEX($Y:$Y,MATCH(AB28,$C:$C,FALSE)) -> 45429
A29: =A28+1 -> 22 | B29: 45385 | C29: GMIAMMPIK/2024/04/023 | D29: 11L-3024 | E29: =VLOOKUP(D29,MP!$A$1:$C$14184,2,0) -> LED FLood Light 6 Eyes 18 Watt 10-30 VDC | F29: 1 | G29: PCS | H29: W52606 | I29: =IFERROR(INDEX(POP!$I:$I,MATCH(H29,POP!$G:$G,0)),"general") -> general | J29: =IFERROR(INDEX(POP!$E:$E,MATCH(H29,POP!$G:$G,0)),"general") -> general | K29: REPLACE WORKLAMP | L29: FANDY | M29: FAUZI | N29: 200000679595 | O29: DONE FROM BC | P29: =B29 -> 45385 | Q29: 9200009206 | R29: 45400 | U29: DO 23492 | V29: 26/4/2024 | W29: GMI-0019594 | X29: 45408 | Y29: 45457 | AA29: =AA28+1 -> 22 | AB29: GMIAMMPIK/2024/04/023 | AC29: =IFERROR(INDEX($B:$B,MATCH(AB29,$C:$C,FALSE)),"") -> 45385 | AD29: =INDEX($U:$U,MATCH(AB29,$C:$C,FALSE)) -> DO 23492 | AE29: =IFERROR(INDEX($V:$V,MATCH(AB29,$C:$C,FALSE)),"") -> 26/4/2024 | AF29: =IFERROR(INDEX($N:$N,MATCH(AB29,$C:$C,FALSE)),"") -> 200000679595 | AG29: =INDEX($Q:$Q,MATCH(AB29,$C:$C,FALSE)) -> 9200009206 | AH29: =IFERROR(INDEX($S:$S,MATCH(AB29,$C:$C,FALSE)),"") | AI29: =IFERROR(INDEX($T:$T,MATCH(AB29,$C:$C,FALSE)),"") | AJ29: =INDEX($W:$W,MATCH(AB29,$C:$C,FALSE)) -> GMI-0019594 | AK29: =IFERROR(INDEX($X:$X,MATCH(AB29,$C:$C,FALSE)),"") -> 45408 | AL29: =INDEX($O:$O,MATCH(AF29,$N:$N,FALSE),"") -> DONE FROM BC | AM29: =INDEX($Y:$Y,MATCH(AB29,$C:$C,FALSE)) -> 45457
A30: =A29+1 -> 23 | B30: 45386 | C30: GMIAMMPIK/2024/04/024 | D30: 11L-3024 | E30: =VLOOKUP(D30,MP!$A$1:$C$14184,2,0) -> LED FLood Light 6 Eyes 18 Watt 10-30 VDC | F30: 1 | G30: PCS | H30: H57106 | I30: =IFERROR(INDEX(POP!$I:$I,MATCH(H30,POP!$G:$G,0)),"general") -> general | J30: =IFERROR(INDEX(POP!$E:$E,MATCH(H30,POP!$G:$G,0)),"general") -> general | K30: REPLACE WORKLAMP | L30: FANDY | M30: FAUZI | N30: 200000680006 | O30: DONE FROM BC | P30: =B30 -> 45386 | Q30: 7000149477 | R30: 45400 | U30: DO 23493 | V30: 26/4/2024 | W30: GMI-0019595 | X30: 45408 | Y30: 45457 | AA30: =AA29+1 -> 23 | AB30: GMIAMMPIK/2024/04/024 | AC30: =IFERROR(INDEX($B:$B,MATCH(AB30,$C:$C,FALSE)),"") -> 45386 | AD30: =INDEX($U:$U,MATCH(AB30,$C:$C,FALSE)) -> DO 23493 | AE30: =IFERROR(INDEX($V:$V,MATCH(AB30,$C:$C,FALSE)),"") -> 26/4/2024 | AF30: =IFERROR(INDEX($N:$N,MATCH(AB30,$C:$C,FALSE)),"") -> 200000680006 | AG30: =INDEX($Q:$Q,MATCH(AB30,$C:$C,FALSE)) -> 7000149477 | AH30: =IFERROR(INDEX($S:$S,MATCH(AB30,$C:$C,FALSE)),"") | AI30: =IFERROR(INDEX($T:$T,MATCH(AB30,$C:$C,FALSE)),"") | AJ30: =INDEX($W:$W,MATCH(AB30,$C:$C,FALSE)) -> GMI-0019595 | AK30: =IFERROR(INDEX($X:$X,MATCH(AB30,$C:$C,FALSE)),"") -> 45408 | AL30: =INDEX($O:$O,MATCH(AF30,$N:$N,FALSE),"") -> DONE FROM BC | AM30: =INDEX($Y:$Y,MATCH(AB30,$C:$C,FALSE)) -> 45457
A31: =A30+1 -> 24 | B31: 45386 | C31: GMIAMMPIK/2024/04/025 | D31: 11L-3024 | E31: =VLOOKUP(D31,MP!$A$1:$C$14184,2,0) -> LED FLood Light 6 Eyes 18 Watt 10-30 VDC | F31: 1 | G31: PCS | H31: DA4826PPA | I31: =IFERROR(INDEX(POP!$I:$I,MATCH(H31,POP!$G:$G,0)),"general") -> general | J31: =IFERROR(INDEX(POP!$E:$E,MATCH(H31,POP!$G:$G,0)),"general") -> general | K31: REPLACE WORKLAMP | L31: FANDY | M31: FAUZI | N31: 200000680007 | O31: DONE FROM BC | P31: =B31 -> 45386 | Q31: 7000149478 | R31: 45400 | U31: DO 23495 | V31: 26/4/2024 | W31: GMI-0019597 | X31: 45408 | Y31: 45457 | AA31: =AA30+1 -> 24 | AB31: GMIAMMPIK/2024/04/025 | AC31: =IFERROR(INDEX($B:$B,MATCH(AB31,$C:$C,FALSE)),"") -> 45386 | AD31: =INDEX($U:$U,MATCH(AB31,$C:$C,FALSE)) -> DO 23495 | AE31: =IFERROR(INDEX($V:$V,MATCH(AB31,$C:$C,FALSE)),"") -> 26/4/2024 | AF31: =IFERROR(INDEX($N:$N,MATCH(AB31,$C:$C,FALSE)),"") -> 200000680007 | AG31: =INDEX($Q:$Q,MATCH(AB31,$C:$C,FALSE)) -> 7000149478 | AH31: =IFERROR(INDEX($S:$S,MATCH(AB31,$C:$C,FALSE)),"") | AI31: =IFERROR(INDEX($T:$T,MATCH(AB31,$C:$C,FALSE)),"") | AJ31: =INDEX($W:$W,MATCH(AB31,$C:$C,FALSE)) -> GMI-0019597 | AK31: =IFERROR(INDEX($X:$X,MATCH(AB31,$C:$C,FALSE)),"") -> 45408 | AL31: =INDEX($O:$O,MATCH(AF31,$N:$N,FALSE),"") -> DONE FROM BC | AM31: =INDEX($Y:$Y,MATCH(AB31,$C:$C,FALSE)) -> 45457
A32: =A31+1 -> 25 | B32: 45395 | C32: GMIAMMPIK/2024/04/026 | D32: 11L-3024 | E32: =VLOOKUP(D32,MP!$A$1:$C$14184,2,0) -> LED FLood Light 6 Eyes 18 Watt 10-30 VDC | F32: 1 | G32: PCS | H32: G5816 | I32: =IFERROR(INDEX(POP!$I:$I,MATCH(H32,POP!$G:$G,0)),"general") -> general | J32: =IFERROR(INDEX(POP!$E:$E,MATCH(H32,POP!$G:$G,0)),"general") -> general | K32: REPLACE WORKLAMP | L32: FANDY | M32: FAUZI | N32: 200000682189 | O32: DONE FROM BC | P32: =B32 -> 45395 | Q32: 9200009515 | R32: 45400 | U32: DO 23494 | V32: 26/4/2024 | W32: GMI-0019596 | X32: 45408 | Y32: 45457 | AA32: =AA31+1 -> 25 | AB32: GMIAMMPIK/2024/04/026 | AC32: =IFERROR(INDEX($B:$B,MATCH(AB32,$C:$C,FALSE)),"") -> 45395 | AD32: =INDEX($U:$U,MATCH(AB32,$C:$C,FALSE)) -> DO 23494 | AE32: =IFERROR(INDEX($V:$V,MATCH(AB32,$C:$C,FALSE)),"") -> 26/4/2024 | AF32: =IFERROR(INDEX($N:$N,MATCH(AB32,$C:$C,FALSE)),"") -> 200000682189 | AG32: =INDEX($Q:$Q,MATCH(AB32,$C:$C,FALSE)) -> 9200009515 | AH32: =IFERROR(INDEX($S:$S,MATCH(AB32,$C:$C,FALSE)),"") | AI32: =IFERROR(INDEX($T:$T,MATCH(AB32,$C:$C,FALSE)),"") | AJ32: =INDEX($W:$W,MATCH(AB32,$C:$C,FALSE)) -> GMI-0019596 | AK32: =IFERROR(INDEX($X:$X,MATCH(AB32,$C:$C,FALSE)),"") -> 45408 | AL32: =INDEX($O:$O,MATCH(AF32,$N:$N,FALSE),"") -> DONE FROM BC | AM32: =INDEX($Y:$Y,MATCH(AB32,$C:$C,FALSE)) -> 45457
A33: =A32+1 -> 26 | B33: 45398 | C33: GMIAMMPIK/2024/04/027 | D33: 11L-3024 | E33: =VLOOKUP(D33,MP!$A$1:$C$14184,2,0) -> LED FLood Light 6 Eyes 18 Watt 10-30 VDC | F33: 1 | G33: PCS | H33: FT52610 | I33: =IFERROR(INDEX(POP!$I:$I,MATCH(H33,POP!$G:$G,0)),"general") -> general | J33: =IFERROR(INDEX(POP!$E:$E,MATCH(H33,POP!$G:$G,0)),"general") -> general | K33: REPLACE WORKLAMP | L33: FANDY | M33: RESTU | N33: 200000683408 | O33: DONE FROM BC | P33: =B33 -> 45398 | Q33: 7000150439 | R33: 45401 | U33: DO 23536 | V33: 29/4/2024 | W33: GMI-0019636 | X33: 45414 | Y33: 45457 | AA33: =AA32+1 -> 26 | AB33: GMIAMMPIK/2024/04/027 | AC33: =IFERROR(INDEX($B:$B,MATCH(AB33,$C:$C,FALSE)),"") -> 45398 | AD33: =INDEX($U:$U,MATCH(AB33,$C:$C,FALSE)) -> DO 23536 | AE33: =IFERROR(INDEX($V:$V,MATCH(AB33,$C:$C,FALSE)),"") -> 29/4/2024 | AF33: =IFERROR(INDEX($N:$N,MATCH(AB33,$C:$C,FALSE)),"") -> 200000683408 | AG33: =INDEX($Q:$Q,MATCH(AB33,$C:$C,FALSE)) -> 7000150439 | AH33: =IFERROR(INDEX($S:$S,MATCH(AB33,$C:$C,FALSE)),"") | AI33: =IFERROR(INDEX($T:$T,MATCH(AB33,$C:$C,FALSE)),"") | AJ33: =INDEX($W:$W,MATCH(AB33,$C:$C,FALSE)) -> GMI-0019636 | AK33: =IFERROR(INDEX($X:$X,MATCH(AB33,$C:$C,FALSE)),"") -> 45414 | AL33: =INDEX($O:$O,MATCH(AF33,$N:$N,FALSE),"") -> DONE FROM BC | AM33: =INDEX($Y:$Y,MATCH(AB33,$C:$C,FALSE)) -> 45457
A34: =A33+1 -> 27 | B34: 45400 | C34: GMIAMMPIK/2024/04/028 | D34: 11L-3024 | E34: =VLOOKUP(D34,MP!$A$1:$C$14184,2,0) -> LED FLood Light 6 Eyes 18 Watt 10-30 VDC | F34: 1 | G34: PCS | H34: VS25PPA | I34: =IFERROR(INDEX(POP!$I:$I,MATCH(H34,POP!$G:$G,0)),"general") -> general | J34: =IFERROR(INDEX(POP!$E:$E,MATCH(H34,POP!$G:$G,0)),"general") -> general | K34: REPLACE WORKLAMP | L34: FANDY | M34: FAUZI | N34: 200000684138 | O34: DONE FROM BC | P34: =B34 -> 45400 | Q34: 7000150576 | R34: 45401 | U34: DO 23538 | V34: 29/4/2024 | W34: GMI-0019637 | X34: 45414 | Y34: 45457 | AA34: =AA33+1 -> 27 | AB34: GMIAMMPIK/2024/04/028 | AC34: =IFERROR(INDEX($B:$B,MATCH(AB34,$C:$C,FALSE)),"") -> 45400 | AD34: =INDEX($U:$U,MATCH(AB34,$C:$C,FALSE)) -> DO 23538 | AE34: =IFERROR(INDEX($V:$V,MATCH(AB34,$C:$C,FALSE)),"") -> 29/4/2024 | AF34: =IFERROR(INDEX($N:$N,MATCH(AB34,$C:$C,FALSE)),"") -> 200000684138 | AG34: =INDEX($Q:$Q,MATCH(AB34,$C:$C,FALSE)) -> 7000150576 | AH34: =IFERROR(INDEX($S:$S,MATCH(AB34,$C:$C,FALSE)),"") | AI34: =IFERROR(INDEX($T:$T,MATCH(AB34,$C:$C,FALSE)),"") | AJ34: =INDEX($W:$W,MATCH(AB34,$C:$C,FALSE)) -> GMI-0019637 | AK34: =IFERROR(INDEX($X:$X,MATCH(AB34,$C:$C,FALSE)),"") -> 45414 | AL34: =INDEX($O:$O,MATCH(AF34,$N:$N,FALSE),"") -> DONE FROM BC | AM34: =INDEX($Y:$Y,MATCH(AB34,$C:$C,FALSE)) -> 45457
A35: =A34+1 -> 28 | B35: 45406 | C35: GMIAMMPIK/2024/04/029 | D35: 11L-3024 | E35: =VLOOKUP(D35,MP!$A$1:$C$14184,2,0) -> LED FLood Light 6 Eyes 18 Watt 10-30 VDC | F35: 2 | G35: PCS | H35: M53803 | I35: =IFERROR(INDEX(POP!$I:$I,MATCH(H35,POP!$G:$G,0)),"general") -> general | J35: =IFERROR(INDEX(POP!$E:$E,MATCH(H35,POP!$G:$G,0)),"general") -> general | K35: REPLACE WORKLAMP | L35: FANDY | M35: FAUZI | N35: 200000686439 | O35: DONE FROM BC | P35: =B35 -> 45406 | Q35: 7000151244 | R35: 45406 | U35: DO 23891 | V35: 16/5/2024 | W35: GMI-0020008 | X35: 45432 | Y35: 45457 | AA35: =AA34+1 -> 28 | AB35: GMIAMMPIK/2024/04/029 | AC35: =IFERROR(INDEX($B:$B,MATCH(AB35,$C:$C,FALSE)),"") -> 45406 | AD35: =INDEX($U:$U,MATCH(AB35,$C:$C,FALSE)) -> DO 23891 | AE35: =IFERROR(INDEX($V:$V,MATCH(AB35,$C:$C,FALSE)),"") -> 16/5/2024 | AF35: =IFERROR(INDEX($N:$N,MATCH(AB35,$C:$C,FALSE)),"") -> 200000686439 | AG35: =INDEX($Q:$Q,MATCH(AB35,$C:$C,FALSE)) -> 7000151244 | AH35: =IFERROR(INDEX($S:$S,MATCH(AB35,$C:$C,FALSE)),"") | AI35: =IFERROR(INDEX($T:$T,MATCH(AB35,$C:$C,FALSE)),"") | AJ35: =INDEX($W:$W,MATCH(AB35,$C:$C,FALSE)) -> GMI-0020008 | AK35: =IFERROR(INDEX($X:$X,MATCH(AB35,$C:$C,FALSE)),"") -> 45432 | AL35: =INDEX($O:$O,MATCH(AF35,$N:$N,FALSE),"") -> DONE FROM BC | AM35: =INDEX($Y:$Y,MATCH(AB35,$C:$C,FALSE)) -> 45457
A36: =A35+1 -> 29 | B36: 45406 | C36: GMIAMMPIK/2024/04/030 | D36: 11L-3024 | E36: =VLOOKUP(D36,MP!$A$1:$C$14184,2,0) -> LED FLood Light 6 Eyes 18 Watt 10-30 VDC | F36: 10 | G36: PCS | H36: PLTAM15 | I36: =IFERROR(INDEX(POP!$I:$I,MATCH(H36,POP!$G:$G,0)),"general") -> general | J36: =IFERROR(INDEX(POP!$E:$E,MATCH(H36,POP!$G:$G,0)),"general") -> general | K36: REPLACE WORKLAMP | L36: FANDY | M36: HARLY | N36: 260000019924 | O36: DONE FROM BC | P36: =B36 -> 45406 | Q36: 9200009909 | U36: DO 24032 | V36: 24/5/2024 | W36: GMI-0020134 | X36: 45436 | Y36: 45457 | AA36: =AA35+1 -> 29 | AB36: GMIAMMPIK/2024/04/030 | AC36: =IFERROR(INDEX($B:$B,MATCH(AB36,$C:$C,FALSE)),"") -> 45406 | AD36: =INDEX($U:$U,MATCH(AB36,$C:$C,FALSE)) -> DO 24032 | AE36: =IFERROR(INDEX($V:$V,MATCH(AB36,$C:$C,FALSE)),"") -> 24/5/2024 | AF36: =IFERROR(INDEX($N:$N,MATCH(AB36,$C:$C,FALSE)),"") -> 260000019924 | AG36: =INDEX($Q:$Q,MATCH(AB36,$C:$C,FALSE)) -> 9200009909 | AH36: =IFERROR(INDEX($S:$S,MATCH(AB36,$C:$C,FALSE)),"") | AI36: =IFERROR(INDEX($T:$T,MATCH(AB36,$C:$C,FALSE)),"") | AJ36: =INDEX($W:$W,MATCH(AB36,$C:$C,FALSE)) -> GMI-0020134 | AK36: =IFERROR(INDEX($X:$X,MATCH(AB36,$C:$C,FALSE)),"") -> 45436 | AL36: =INDEX($O:$O,MATCH(AF36,$N:$N,FALSE),"") -> DONE FROM BC | AM36: =INDEX($Y:$Y,MATCH(AB36,$C:$C,FALSE)) -> 45457
A37: =A36+1 -> 30 | B37: 12 Mei 2024 | C37: GMIAMMPIK/2024/05/031 | D37: 11L-3024 | E37: =VLOOKUP(D37,MP!$A$1:$C$14184,2,0) -> LED FLood Light 6 Eyes 18 Watt 10-30 VDC | F37: 2 | G37: PCS | H37: H57072 | I37: =IFERROR(INDEX(POP!$I:$I,MATCH(H37,POP!$G:$G,0)),"general") -> general | J37: =IFERROR(INDEX(POP!$E:$E,MATCH(H37,POP!$G:$G,0)),"general") -> general | K37: REPLACE WORKLAMP | L37: FANDY | M37: WIWIK | N37: 200000693114 | O37: DONE FROM BC | P37: =B37 -> 12 Mei 2024 | Q37: 9200010641 | U37: DO 24047 | V37: 25/5/2024 | W37: GMI-0020158 | X37: 45441 | Y37: 45502 | AA37: =AA36+1 -> 30 | AB37: GMIAMMPIK/2024/05/031 | AC37: =IFERROR(INDEX($B:$B,MATCH(AB37,$C:$C,FALSE)),"") -> 12 Mei 2024 | AD37: =INDEX($U:$U,MATCH(AB37,$C:$C,FALSE)) -> DO 24047 | AE37: =IFERROR(INDEX($V:$V,MATCH(AB37,$C:$C,FALSE)),"") -> 25/5/2024 | AF37: =IFERROR(INDEX($N:$N,MATCH(AB37,$C:$C,FALSE)),"") -> 200000693114 | AG37: =INDEX($Q:$Q,MATCH(AB37,$C:$C,FALSE)) -> 9200010641 | AH37: =IFERROR(INDEX($S:$S,MATCH(AB37,$C:$C,FALSE)),"") | AI37: =IFERROR(INDEX($T:$T,MATCH(AB37,$C:$C,FALSE)),"") | AJ37: =INDEX($W:$W,MATCH(AB37,$C:$C,FALSE)) -> GMI-0020158 | AK37: =IFERROR(INDEX($X:$X,MATCH(AB37,$C:$C,FALSE)),"") -> 45441 | AL37: =INDEX($O:$O,MATCH(AF37,$N:$N,FALSE),"") -> DONE FROM BC | AM37: =INDEX($Y:$Y,MATCH(AB37,$C:$C,FALSE)) -> 45502
A38: =A37+1 -> 31 | B38: 14 Mei 2024 | C38: GMIAMMPIK/2024/05/032 | D38: 11L-3024 | E38: =VLOOKUP(D38,MP!$A$1:$C$14184,2,0) -> LED FLood Light 6 Eyes 18 Watt 10-30 VDC | F38: 1 | G38: PCS | H38: WT2532PPA | I38: =IFERROR(INDEX(POP!$I:$I,MATCH(H38,POP!$G:$G,0)),"general") -> general | J38: =IFERROR(INDEX(POP!$E:$E,MATCH(H38,POP!$G:$G,0)),"general") -> general | K38: REPLACE WORKLAMP | L38: FANDY | M38: WIWIK | N38: 200000693458 | O38: DONE FROM BC | P38: =B38 -> 14 Mei 2024 | Q38: 9200010735 | R38: 45427 | T38: 45443 | U38: DO 24311 | V38: 45297 | W38: GMI-0020419 | X38: 45451 | Y38: 45502 | AA38: =AA37+1 -> 31 | AB38: GMIAMMPIK/2024/05/032 | AC38: =IFERROR(INDEX($B:$B,MATCH(AB38,$C:$C,FALSE)),"") -> 14 Mei 2024 | AD38: =INDEX($U:$U,MATCH(AB38,$C:$C,FALSE)) -> DO 24311 | AE38: =IFERROR(INDEX($V:$V,MATCH(AB38,$C:$C,FALSE)),"") -> 45297 | AF38: =IFERROR(INDEX($N:$N,MATCH(AB38,$C:$C,FALSE)),"") -> 200000693458 | AG38: =INDEX($Q:$Q,MATCH(AB38,$C:$C,FALSE)) -> 9200010735 | AH38: =IFERROR(INDEX($S:$S,MATCH(AB38,$C:$C,FALSE)),"") | AI38: =IFERROR(INDEX($T:$T,MATCH(AB38,$C:$C,FALSE)),"") -> 45443 | AJ38: =INDEX($W:$W,MATCH(AB38,$C:$C,FALSE)) -> GMI-0020419 | AK38: =IFERROR(INDEX($X:$X,MATCH(AB38,$C:$C,FALSE)),"") -> 45451 | AL38: =INDEX($O:$O,MATCH(AF38,$N:$N,FALSE),"") -> DONE FROM BC | AM38: =INDEX($Y:$Y,MATCH(AB38,$C:$C,FALSE)) -> 45502
A39: =A38+1 -> 32 | B39: 17 Mei 2024 | C39: GMIAMMPIK/2024/05/033 | D39: 11L-3024 | E39: =VLOOKUP(D39,MP!$A$1:$C$14184,2,0) -> LED FLood Light 6 Eyes 18 Watt 10-30 VDC | F39: 3 | G39: PCS | H39: F54404 | I39: =IFERROR(INDEX(POP!$I:$I,MATCH(H39,POP!$G:$G,0)),"general") -> general | J39: =IFERROR(INDEX(POP!$E:$E,MATCH(H39,POP!$G:$G,0)),"general") -> general | K39: REPLACE WORKLAMP | L39: FANDY | M39: WIWIK | N39: 200000694785 | O39: DONE FROM BC | P39: =B39 -> 17 Mei 2024 | Q39: 9200010805 | R39: 45428 | T39: 45443 | U39: DO 24313 | V39: 45297 | W39: GMI-0020420 | X39: 45451 | Y39: 45502 | AA39: =AA38+1 -> 32 | AB39: GMIAMMPIK/2024/05/033 | AC39: =IFERROR(INDEX($B:$B,MATCH(AB39,$C:$C,FALSE)),"") -> 17 Mei 2024 | AD39: =INDEX($U:$U,MATCH(AB39,$C:$C,FALSE)) -> DO 24313 | AE39: =IFERROR(INDEX($V:$V,MATCH(AB39,$C:$C,FALSE)),"") -> 45297 | AF39: =IFERROR(INDEX($N:$N,MATCH(AB39,$C:$C,FALSE)),"") -> 200000694785 | AG39: =INDEX($Q:$Q,MATCH(AB39,$C:$C,FALSE)) -> 9200010805 | AH39: =IFERROR(INDEX($S:$S,MATCH(AB39,$C:$C,FALSE)),"") | AI39: =IFERROR(INDEX($T:$T,MATCH(AB39,$C:$C,FALSE)),"") -> 45443 | AJ39: =INDEX($W:$W,MATCH(AB39,$C:$C,FALSE)) -> GMI-0020420 | AK39: =IFERROR(INDEX($X:$X,MATCH(AB39,$C:$C,FALSE)),"") -> 45451 | AL39: =INDEX($O:$O,MATCH(AF39,$N:$N,FALSE),"") -> DONE FROM BC | AM39: =INDEX($Y:$Y,MATCH(AB39,$C:$C,FALSE)) -> 45502
A40: =A39+1 -> 33 | B40: 18 Mei 2024 | C40: GMIAMMPIK/2024/05/034 | D40: 11L-3024 | E40: =VLOOKUP(D40,MP!$A$1:$C$14184,2,0) -> LED FLood Light 6 Eyes 18 Watt 10-30 VDC | F40: 1 | G40: PCS | H40: E53905 | I40: =IFERROR(INDEX(POP!$I:$I,MATCH(H40,POP!$G:$G,0)),"general") -> general | J40: =IFERROR(INDEX(POP!$E:$E,MATCH(H40,POP!$G:$G,0)),"general") -> general | K40: REPLACE WORKLAMP | L40: FANDY | M40: WIWIK | N40: 200000695618 | O40: DONE FROM BC | P40: =B40 -> 18 Mei 2024 | Q40: 9200010914 | R40: 20/5/2024 | T40: 22/5/2024 | U40: DO 24079 | V40: 25/5/2024 | W40: GMI-0020195 | X40: 45442 | Y40: 45502 | AA40: =AA39+1 -> 33 | AB40: GMIAMMPIK/2024/05/034 | AC40: =IFERROR(INDEX($B:$B,MATCH(AB40,$C:$C,FALSE)),"") -> 18 Mei 2024 | AD40: =INDEX($U:$U,MATCH(AB40,$C:$C,FALSE)) -> DO 24079 | AE40: =IFERROR(INDEX($V:$V,MATCH(AB40,$C:$C,FALSE)),"") -> 25/5/2024 | AF40: =IFERROR(INDEX($N:$N,MATCH(AB40,$C:$C,FALSE)),"") -> 200000695618 | AG40: =INDEX($Q:$Q,MATCH(AB40,$C:$C,FALSE)) -> 9200010914 | AH40: =IFERROR(INDEX($S:$S,MATCH(AB40,$C:$C,FALSE)),"") | AI40: =IFERROR(INDEX($T:$T,MATCH(AB40,$C:$C,FALSE)),"") -> 22/5/2024 | AJ40: =INDEX($W:$W,MATCH(AB40,$C:$C,FALSE)) -> GMI-0020195 | AK40: =IFERROR(INDEX($X:$X,MATCH(AB40,$C:$C,FALSE)),"") -> 45442 | AL40: =INDEX($O:$O,MATCH(AF40,$N:$N,FALSE),"") -> DONE FROM BC | AM40: =INDEX($Y:$Y,MATCH(AB40,$C:$C,FALSE)) -> 45502
A41: =A40+1 -> 34 | B41: 21 Mei 2024 | C41: GMIAMMPIK/2024/05/035 | D41: 11L-3024 | E41: =VLOOKUP(D41,MP!$A$1:$C$14184,2,0) -> LED FLood Light 6 Eyes 18 Watt 10-30 VDC | F41: 2 | G41: PCS | H41: PLTAM15 | I41: =IFERROR(INDEX(POP!$I:$I,MATCH(H41,POP!$G:$G,0)),"general") -> general | J41: =IFERROR(INDEX(POP!$E:$E,MATCH(H41,POP!$G:$G,0)),"general") -> general | K41: REPLACE WORKLAMP | L41: FANDY | M41: NUGROHO | N41: 260000020340 | O41: DONE FROM BC | P41: =B41 -> 21 Mei 2024 | Q41: 7000153962 | R41: 22/5/2024 | T41: 24/5/2024 | U41: DO 24157 | V41: 27/5/2024 | W41: GMI-0020242 | X41: 45447 | Y41: 45502 | AA41: =AA40+1 -> 34 | AB41: GMIAMMPIK/2024/05/035 | AC41: =IFERROR(INDEX($B:$B,MATCH(AB41,$C:$C,FALSE)),"") -> 21 Mei 2024 | AD41: =INDEX($U:$U,MATCH(AB41,$C:$C,FALSE)) -> DO 24157 | AE41: =IFERROR(INDEX($V:$V,MATCH(AB41,$C:$C,FALSE)),"") -> 27/5/2024 | AF41: =IFERROR(INDEX($N:$N,MATCH(AB41,$C:$C,FALSE)),"") -> 260000020340 | AG41: =INDEX($Q:$Q,MATCH(AB41,$C:$C,FALSE)) -> 7000153962 | AH41: =IFERROR(INDEX($S:$S,MATCH(AB41,$C:$C,FALSE)),"") | AI41: =IFERROR(INDEX($T:$T,MATCH(AB41,$C:$C,FALSE)),"") -> 24/5/2024 | AJ41: =INDEX($W:$W,MATCH(AB41,$C:$C,FALSE)) -> GMI-0020242 | AK41: =IFERROR(INDEX($X:$X,MATCH(AB41,$C:$C,FALSE)),"") -> 45447 | AL41: =INDEX($O:$O,MATCH(AF41,$N:$N,FALSE),"") -> DONE FROM BC | AM41: =INDEX($Y:$Y,MATCH(AB41,$C:$C,FALSE)) -> 45502
A42: =A41+1 -> 35 | B42: 22 Mei 2024 | C42: GMIAMMPIK/2024/05/036 | D42: 11L-3024 | E42: =VLOOKUP(D42,MP!$A$1:$C$14184,2,0) -> LED FLood Light 6 Eyes 18 Watt 10-30 VDC | F42: 2 | G42: PCS | H42: W52606 | I42: =IFERROR(INDEX(POP!$I:$I,MATCH(H42,POP!$G:$G,0)),"general") -> general | J42: =IFERROR(INDEX(POP!$E:$E,MATCH(H42,POP!$G:$G,0)),"general") -> general | K42: REPLACE WORKLAMP | L42: FANDY | M42: NUGROHO | N42: 200000697304 | O42: DONE FROM BC | P42: =B42 -> 22 Mei 2024 | Q42: 7000153994 | R42: 24/5/2024 | T42: 25/5/2024 | U42: DO 24178 | V42: 28/5/2024 | W42: GMI-0020246 | X42: 45447 | Y42: 45502 | AA42: =AA41+1 -> 35 | AB42: GMIAMMPIK/2024/05/036 | AC42: =IFERROR(INDEX($B:$B,MATCH(AB42,$C:$C,FALSE)),"") -> 22 Mei 2024 | AD42: =INDEX($U:$U,MATCH(AB42,$C:$C,FALSE)) -> DO 24178 | AE42: =IFERROR(INDEX($V:$V,MATCH(AB42,$C:$C,FALSE)),"") -> 28/5/2024 | AF42: =IFERROR(INDEX($N:$N,MATCH(AB42,$C:$C,FALSE)),"") -> 200000697304 | AG42: =INDEX($Q:$Q,MATCH(AB42,$C:$C,FALSE)) -> 7000153994 | AH42: =IFERROR(INDEX($S:$S,MATCH(AB42,$C:$C,FALSE)),"") | AI42: =IFERROR(INDEX($T:$T,MATCH(AB42,$C:$C,FALSE)),"") -> 25/5/2024 | AJ42: =INDEX($W:$W,MATCH(AB42,$C:$C,FALSE)) -> GMI-0020246 | AK42: =IFERROR(INDEX($X:$X,MATCH(AB42,$C:$C,FALSE)),"") -> 45447 | AL42: =INDEX($O:$O,MATCH(AF42,$N:$N,FALSE),"") -> DONE FROM BC | AM42: =INDEX($Y:$Y,MATCH(AB42,$C:$C,FALSE)) -> 45502
A43: =A42+1 -> 36 | B43: 23 Mei 2024 | C43: GMIAMMPIK/2024/05/037 | D43: 11L-3024 | E43: =VLOOKUP(D43,MP!$A$1:$C$14184,2,0) -> LED FLood Light 6 Eyes 18 Watt 10-30 VDC | F43: 2 | G43: PCS | H43: DA54830 | I43: =IFERROR(INDEX(POP!$I:$I,MATCH(H43,POP!$G:$G,0)),"general") -> general | J43: =IFERROR(INDEX(POP!$E:$E,MATCH(H43,POP!$G:$G,0)),"general") -> general | K43: REPLACE WORKLAMP | L43: FANDY | M43: NUGROHO | N43: 200000697702 | O43: DONE FROM BC | P43: =B43 -> 23 Mei 2024 | Q43: 9200011112 | R43: 24/5/2024 | T43: 25/5/2024 | U43: DO 24176 | V43: 28/5/2024 | W43: GMI-0020245 | X43: 45447 | Y43: 45502 | AA43: =AA42+1 -> 36 | AB43: GMIAMMPIK/2024/05/037 | AC43: =IFERROR(INDEX($B:$B,MATCH(AB43,$C:$C,FALSE)),"") -> 23 Mei 2024 | AD43: =INDEX($U:$U,MATCH(AB43,$C:$C,FALSE)) -> DO 24176 | AE43: =IFERROR(INDEX($V:$V,MATCH(AB43,$C:$C,FALSE)),"") -> 28/5/2024 | AF43: =IFERROR(INDEX($N:$N,MATCH(AB43,$C:$C,FALSE)),"") -> 200000697702 | AG43: =INDEX($Q:$Q,MATCH(AB43,$C:$C,FALSE)) -> 9200011112 | AH43: =IFERROR(INDEX($S:$S,MATCH(AB43,$C:$C,FALSE)),"") | AI43: =IFERROR(INDEX($T:$T,MATCH(AB43,$C:$C,FALSE)),"") -> 25/5/2024 | AJ43: =INDEX($W:$W,MATCH(AB43,$C:$C,FALSE)) -> GMI-0020245 | AK43: =IFERROR(INDEX($X:$X,MATCH(AB43,$C:$C,FALSE)),"") -> 45447 | AL43: =INDEX($O:$O,MATCH(AF43,$N:$N,FALSE),"") -> DONE FROM BC | AM43: =INDEX($Y:$Y,MATCH(AB43,$C:$C,FALSE)) -> 45502
A44: =A43+1 -> 37 | B44: 23 Mei 2024 | C44: GMIAMMPIK/2024/05/038 | D44: 11L-3024 | E44: =VLOOKUP(D44,MP!$A$1:$C$14184,2,0) -> LED FLood Light 6 Eyes 18 Watt 10-30 VDC | F44: 1 | G44: PCS | H44: DA54831 | I44: =IFERROR(INDEX(POP!$I:$I,MATCH(H44,POP!$G:$G,0)),"general") -> general | J44: =IFERROR(INDEX(POP!$E:$E,MATCH(H44,POP!$G:$G,0)),"general") -> general | K44: REPLACE WORKLAMP | L44: FANDY | M44: NUGROHO | N44: 200000697699 | O44: DONE FROM BC | P44: =B44 -> 23 Mei 2024 | Q44: 9200011114 | R44: 24/5/2024 | T44: 25/5/2024 | U44: DO 24174 | V44: 27/5/2024 | W44: GMI-0020243 | X44: 45447 | Y44: 45502 | AA44: =AA43+1 -> 37 | AB44: GMIAMMPIK/2024/05/038 | AC44: =IFERROR(INDEX($B:$B,MATCH(AB44,$C:$C,FALSE)),"") -> 23 Mei 2024 | AD44: =INDEX($U:$U,MATCH(AB44,$C:$C,FALSE)) -> DO 24174 | AE44: =IFERROR(INDEX($V:$V,MATCH(AB44,$C:$C,FALSE)),"") -> 27/5/2024 | AF44: =IFERROR(INDEX($N:$N,MATCH(AB44,$C:$C,FALSE)),"") -> 200000697699 | AG44: =INDEX($Q:$Q,MATCH(AB44,$C:$C,FALSE)) -> 9200011114 | AH44: =IFERROR(INDEX($S:$S,MATCH(AB44,$C:$C,FALSE)),"") | AI44: =IFERROR(INDEX($T:$T,MATCH(AB44,$C:$C,FALSE)),"") -> 25/5/2024 | AJ44: =INDEX($W:$W,MATCH(AB44,$C:$C,FALSE)) -> GMI-0020243 | AK44: =IFERROR(INDEX($X:$X,MATCH(AB44,$C:$C,FALSE)),"") -> 45447 | AL44: =INDEX($O:$O,MATCH(AF44,$N:$N,FALSE),"") -> DONE FROM BC | AM44: =INDEX($Y:$Y,MATCH(AB44,$C:$C,FALSE)) -> 45502
A45: =A44+1 -> 38 | B45: 23 Mei 2024 | C45: GMIAMMPIK/2024/05/039 | D45: 11L-3024 | E45: =VLOOKUP(D45,MP!$A$1:$C$14184,2,0) -> LED FLood Light 6 Eyes 18 Watt 10-30 VDC | F45: 2 | G45: PCS | H45: PLTAM15 | I45: =IFERROR(INDEX(POP!$I:$I,MATCH(H45,POP!$G:$G,0)),"general") -> general | J45: =IFERROR(INDEX(POP!$E:$E,MATCH(H45,POP!$G:$G,0)),"general") -> general | K45: REPLACE WORKLAMP | L45: FANDY | M45: WIWIK | N45: 200000697611 | O45: DONE FROM BC | P45: =B45 -> 23 Mei 2024 | Q45: 9200011125 | R45: 24/5/2024 | T45: 25/5/2024 | U45: DO 24175 | V45: 27/5/2024 | W45: GMI-0020244 | X45: 45447 | Y45: 45502 | AA45: =AA44+1 -> 38 | AB45: GMIAMMPIK/2024/05/039 | AC45: =IFERROR(INDEX($B:$B,MATCH(AB45,$C:$C,FALSE)),"") -> 23 Mei 2024 | AD45: =INDEX($U:$U,MATCH(AB45,$C:$C,FALSE)) -> DO 24175 | AE45: =IFERROR(INDEX($V:$V,MATCH(AB45,$C:$C,FALSE)),"") -> 27/5/2024 | AF45: =IFERROR(INDEX($N:$N,MATCH(AB45,$C:$C,FALSE)),"") -> 200000697611 | AG45: =INDEX($Q:$Q,MATCH(AB45,$C:$C,FALSE)) -> 9200011125 | AH45: =IFERROR(INDEX($S:$S,MATCH(AB45,$C:$C,FALSE)),"") | AI45: =IFERROR(INDEX($T:$T,MATCH(AB45,$C:$C,FALSE)),"") -> 25/5/2024 | AJ45: =INDEX($W:$W,MATCH(AB45,$C:$C,FALSE)) -> GMI-0020244 | AK45: =IFERROR(INDEX($X:$X,MATCH(AB45,$C:$C,FALSE)),"") -> 45447 | AL45: =INDEX($O:$O,MATCH(AF45,$N:$N,FALSE),"") -> DONE FROM BC | AM45: =INDEX($Y:$Y,MATCH(AB45,$C:$C,FALSE)) -> 45502
A46: =A45+1 -> 39 | B46: 25 Mei 2024 | C46: GMIAMMPIK/2024/05/040 | D46: 11L-3024 | E46: =VLOOKUP(D46,MP!$A$1:$C$14184,2,0) -> LED FLood Light 6 Eyes 18 Watt 10-30 VDC | F46: 1 | G46: PCS | H46: PLTAM15 | I46: =IFERROR(INDEX(POP!$I:$I,MATCH(H46,POP!$G:$G,0)),"general") -> general | J46: =IFERROR(INDEX(POP!$E:$E,MATCH(H46,POP!$G:$G,0)),"general") -> general | K46: REPLACE WORKLAMP | L46: FANDY | M46: NUGROHO | N46: 200000698376 | O46: DONE FROM BC | P46: =B46 -> 25 Mei 2024 | Q46: 9200011252 | R46: 45438 | T46: 45443 | U46: DO 24314 | V46: 45297 | W46: GMI-0020421 | X46: 45451 | Y46: 45502 | AA46: =AA45+1 -> 39 | AB46: GMIAMMPIK/2024/05/040 | AC46: =IFERROR(INDEX($B:$B,MATCH(AB46,$C:$C,FALSE)),"") -> 25 Mei 2024 | AD46: =INDEX($U:$U,MATCH(AB46,$C:$C,FALSE)) -> DO 24314 | AE46: =IFERROR(INDEX($V:$V,MATCH(AB46,$C:$C,FALSE)),"") -> 45297 | AF46: =IFERROR(INDEX($N:$N,MATCH(AB46,$C:$C,FALSE)),"") -> 200000698376 | AG46: =INDEX($Q:$Q,MATCH(AB46,$C:$C,FALSE)) -> 9200011252 | AH46: =IFERROR(INDEX($S:$S,MATCH(AB46,$C:$C,FALSE)),"") | AI46: =IFERROR(INDEX($T:$T,MATCH(AB46,$C:$C,FALSE)),"") -> 45443 | AJ46: =INDEX($W:$W,MATCH(AB46,$C:$C,FALSE)) -> GMI-0020421 | AK46: =IFERROR(INDEX($X:$X,MATCH(AB46,$C:$C,FALSE)),"") -> 45451 | AL46: =INDEX($O:$O,MATCH(AF46,$N:$N,FALSE),"") -> DONE FROM BC | AM46: =INDEX($Y:$Y,MATCH(AB46,$C:$C,FALSE)) -> 45502
A47: =A46+1 -> 40 | B47: 25 Mei 2024 | C47: GMIAMMPIK/2024/05/041 | D47: 3L4-7ASA | E47: =VLOOKUP(D47,MP!$A$1:$C$14184,2,0) -> LED (SMD Led) Strobe Beacon Amber : 12-24VDC with Alumunium screw base | F47: 1 | G47: PCS | H47: H57121 | I47: =IFERROR(INDEX(POP!$I:$I,MATCH(H47,POP!$G:$G,0)),"general") -> general | J47: =IFERROR(INDEX(POP!$E:$E,MATCH(H47,POP!$G:$G,0)),"general") -> general | K47: REPLACE WORKLAMP | L47: FANDY | M47: NUGROHO | N47: 200000698546 | O47: DONE FROM BC | P47: =B47 -> 25 Mei 2024 | Q47: 9200011253 | R47: 45438 | T47: 45443 | U47: DO 24315 | V47: 45297 | W47: GMI-0020422 | X47: 45451 | Y47: 45502 | AA47: =AA46+1 -> 40 | AB47: GMIAMMPIK/2024/05/041 | AC47: =IFERROR(INDEX($B:$B,MATCH(AB47,$C:$C,FALSE)),"") -> 25 Mei 2024 | AD47: =INDEX($U:$U,MATCH(AB47,$C:$C,FALSE)) -> DO 24315 | AE47: =IFERROR(INDEX($V:$V,MATCH(AB47,$C:$C,FALSE)),"") -> 45297 | AF47: =IFERROR(INDEX($N:$N,MATCH(AB47,$C:$C,FALSE)),"") -> 200000698546 | AG47: =INDEX($Q:$Q,MATCH(AB47,$C:$C,FALSE)) -> 9200011253 | AH47: =IFERROR(INDEX($S:$S,MATCH(AB47,$C:$C,FALSE)),"") | AI47: =IFERROR(INDEX($T:$T,MATCH(AB47,$C:$C,FALSE)),"") -> 45443 | AJ47: =INDEX($W:$W,MATCH(AB47,$C:$C,FALSE)) -> GMI-0020422 | AK47: =IFERROR(INDEX($X:$X,MATCH(AB47,$C:$C,FALSE)),"") -> 45451 | AL47: =INDEX($O:$O,MATCH(AF47,$N:$N,FALSE),"") -> DONE FROM BC | AM47: =INDEX($Y:$Y,MATCH(AB47,$C:$C,FALSE)) -> 45502
A48: =A47+1 -> 41 | B48: 28 Mei 2024 | C48: GMIAMMPIK/2024/05/042 | D48: 3L4-7ASB | E48: =VLOOKUP(D48,MP!$A$1:$C$14184,2,0) -> LED (SMD Led) Strobe Beacon Blue : 12-24VDC with Alumunium screw base | F48: 1 | G48: PCS | H48: E53904 | I48: =IFERROR(INDEX(POP!$I:$I,MATCH(H48,POP!$G:$G,0)),"general") -> general | J48: =IFERROR(INDEX(POP!$E:$E,MATCH(H48,POP!$G:$G,0)),"general") -> general | K48: REPLACE WORKLAMP | L48: FANDY | M48: NUGROHO | N48: 200000699896 | O48: DONE FROM BC | P48: =B48 -> 28 Mei 2024 | Q48: 9200011479 | R48: 45438 | T48: 45443 | U48: DO 24316 | V48: 45297 | W48: GMI-0020423 | X48: 45451 | Y48: 45502 | AA48: =AA47+1 -> 41 | AB48: GMIAMMPIK/2024/05/042 | AC48: =IFERROR(INDEX($B:$B,MATCH(AB48,$C:$C,FALSE)),"") -> 28 Mei 2024 | AD48: =INDEX($U:$U,MATCH(AB48,$C:$C,FALSE)) -> DO 24316 | AE48: =IFERROR(INDEX($V:$V,MATCH(AB48,$C:$C,FALSE)),"") -> 45297 | AF48: =IFERROR(INDEX($N:$N,MATCH(AB48,$C:$C,FALSE)),"") -> 200000699896 | AG48: =INDEX($Q:$Q,MATCH(AB48,$C:$C,FALSE)) -> 9200011479 | AH48: =IFERROR(INDEX($S:$S,MATCH(AB48,$C:$C,FALSE)),"") | AI48: =IFERROR(INDEX($T:$T,MATCH(AB48,$C:$C,FALSE)),"") -> 45443 | AJ48: =INDEX($W:$W,MATCH(AB48,$C:$C,FALSE)) -> GMI-0020423 | AK48: =IFERROR(INDEX($X:$X,MATCH(AB48,$C:$C,FALSE)),"") -> 45451 | AL48: =INDEX($O:$O,MATCH(AF48,$N:$N,FALSE),"") -> DONE FROM BC | AM48: =INDEX($Y:$Y,MATCH(AB48,$C:$C,FALSE)) -> 45502
A49: =A48+1 -> 42 | B49: 30 Mei 2024 | C49: GMIAMMPIK/2024/05/043 | D49: 11L-3024 | E49: =VLOOKUP(D49,MP!$A$1:$C$14184,2,0) -> LED FLood Light 6 Eyes 18 Watt 10-30 VDC | F49: 2 | G49: PCS | H49: E429PPA | I49: =IFERROR(INDEX(POP!$I:$I,MATCH(H49,POP!$G:$G,0)),"general") -> general | J49: =IFERROR(INDEX(POP!$E:$E,MATCH(H49,POP!$G:$G,0)),"general") -> general | K49: REPLACE WORKLAMP | L49: FANDY | M49: FAUZI | N49: 200000700412 | O49: DONE FROM BC | P49: =B49 -> 30 Mei 2024 | Q49: 9200011546 | R49: 45442 | T49: 45448 | U49: DO 24393 | V49: 45418 | W49: GMI-0020496 | X49: 45454 | Y49: 45502 | AA49: =AA48+1 -> 42 | AB49: GMIAMMPIK/2024/05/043 | AC49: =IFERROR(INDEX($B:$B,MATCH(AB49,$C:$C,FALSE)),"") -> 30 Mei 2024 | AD49: =INDEX($U:$U,MATCH(AB49,$C:$C,FALSE)) -> DO 24393 | AE49: =IFERROR(INDEX($V:$V,MATCH(AB49,$C:$C,FALSE)),"") -> 45418 | AF49: =IFERROR(INDEX($N:$N,MATCH(AB49,$C:$C,FALSE)),"") -> 200000700412 | AG49: =INDEX($Q:$Q,MATCH(AB49,$C:$C,FALSE)) -> 9200011546 | AH49: =IFERROR(INDEX($S:$S,MATCH(AB49,$C:$C,FALSE)),"") | AI49: =IFERROR(INDEX($T:$T,MATCH(AB49,$C:$C,FALSE)),"") -> 45448 | AJ49: =INDEX($W:$W,MATCH(AB49,$C:$C,FALSE)) -> GMI-0020496 | AK49: =IFERROR(INDEX($X:$X,MATCH(AB49,$C:$C,FALSE)),"") -> 45454 | AL49: =INDEX($O:$O,MATCH(AF49,$N:$N,FALSE),"") -> DONE FROM BC | AM49: =INDEX($Y:$Y,MATCH(AB49,$C:$C,FALSE)) -> 45502
A50: =A49+1 -> 43 | B50: 30 Mei 2024 | C50: GMIAMMPIK/2024/05/044 | D50: 11L-3024 | E50: =VLOOKUP(D50,MP!$A$1:$C$14184,2,0) -> LED FLood Light 6 Eyes 18 Watt 10-30 VDC | F50: 1 | G50: PCS | H50: W52605 | I50: =IFERROR(INDEX(POP!$I:$I,MATCH(H50,POP!$G:$G,0)),"general") -> general | J50: =IFERROR(INDEX(POP!$E:$E,MATCH(H50,POP!$G:$G,0)),"general") -> general | K50: REPLACE WORKLAMP | L50: FANDY | M50: FAUZI | N50: 200000700434 | O50: DONE FROM BC | P50: =B50 -> 30 Mei 2024 | Q50: 9200011547 | R50: 45442 | T50: 45448 | U50: DO 24394 | V50: 45418 | W50: GMI-0020497 | X50: 45454 | Y50: 45502 | AA50: =AA49+1 -> 43 | AB50: GMIAMMPIK/2024/05/044 | AC50: =IFERROR(INDEX($B:$B,MATCH(AB50,$C:$C,FALSE)),"") -> 30 Mei 2024 | AD50: =INDEX($U:$U,MATCH(AB50,$C:$C,FALSE)) -> DO 24394 | AE50: =IFERROR(INDEX($V:$V,MATCH(AB50,$C:$C,FALSE)),"") -> 45418 | AF50: =IFERROR(INDEX($N:$N,MATCH(AB50,$C:$C,FALSE)),"") -> 200000700434 | AG50: =INDEX($Q:$Q,MATCH(AB50,$C:$C,FALSE)) -> 9200011547 | AH50: =IFERROR(INDEX($S:$S,MATCH(AB50,$C:$C,FALSE)),"") | AI50: =IFERROR(INDEX($T:$T,MATCH(AB50,$C:$C,FALSE)),"") -> 45448 | AJ50: =INDEX($W:$W,MATCH(AB50,$C:$C,FALSE)) -> GMI-0020497 | AK50: =IFERROR(INDEX($X:$X,MATCH(AB50,$C:$C,FALSE)),"") -> 45454 | AL50: =INDEX($O:$O,MATCH(AF50,$N:$N,FALSE),"") -> DONE FROM BC | AM50: =INDEX($Y:$Y,MATCH(AB50,$C:$C,FALSE)) -> 45502
A51: =A50+1 -> 44 | B51: 03 Juni 2024 | C51: GMIAMMPIK/2024/06/045 | D51: 11L-3024 | E51: =VLOOKUP(D51,MP!$A$1:$C$14184,2,0) -> LED FLood Light 6 Eyes 18 Watt 10-30 VDC | F51: 2 | G51: PCS | H51: FT2532PPA | I51: =IFERROR(INDEX(POP!$I:$I,MATCH(H51,POP!$G:$G,0)),"general") -> general | J51: =IFERROR(INDEX(POP!$E:$E,MATCH(H51,POP!$G:$G,0)),"general") -> general | K51: REPLACE WORKLAMP | L51: FANDY | M51: NUGROHO | N51: 200000701915 | O51: DONE FROM BC | P51: =B51 -> 03 Juni 2024 | Q51: 9200011730 | R51: 45447 | T51: 45448 | U51: DO 24395 | V51: 45418 | W51: GMI-0020498 | X51: 45454 | Y51: 45502 | AA51: =AA50+1 -> 44 | AB51: GMIAMMPIK/2024/06/045 | AC51: =IFERROR(INDEX($B:$B,MATCH(AB51,$C:$C,FALSE)),"") -> 03 Juni 2024 | AD51: =INDEX($U:$U,MATCH(AB51,$C:$C,FALSE)) -> DO 24395 | AE51: =IFERROR(INDEX($V:$V,MATCH(AB51,$C:$C,FALSE)),"") -> 45418 | AF51: =IFERROR(INDEX($N:$N,MATCH(AB51,$C:$C,FALSE)),"") -> 200000701915 | AG51: =INDEX($Q:$Q,MATCH(AB51,$C:$C,FALSE)) -> 9200011730 | AH51: =IFERROR(INDEX($S:$S,MATCH(AB51,$C:$C,FALSE)),"") | AI51: =IFERROR(INDEX($T:$T,MATCH(AB51,$C:$C,FALSE)),"") -> 45448 | AJ51: =INDEX($W:$W,MATCH(AB51,$C:$C,FALSE)) -> GMI-0020498 | AK51: =IFERROR(INDEX($X:$X,MATCH(AB51,$C:$C,FALSE)),"") -> 45454 | AL51: =INDEX($O:$O,MATCH(AF51,$N:$N,FALSE),"") -> DONE FROM BC | AM51: =INDEX($Y:$Y,MATCH(AB51,$C:$C,FALSE)) -> 45502
A52: =A51+1 -> 45 | B52: 07 Juni 2024 | C52: GMIAMMPIK/2024/06/046 | D52: 3L4-7ASA | E52: =VLOOKUP(D52,MP!$A$1:$C$14184,2,0) -> LED (SMD Led) Strobe Beacon Amber : 12-24VDC with Alumunium screw base | F52: 1 | G52: PCS | H52: H57106 | I52: =IFERROR(INDEX(POP!$I:$I,MATCH(H52,POP!$G:$G,0)),"general") -> general | J52: =IFERROR(INDEX(POP!$E:$E,MATCH(H52,POP!$G:$G,0)),"general") -> general | K52: REPLACE WORKLAMP | L52: FANDY | M52: NUGROHO | N52: 200000703627 | O52: DONE FROM BC | P52: =B52 -> 07 Juni 2024 | Q52: 9200012019 | R52: 45450 | T52: 45450 | U52: DO 24423 | V52: 45479 | W52: GMI-0020532 | X52: 45456 | Y52: 45502 | AA52: =AA51+1 -> 45 | AB52: GMIAMMPIK/2024/06/046 | AC52: =IFERROR(INDEX($B:$B,MATCH(AB52,$C:$C,FALSE)),"") -> 07 Juni 2024 | AD52: =INDEX($U:$U,MATCH(AB52,$C:$C,FALSE)) -> DO 24423 | AE52: =IFERROR(INDEX($V:$V,MATCH(AB52,$C:$C,FALSE)),"") -> 45479 | AF52: =IFERROR(INDEX($N:$N,MATCH(AB52,$C:$C,FALSE)),"") -> 200000703627 | AG52: =INDEX($Q:$Q,MATCH(AB52,$C:$C,FALSE)) -> 9200012019 | AH52: =IFERROR(INDEX($S:$S,MATCH(AB52,$C:$C,FALSE)),"") | AI52: =IFERROR(INDEX($T:$T,MATCH(AB52,$C:$C,FALSE)),"") -> 45450 | AJ52: =INDEX($W:$W,MATCH(AB52,$C:$C,FALSE)) -> GMI-0020532 | AK52: =IFERROR(INDEX($X:$X,MATCH(AB52,$C:$C,FALSE)),"") -> 45456 | AL52: =INDEX($O:$O,MATCH(AF52,$N:$N,FALSE),"") -> DONE FROM BC | AM52: =INDEX($Y:$Y,MATCH(AB52,$C:$C,FALSE)) -> 45502
A53: =A52+1 -> 46 | B53: 11 Juni 2024 | C53: GMIAMMPIK/2024/06/047 | D53: 11L-3024 | E53: =VLOOKUP(D53,MP!$A$1:$C$14184,2,0) -> LED FLood Light 6 Eyes 18 Watt 10-30 VDC | F53: 2 | G53: PCS | H53: E5115 | I53: =IFERROR(INDEX(POP!$I:$I,MATCH(H53,POP!$G:$G,0)),"general") -> general | J53: =IFERROR(INDEX(POP!$E:$E,MATCH(H53,POP!$G:$G,0)),"general") -> general | K53: REPLACE WORKLAMP | L53: FANDY | M53: FAUZI | N53: 200000705210 | O53: DONE FROM BC | P53: =B53 -> 11 Juni 2024 | Q53: 9200012235 | R53: 45454 | T53: 45455 | U53: DO 24524 | V53: 13/6/2024 | W53: GMI-0020588 | X53: 45463 | Y53: 45531 | AA53: =AA52+1 -> 46 | AB53: GMIAMMPIK/2024/06/047 | AC53: =IFERROR(INDEX($B:$B,MATCH(AB53,$C:$C,FALSE)),"") -> 11 Juni 2024 | AD53: =INDEX($U:$U,MATCH(AB53,$C:$C,FALSE)) -> DO 24524 | AE53: =IFERROR(INDEX($V:$V,MATCH(AB53,$C:$C,FALSE)),"") -> 13/6/2024 | AF53: =IFERROR(INDEX($N:$N,MATCH(AB53,$C:$C,FALSE)),"") -> 200000705210 | AG53: =INDEX($Q:$Q,MATCH(AB53,$C:$C,FALSE)) -> 9200012235 | AH53: =IFERROR(INDEX($S:$S,MATCH(AB53,$C:$C,FALSE)),"") | AI53: =IFERROR(INDEX($T:$T,MATCH(AB53,$C:$C,FALSE)),"") -> 45455 | AJ53: =INDEX($W:$W,MATCH(AB53,$C:$C,FALSE)) -> GMI-0020588 | AK53: =IFERROR(INDEX($X:$X,MATCH(AB53,$C:$C,FALSE)),"") -> 45463 | AL53: =INDEX($O:$O,MATCH(AF53,$N:$N,FALSE),"") -> DONE FROM BC | AM53: =INDEX($Y:$Y,MATCH(AB53,$C:$C,FALSE)) -> 45531
A54: =A53+1 -> 47 | B54: 11 Juni 2024 | C54: GMIAMMPIK/2024/06/048 | D54: 3L4-7ASA | E54: =VLOOKUP(D54,MP!$A$1:$C$14184,2,0) -> LED (SMD Led) Strobe Beacon Amber : 12-24VDC with Alumunium screw base | F54: 1 | G54: PCS | H54: PLTAM15 | I54: =IFERROR(INDEX(POP!$I:$I,MATCH(H54,POP!$G:$G,0)),"general") -> general | J54: =IFERROR(INDEX(POP!$E:$E,MATCH(H54,POP!$G:$G,0)),"general") -> general | K54: REPLACE WORKLAMP | L54: FANDY | M54: FAUZI | N54: 200000705172 | O54: DONE FROM BC | P54: =B54 -> 11 Juni 2024 | Q54: 9200012237 | R54: 45454 | T54: 45455 | U54: DO 24525 | V54: 13/6/2024 | W54: GMI-0020587 | X54: 45463 | Y54: 45531 | AA54: =AA53+1 -> 47 | AB54: GMIAMMPIK/2024/06/048 | AC54: =IFERROR(INDEX($B:$B,MATCH(AB54,$C:$C,FALSE)),"") -> 11 Juni 2024 | AD54: =INDEX($U:$U,MATCH(AB54,$C:$C,FALSE)) -> DO 24525 | AE54: =IFERROR(INDEX($V:$V,MATCH(AB54,$C:$C,FALSE)),"") -> 13/6/2024 | AF54: =IFERROR(INDEX($N:$N,MATCH(AB54,$C:$C,FALSE)),"") -> 200000705172 | AG54: =INDEX($Q:$Q,MATCH(AB54,$C:$C,FALSE)) -> 9200012237 | AH54: =IFERROR(INDEX($S:$S,MATCH(AB54,$C:$C,FALSE)),"") | AI54: =IFERROR(INDEX($T:$T,MATCH(AB54,$C:$C,FALSE)),"") -> 45455 | AJ54: =INDEX($W:$W,MATCH(AB54,$C:$C,FALSE)) -> GMI-0020587 | AK54: =IFERROR(INDEX($X:$X,MATCH(AB54,$C:$C,FALSE)),"") -> 45463 | AL54: =INDEX($O:$O,MATCH(AF54,$N:$N,FALSE),"") -> DONE FROM BC | AM54: =INDEX($Y:$Y,MATCH(AB54,$C:$C,FALSE)) -> 45531
A55: =A54+1 -> 48 | B55: 22 Juni 2024 | C55: GMIAMMPIK/2024/06/049 | D55: 11L-3024 | E55: =VLOOKUP(D55,MP!$A$1:$C$14184,2,0) -> LED FLood Light 6 Eyes 18 Watt 10-30 VDC | F55: 2 | G55: PCS | H55: D5834 | I55: =IFERROR(INDEX(POP!$I:$I,MATCH(H55,POP!$G:$G,0)),"general") -> general | J55: =IFERROR(INDEX(POP!$E:$E,MATCH(H55,POP!$G:$G,0)),"general") -> general | K55: REPLACE WORKLAMP | L55: FANDY | M55: FAUZI | N55: 200000709273 | O55: DONE FROM BC | P55: =B55 -> 22 Juni 2024 | Q55: 9200012836 | R55: 45465 | T55: 45467 | U55: DO 24734 | V55: 45329 | W55: GMI-0020876 | X55: 45477 | Y55: 45531 | AA55: =AA54+1 -> 48 | AB55: GMIAMMPIK/2024/06/049 | AC55: =IFERROR(INDEX($B:$B,MATCH(AB55,$C:$C,FALSE)),"") -> 22 Juni 2024 | AD55: =INDEX($U:$U,MATCH(AB55,$C:$C,FALSE)) -> DO 24734 | AE55: =IFERROR(INDEX($V:$V,MATCH(AB55,$C:$C,FALSE)),"") -> 45329 | AF55: =IFERROR(INDEX($N:$N,MATCH(AB55,$C:$C,FALSE)),"") -> 200000709273 | AG55: =INDEX($Q:$Q,MATCH(AB55,$C:$C,FALSE)) -> 9200012836 | AH55: =IFERROR(INDEX($S:$S,MATCH(AB55,$C:$C,FALSE)),"") | AI55: =IFERROR(INDEX($T:$T,MATCH(AB55,$C:$C,FALSE)),"") -> 45467 | AJ55: =INDEX($W:$W,MATCH(AB55,$C:$C,FALSE)) -> GMI-0020876 | AK55: =IFERROR(INDEX($X:$X,MATCH(AB55,$C:$C,FALSE)),"") -> 45477 | AL55: =INDEX($O:$O,MATCH(AF55,$N:$N,FALSE),"") -> DONE FROM BC | AM55: =INDEX($Y:$Y,MATCH(AB55,$C:$C,FALSE)) -> 45531
A56: =A55+1 -> 49 | B56: 22 Juni 2024 | C56: GMIAMMPIK/2024/06/050 | D56: 11L-3024 | E56: =VLOOKUP(D56,MP!$A$1:$C$14184,2,0) -> LED FLood Light 6 Eyes 18 Watt 10-30 VDC | F56: 1 | G56: PCS | H56: SV508 | I56: =IFERROR(INDEX(POP!$I:$I,MATCH(H56,POP!$G:$G,0)),"general") -> general | J56: =IFERROR(INDEX(POP!$E:$E,MATCH(H56,POP!$G:$G,0)),"general") -> general | K56: REPLACE WORKLAMP | L56: FANDY | M56: FAUZI | N56: 200000709348 | O56: DONE FROM BC | P56: =B56 -> 22 Juni 2024 | Q56: 9200012841 | R56: 45465 | T56: 45467 | U56: DO 24739 | V56: 45329 | W56: GMI-0020877 | X56: 45477 | Y56: 45531 | AA56: =AA55+1 -> 49 | AB56: GMIAMMPIK/2024/06/050 | AC56: =IFERROR(INDEX($B:$B,MATCH(AB56,$C:$C,FALSE)),"") -> 22 Juni 2024 | AD56: =INDEX($U:$U,MATCH(AB56,$C:$C,FALSE)) -> DO 24739 | AE56: =IFERROR(INDEX($V:$V,MATCH(AB56,$C:$C,FALSE)),"") -> 45329 | AF56: =IFERROR(INDEX($N:$N,MATCH(AB56,$C:$C,FALSE)),"") -> 200000709348 | AG56: =INDEX($Q:$Q,MATCH(AB56,$C:$C,FALSE)) -> 9200012841 | AH56: =IFERROR(INDEX($S:$S,MATCH(AB56,$C:$C,FALSE)),"") | AI56: =IFERROR(INDEX($T:$T,MATCH(AB56,$C:$C,FALSE)),"") -> 45467 | AJ56: =INDEX($W:$W,MATCH(AB56,$C:$C,FALSE)) -> GMI-0020877 | AK56: =IFERROR(INDEX($X:$X,MATCH(AB56,$C:$C,FALSE)),"") -> 45477 | AL56: =INDEX($O:$O,MATCH(AF56,$N:$N,FALSE),"") -> DONE FROM BC | AM56: =INDEX($Y:$Y,MATCH(AB56,$C:$C,FALSE)) -> 45531
A57: =A56+1 -> 50 | B57: 24 Juni 2024 | C57: GMIAMMPIK/2024/06/051 | D57: 14L-0312-HD785 | E57: =VLOOKUP(D57,MP!$A$1:$C$14184,2,0) -> Control Panel HD785-7 | F57: 1 | G57: PCS | H57: H57121 | I57: =IFERROR(INDEX(POP!$I:$I,MATCH(H57,POP!$G:$G,0)),"general") -> general | J57: =IFERROR(INDEX(POP!$E:$E,MATCH(H57,POP!$G:$G,0)),"general") -> general | K57: REPLACE CONTROL PANEL | L57: FANDY | M57: RESTU | N57: 200000707306 | O57: DONE FROM BC | P57: =B57 -> 24 Juni 2024 | Q57: 9200012776 | R57: 45464 | T57: 45467 | U57: DO 24733 | V57: 45329 | W57: GMI-0020875 | X57: 45477 | Y57: 45531 | AA57: =AA56+1 -> 50 | AB57: GMIAMMPIK/2024/06/051 | AC57: =IFERROR(INDEX($B:$B,MATCH(AB57,$C:$C,FALSE)),"") -> 24 Juni 2024 | AD57: =INDEX($U:$U,MATCH(AB57,$C:$C,FALSE)) -> DO 24733 | AE57: =IFERROR(INDEX($V:$V,MATCH(AB57,$C:$C,FALSE)),"") -> 45329 | AF57: =IFERROR(INDEX($N:$N,MATCH(AB57,$C:$C,FALSE)),"") -> 200000707306 | AG57: =INDEX($Q:$Q,MATCH(AB57,$C:$C,FALSE)) -> 9200012776 | AH57: =IFERROR(INDEX($S:$S,MATCH(AB57,$C:$C,FALSE)),"") | AI57: =IFERROR(INDEX($T:$T,MATCH(AB57,$C:$C,FALSE)),"") -> 45467 | AJ57: =INDEX($W:$W,MATCH(AB57,$C:$C,FALSE)) -> GMI-0020875 | AK57: =IFERROR(INDEX($X:$X,MATCH(AB57,$C:$C,FALSE)),"") -> 45477 | AL57: =INDEX($O:$O,MATCH(AF57,$N:$N,FALSE),"") -> DONE FROM BC | AM57: =INDEX($Y:$Y,MATCH(AB57,$C:$C,FALSE)) -> 45531
A58: =A57+1 -> 51 | B58: 28 Juni 2024 | C58: GMIAMMPIK/2024/06/052 | D58: 11L-1290-ARW | E58: =VLOOKUP(D58,MP!$A$1:$C$14184,2,0) -> LED Combination Lamp Amber Red White | F58: 1 | G58: PCS | H58: F54402 | I58: =IFERROR(INDEX(POP!$I:$I,MATCH(H58,POP!$G:$G,0)),"general") -> general | J58: =IFERROR(INDEX(POP!$E:$E,MATCH(H58,POP!$G:$G,0)),"general") -> general | K58: REPLACE WORKLAMP | L58: FANDY | M58: FAUZI | N58: 200000711924 | O58: DONE FROM BC | P58: =B58 -> 28 Juni 2024 | Q58: 9200013168 | R58: 45472 | T58: 45476 | U58: DO 25150 | V58: 16/7/2024 | W58: GMI-0021204 | X58: 45491 | Y58: 45531 | AA58: =AA57+1 -> 51 | AB58: GMIAMMPIK/2024/06/052 | AC58: =IFERROR(INDEX($B:$B,MATCH(AB58,$C:$C,FALSE)),"") -> 28 Juni 2024 | AD58: =INDEX($U:$U,MATCH(AB58,$C:$C,FALSE)) -> DO 25150 | AE58: =IFERROR(INDEX($V:$V,MATCH(AB58,$C:$C,FALSE)),"") -> 16/7/2024 | AF58: =IFERROR(INDEX($N:$N,MATCH(AB58,$C:$C,FALSE)),"") -> 200000711924 | AG58: =INDEX($Q:$Q,MATCH(AB58,$C:$C,FALSE)) -> 9200013168 | AH58: =IFERROR(INDEX($S:$S,MATCH(AB58,$C:$C,FALSE)),"") | AI58: =IFERROR(INDEX($T:$T,MATCH(AB58,$C:$C,FALSE)),"") -> 45476 | AJ58: =INDEX($W:$W,MATCH(AB58,$C:$C,FALSE)) -> GMI-0021204 | AK58: =IFERROR(INDEX($X:$X,MATCH(AB58,$C:$C,FALSE)),"") -> 45491 | AL58: =INDEX($O:$O,MATCH(AF58,$N:$N,FALSE),"") -> DONE FROM BC | AM58: =INDEX($Y:$Y,MATCH(AB58,$C:$C,FALSE)) -> 45531
A59: =A58+1 -> 52 | B59: 28 Juni 2024 | C59: GMIAMMPIK/2024/06/053 | D59: 11L-3024 | E59: =VLOOKUP(D59,MP!$A$1:$C$14184,2,0) -> LED FLood Light 6 Eyes 18 Watt 10-30 VDC | F59: 1 | G59: PCS | H59: H57072 | I59: =IFERROR(INDEX(POP!$I:$I,MATCH(H59,POP!$G:$G,0)),"general") -> general | J59: =IFERROR(INDEX(POP!$E:$E,MATCH(H59,POP!$G:$G,0)),"general") -> general | K59: REPLACE WORKLAMP | L59: FANDY | M59: FAUZI | N59: 200000711981 | O59: DONE FROM BC | P59: =B59 -> 28 Juni 2024 | Q59: 9200013170 | R59: 45472 | T59: 45476 | U59: DO 24969 | V59: 45572 | W59: GMI-0021088 | X59: 45485 | Y59: 45531 | AA59: =AA58+1 -> 52 | AB59: GMIAMMPIK/2024/06/053 | AC59: =IFERROR(INDEX($B:$B,MATCH(AB59,$C:$C,FALSE)),"") -> 28 Juni 2024 | AD59: =INDEX($U:$U,MATCH(AB59,$C:$C,FALSE)) -> DO 24969 | AE59: =IFERROR(INDEX($V:$V,MATCH(AB59,$C:$C,FALSE)),"") -> 45572 | AF59: =IFERROR(INDEX($N:$N,MATCH(AB59,$C:$C,FALSE)),"") -> 200000711981 | AG59: =INDEX($Q:$Q,MATCH(AB59,$C:$C,FALSE)) -> 9200013170 | AH59: =IFERROR(INDEX($S:$S,MATCH(AB59,$C:$C,FALSE)),"") | AI59: =IFERROR(INDEX($T:$T,MATCH(AB59,$C:$C,FALSE)),"") -> 45476 | AJ59: =INDEX($W:$W,MATCH(AB59,$C:$C,FALSE)) -> GMI-0021088 | AK59: =IFERROR(INDEX($X:$X,MATCH(AB59,$C:$C,FALSE)),"") -> 45485 | AL59: =INDEX($O:$O,MATCH(AF59,$N:$N,FALSE),"") -> DONE FROM BC | AM59: =INDEX($Y:$Y,MATCH(AB59,$C:$C,FALSE)) -> 45531
A60: =A59+1 -> 53 | B60: 04 Juli 2024 | C60: GMIAMMPIK/2024/07/054 | D60: 11L-3024 | E60: =VLOOKUP(D60,MP!$A$1:$C$14184,2,0) -> LED FLood Light 6 Eyes 18 Watt 10-30 VDC | F60: 2 | G60: PCS | H60: F54078 | I60: =IFERROR(INDEX(POP!$I:$I,MATCH(H60,POP!$G:$G,0)),"general") -> general | J60: =IFERROR(INDEX(POP!$E:$E,MATCH(H60,POP!$G:$G,0)),"general") -> general | K60: REPLACE WORKLAMP | L60: FANDY | M60: WIWIK | N60: 200000713970 | O60: DONE FROM BC | P60: =B60 -> 04 Juli 2024 | Q60: 9200013413 | R60: 45477 | T60: 45478 | U60: DO 25011 | V60: 45603 | W60: GMI-0021089 | X60: 45485 | Y60: 45531 | AA60: =AA59+1 -> 53 | AB60: GMIAMMPIK/2024/07/054 | AC60: =IFERROR(INDEX($B:$B,MATCH(AB60,$C:$C,FALSE)),"") -> 04 Juli 2024 | AD60: =INDEX($U:$U,MATCH(AB60,$C:$C,FALSE)) -> DO 25011 | AE60: =IFERROR(INDEX($V:$V,MATCH(AB60,$C:$C,FALSE)),"") -> 45603 | AF60: =IFERROR(INDEX($N:$N,MATCH(AB60,$C:$C,FALSE)),"") -> 200000713970 | AG60: =INDEX($Q:$Q,MATCH(AB60,$C:$C,FALSE)) -> 9200013413 | AH60: =IFERROR(INDEX($S:$S,MATCH(AB60,$C:$C,FALSE)),"") | AI60: =IFERROR(INDEX($T:$T,MATCH(AB60,$C:$C,FALSE)),"") -> 45478 | AJ60: =INDEX($W:$W,MATCH(AB60,$C:$C,FALSE)) -> GMI-0021089 | AK60: =IFERROR(INDEX($X:$X,MATCH(AB60,$C:$C,FALSE)),"") -> 45485 | AL60: =INDEX($O:$O,MATCH(AF60,$N:$N,FALSE),"") -> DONE FROM BC | AM60: =INDEX($Y:$Y,MATCH(AB60,$C:$C,FALSE)) -> 45531
A61: =A60+1 -> 54 | B61: 05 Juli 2024 | C61: GMIAMMPIK/2024/07/055 | D61: 3L4-7ASA | E61: =VLOOKUP(D61,MP!$A$1:$C$14184,2,0) -> LED (SMD Led) Strobe Beacon Amber : 12-24VDC with Alumunium screw base | F61: 1 | G61: PCS | H61: PLTAM15 | I61: =IFERROR(INDEX(POP!$I:$I,MATCH(H61,POP!$G:$G,0)),"general") -> general | J61: =IFERROR(INDEX(POP!$E:$E,MATCH(H61,POP!$G:$G,0)),"general") -> general | K61: REPLACE WORKLAMP | L61: FANDY | M61: WIWIK | N61: 200000714252 | O61: DONE FROM BC | P61: =B61 -> 05 Juli 2024 | Q61: 9200013492 | R61: 45478 | T61: 45483 | U61: DO 25195 | V61: 17/7/2024 | W61: GMI-0021203 | X61: 45491 | Y61: 45531 | AA61: =AA60+1 -> 54 | AB61: GMIAMMPIK/2024/07/055 | AC61: =IFERROR(INDEX($B:$B,MATCH(AB61,$C:$C,FALSE)),"") -> 05 Juli 2024 | AD61: =INDEX($U:$U,MATCH(AB61,$C:$C,FALSE)) -> DO 25195 | AE61: =IFERROR(INDEX($V:$V,MATCH(AB61,$C:$C,FALSE)),"") -> 17/7/2024 | AF61: =IFERROR(INDEX($N:$N,MATCH(AB61,$C:$C,FALSE)),"") -> 200000714252 | AG61: =INDEX($Q:$Q,MATCH(AB61,$C:$C,FALSE)) -> 9200013492 | AH61: =IFERROR(INDEX($S:$S,MATCH(AB61,$C:$C,FALSE)),"") | AI61: =IFERROR(INDEX($T:$T,MATCH(AB61,$C:$C,FALSE)),"") -> 45483 | AJ61: =INDEX($W:$W,MATCH(AB61,$C:$C,FALSE)) -> GMI-0021203 | AK61: =IFERROR(INDEX($X:$X,MATCH(AB61,$C:$C,FALSE)),"") -> 45491 | AL61: =INDEX($O:$O,MATCH(AF61,$N:$N,FALSE),"") -> DONE FROM BC | AM61: =INDEX($Y:$Y,MATCH(AB61,$C:$C,FALSE)) -> 45531
A62: =A61+1 -> 55 | B62: 08 Juli 2024 | C62: GMIAMMPIK/2024/07/056 | D62: 3L4-7ASA | E62: =VLOOKUP(D62,MP!$A$1:$C$14184,2,0) -> LED (SMD Led) Strobe Beacon Amber : 12-24VDC with Alumunium screw base | F62: 6 | G62: PCS | H62: PLTAM15 | I62: =IFERROR(INDEX(POP!$I:$I,MATCH(H62,POP!$G:$G,0)),"general") -> general | J62: =IFERROR(INDEX(POP!$E:$E,MATCH(H62,POP!$G:$G,0)),"general") -> general | K62: REPLACE WORKLAMP | L62: FANDY | M62: WIWIK | N62: 200000715968 | O62: DONE FROM BC | P62: =B62 -> 08 Juli 2024 | Q62: 9200013626 | R62: 45482 | T62: 45483 | U62: DO 25196 | V62: 17/7/2024 | W62: GMI-0021205 | X62: 45491 | Y62: 45531 | AA62: =AA61+1 -> 55 | AB62: GMIAMMPIK/2024/07/056 | AC62: =IFERROR(INDEX($B:$B,MATCH(AB62,$C:$C,FALSE)),"") -> 08 Juli 2024 | AD62: =INDEX($U:$U,MATCH(AB62,$C:$C,FALSE)) -> DO 25196 | AE62: =IFERROR(INDEX($V:$V,MATCH(AB62,$C:$C,FALSE)),"") -> 17/7/2024 | AF62: =IFERROR(INDEX($N:$N,MATCH(AB62,$C:$C,FALSE)),"") -> 200000715968 | AG62: =INDEX($Q:$Q,MATCH(AB62,$C:$C,FALSE)) -> 9200013626 | AH62: =IFERROR(INDEX($S:$S,MATCH(AB62,$C:$C,FALSE)),"") | AI62: =IFERROR(INDEX($T:$T,MATCH(AB62,$C:$C,FALSE)),"") -> 45483 | AJ62: =INDEX($W:$W,MATCH(AB62,$C:$C,FALSE)) -> GMI-0021205 | AK62: =IFERROR(INDEX($X:$X,MATCH(AB62,$C:$C,FALSE)),"") -> 45491 | AL62: =INDEX($O:$O,MATCH(AF62,$N:$N,FALSE),"") -> DONE FROM BC | AM62: =INDEX($Y:$Y,MATCH(AB62,$C:$C,FALSE)) -> 45531
A63: =A62+1 -> 56 | B63: 09 Juli 2024 | C63: GMIAMMPIK/2024/07/057 | D63: 11L-3024 | E63: =VLOOKUP(D63,MP!$A$1:$C$14184,2,0) -> LED FLood Light 6 Eyes 18 Watt 10-30 VDC | F63: 1 | G63: PCS | H63: E53904 | I63: =IFERROR(INDEX(POP!$I:$I,MATCH(H63,POP!$G:$G,0)),"general") -> general | J63: =IFERROR(INDEX(POP!$E:$E,MATCH(H63,POP!$G:$G,0)),"general") -> general | K63: REPLACE WORKLAMP | L63: FANDY | M63: WIWIK | N63: 200000716425 | O63: DONE FROM BC | P63: =B63 -> 09 Juli 2024 | Q63: 9200013706 | R63: 45483 | T63: 45483 | U63: DO 25097 | V63: 15/7/2024 | W63: GMI-0021202 | X63: 45491 | Y63: 45531 | AA63: =AA62+1 -> 56 | AB63: GMIAMMPIK/2024/07/057 | AC63: =IFERROR(INDEX($B:$B,MATCH(AB63,$C:$C,FALSE)),"") -> 09 Juli 2024 | AD63: =INDEX($U:$U,MATCH(AB63,$C:$C,FALSE)) -> DO 25097 | AE63: =IFERROR(INDEX($V:$V,MATCH(AB63,$C:$C,FALSE)),"") -> 15/7/2024 | AF63: =IFERROR(INDEX($N:$N,MATCH(AB63,$C:$C,FALSE)),"") -> 200000716425 | AG63: =INDEX($Q:$Q,MATCH(AB63,$C:$C,FALSE)) -> 9200013706 | AH63: =IFERROR(INDEX($S:$S,MATCH(AB63,$C:$C,FALSE)),"") | AI63: =IFERROR(INDEX($T:$T,MATCH(AB63,$C:$C,FALSE)),"") -> 45483 | AJ63: =INDEX($W:$W,MATCH(AB63,$C:$C,FALSE)) -> GMI-0021202 | AK63: =IFERROR(INDEX($X:$X,MATCH(AB63,$C:$C,FALSE)),"") -> 45491 | AL63: =INDEX($O:$O,MATCH(AF63,$N:$N,FALSE),"") -> DONE FROM BC | AM63: =INDEX($Y:$Y,MATCH(AB63,$C:$C,FALSE)) -> 45531
A64: =A63+1 -> 57 | B64: 17 Juli 2024 | C64: GMIAMMPIK/2024/07/058 | D64: 11L-3024 | E64: =VLOOKUP(D64,MP!$A$1:$C$14184,2,0) -> LED FLood Light 6 Eyes 18 Watt 10-30 VDC | F64: 1 | G64: PCS | H64: LT2512PPA | I64: =IFERROR(INDEX(POP!$I:$I,MATCH(H64,POP!$G:$G,0)),"general") -> general | J64: =IFERROR(INDEX(POP!$E:$E,MATCH(H64,POP!$G:$G,0)),"general") -> general | K64: REPLACE WORKLAMP | L64: FANDY | M64: WIWIK | N64: 200000719331 | O64: DONE FROM BC | P64: =B64 -> 17 Juli 2024 | Q64: 9200014081 | R64: 45491 | T64: 45491 | U64: DO 25286 | V64: 20/7/2024 | W64: GMI-0021357 | X64: 45495 | Y64: 45555 | AA64: =AA63+1 -> 57 | AB64: GMIAMMPIK/2024/07/058 | AC64: =IFERROR(INDEX($B:$B,MATCH(AB64,$C:$C,FALSE)),"") -> 17 Juli 2024 | AD64: =INDEX($U:$U,MATCH(AB64,$C:$C,FALSE)) -> DO 25286 | AE64: =IFERROR(INDEX($V:$V,MATCH(AB64,$C:$C,FALSE)),"") -> 20/7/2024 | AF64: =IFERROR(INDEX($N:$N,MATCH(AB64,$C:$C,FALSE)),"") -> 200000719331 | AG64: =INDEX($Q:$Q,MATCH(AB64,$C:$C,FALSE)) -> 9200014081 | AH64: =IFERROR(INDEX($S:$S,MATCH(AB64,$C:$C,FALSE)),"") | AI64: =IFERROR(INDEX($T:$T,MATCH(AB64,$C:$C,FALSE)),"") -> 45491 | AJ64: =INDEX($W:$W,MATCH(AB64,$C:$C,FALSE)) -> GMI-0021357 | AK64: =IFERROR(INDEX($X:$X,MATCH(AB64,$C:$C,FALSE)),"") -> 45495 | AL64: =INDEX($O:$O,MATCH(AF64,$N:$N,FALSE),"") -> DONE FROM BC | AM64: =INDEX($Y:$Y,MATCH(AB64,$C:$C,FALSE)) -> 45555
A65: =A64+1 -> 58 | B65: 18 Juli 2024 | C65: GMIAMMPIK/2024/07/059 | D65: 11L-3024 | E65: =VLOOKUP(D65,MP!$A$1:$C$14184,2,0) -> LED FLood Light 6 Eyes 18 Watt 10-30 VDC | F65: 2 | G65: PCS | H65: F54406 | I65: =IFERROR(INDEX(POP!$I:$I,MATCH(H65,POP!$G:$G,0)),"general") -> general | J65: =IFERROR(INDEX(POP!$E:$E,MATCH(H65,POP!$G:$G,0)),"general") -> general | K65: REPLACE WORKLAMP | L65: FANDY | M65: WIWIK | N65: 200000720062 | O65: DONE FROM BC | P65: =B65 -> 18 Juli 2024 | Q65: 9200014162 | R65: 45492 | T65: 20/7/2024 | U65: DO 25329 | V65: 22/7/2024 | W65: GMI-0021404 | X65: 45497 | Y65: 45555 | AA65: =AA64+1 -> 58 | AB65: GMIAMMPIK/2024/07/059 | AC65: =IFERROR(INDEX($B:$B,MATCH(AB65,$C:$C,FALSE)),"") -> 18 Juli 2024 | AD65: =INDEX($U:$U,MATCH(AB65,$C:$C,FALSE)) -> DO 25329 | AE65: =IFERROR(INDEX($V:$V,MATCH(AB65,$C:$C,FALSE)),"") -> 22/7/2024 | AF65: =IFERROR(INDEX($N:$N,MATCH(AB65,$C:$C,FALSE)),"") -> 200000720062 | AG65: =INDEX($Q:$Q,MATCH(AB65,$C:$C,FALSE)) -> 9200014162 | AH65: =IFERROR(INDEX($S:$S,MATCH(AB65,$C:$C,FALSE)),"") | AI65: =IFERROR(INDEX($T:$T,MATCH(AB65,$C:$C,FALSE)),"") -> 20/7/2024 | AJ65: =INDEX($W:$W,MATCH(AB65,$C:$C,FALSE)) -> GMI-0021404 | AK65: =IFERROR(INDEX($X:$X,MATCH(AB65,$C:$C,FALSE)),"") -> 45497 | AL65: =INDEX($O:$O,MATCH(AF65,$N:$N,FALSE),"") -> DONE FROM BC | AM65: =INDEX($Y:$Y,MATCH(AB65,$C:$C,FALSE)) -> 45555
A66: =A65+1 -> 59 | B66: 20 Juli 2024 | C66: GMIAMMPIK/2024/07/060 | D66: 3L4-7ASA | E66: =VLOOKUP(D66,MP!$A$1:$C$14184,2,0) -> LED (SMD Led) Strobe Beacon Amber : 12-24VDC with Alumunium screw base | F66: 2 | G66: PCS | H66: WT2522PPA | I66: =IFERROR(INDEX(POP!$I:$I,MATCH(H66,POP!$G:$G,0)),"general") -> general | J66: =IFERROR(INDEX(POP!$E:$E,MATCH(H66,POP!$G:$G,0)),"general") -> general | K66: REPLACE WORKLAMP | L66: FANDY | M66: WIWIK | N66: 200000720673 | O66: DONE FROM BC | P66: =B66 -> 20 Juli 2024 | Q66: 9200014255 | U66: DO 25584 | V66: 30/7/2024 | W66: GMI-0021661 | X66: 45507 | Y66: 45555 | AA66: =AA65+1 -> 59 | AB66: GMIAMMPIK/2024/07/060 | AC66: =IFERROR(INDEX($B:$B,MATCH(AB66,$C:$C,FALSE)),"") -> 20 Juli 2024 | AD66: =INDEX($U:$U,MATCH(AB66,$C:$C,FALSE)) -> DO 25584 | AE66: =IFERROR(INDEX($V:$V,MATCH(AB66,$C:$C,FALSE)),"") -> 30/7/2024 | AF66: =IFERROR(INDEX($N:$N,MATCH(AB66,$C:$C,FALSE)),"") -> 200000720673 | AG66: =INDEX($Q:$Q,MATCH(AB66,$C:$C,FALSE)) -> 9200014255 | AH66: =IFERROR(INDEX($S:$S,MATCH(AB66,$C:$C,FALSE)),"") | AI66: =IFERROR(INDEX($T:$T,MATCH(AB66,$C:$C,FALSE)),"") | AJ66: =INDEX($W:$W,MATCH(AB66,$C:$C,FALSE)) -> GMI-0021661 | AK66: =IFERROR(INDEX($X:$X,MATCH(AB66,$C:$C,FALSE)),"") -> 45507 | AL66: =INDEX($O:$O,MATCH(AF66,$N:$N,FALSE),"") -> DONE FROM BC | AM66: =INDEX($Y:$Y,MATCH(AB66,$C:$C,FALSE)) -> 45555
A67: =A66+1 -> 60 | B67: 21 Juli 2024 | C67: GMIAMMPIK/2024/07/061 | D67: 11L-3024 | E67: =VLOOKUP(D67,MP!$A$1:$C$14184,2,0) -> LED FLood Light 6 Eyes 18 Watt 10-30 VDC | F67: 2 | G67: PCS | H67: F54039 | I67: =IFERROR(INDEX(POP!$I:$I,MATCH(H67,POP!$G:$G,0)),"general") -> general | J67: =IFERROR(INDEX(POP!$E:$E,MATCH(H67,POP!$G:$G,0)),"general") -> general | K67: REPLACE WORKLAMP | L67: FANDY | M67: WIWIK | N67: 200000721443 | O67: DONE FROM BC | P67: =B67 -> 21 Juli 2024 | Q67: 9200014287 | U67: DO 25341 | V67: 23/7/2024 | W67: GMI-0021405 | X67: 45497 | Y67: 45555 | AA67: =AA66+1 -> 60 | AB67: GMIAMMPIK/2024/07/061 | AC67: =IFERROR(INDEX($B:$B,MATCH(AB67,$C:$C,FALSE)),"") -> 21 Juli 2024 | AD67: =INDEX($U:$U,MATCH(AB67,$C:$C,FALSE)) -> DO 25341 | AE67: =IFERROR(INDEX($V:$V,MATCH(AB67,$C:$C,FALSE)),"") -> 23/7/2024 | AF67: =IFERROR(INDEX($N:$N,MATCH(AB67,$C:$C,FALSE)),"") -> 200000721443 | AG67: =INDEX($Q:$Q,MATCH(AB67,$C:$C,FALSE)) -> 9200014287 | AH67: =IFERROR(INDEX($S:$S,MATCH(AB67,$C:$C,FALSE)),"") | AI67: =IFERROR(INDEX($T:$T,MATCH(AB67,$C:$C,FALSE)),"") | AJ67: =INDEX($W:$W,MATCH(AB67,$C:$C,FALSE)) -> GMI-0021405 | AK67: =IFERROR(INDEX($X:$X,MATCH(AB67,$C:$C,FALSE)),"") -> 45497 | AL67: =INDEX($O:$O,MATCH(AF67,$N:$N,FALSE),"") -> DONE FROM BC | AM67: =INDEX($Y:$Y,MATCH(AB67,$C:$C,FALSE)) -> 45555
A68: =A67+1 -> 61 | B68: 23 Juli 2024 | C68: GMIAMMPIK/2024/07/062 | D68: 3L4-7ASA | E68: =VLOOKUP(D68,MP!$A$1:$C$14184,2,0) -> LED (SMD Led) Strobe Beacon Amber : 12-24VDC with Alumunium screw base | F68: 1 | G68: PCS | H68: H57123 | I68: =IFERROR(INDEX(POP!$I:$I,MATCH(H68,POP!$G:$G,0)),"general") -> general | J68: =IFERROR(INDEX(POP!$E:$E,MATCH(H68,POP!$G:$G,0)),"general") -> general | K68: REPLACE WORKLAMP | L68: FANDY | M68: WIWIK | N68: 200000722102 | O68: DONE FROM BC | P68: =B68 -> 23 Juli 2024 | Q68: 9200014422 | R68: 45497 | T68: 45498 | U68: DO 25555 | V68: 29/7/2024 | W68: GMI-0021660 | X68: 45507 | Y68: 45555 | AA68: =AA67+1 -> 61 | AB68: GMIAMMPIK/2024/07/062 | AC68: =IFERROR(INDEX($B:$B,MATCH(AB68,$C:$C,FALSE)),"") -> 23 Juli 2024 | AD68: =INDEX($U:$U,MATCH(AB68,$C:$C,FALSE)) -> DO 25555 | AE68: =IFERROR(INDEX($V:$V,MATCH(AB68,$C:$C,FALSE)),"") -> 29/7/2024 | AF68: =IFERROR(INDEX($N:$N,MATCH(AB68,$C:$C,FALSE)),"") -> 200000722102 | AG68: =INDEX($Q:$Q,MATCH(AB68,$C:$C,FALSE)) -> 9200014422 | AH68: =IFERROR(INDEX($S:$S,MATCH(AB68,$C:$C,FALSE)),"") | AI68: =IFERROR(INDEX($T:$T,MATCH(AB68,$C:$C,FALSE)),"") -> 45498 | AJ68: =INDEX($W:$W,MATCH(AB68,$C:$C,FALSE)) -> GMI-0021660 | AK68: =IFERROR(INDEX($X:$X,MATCH(AB68,$C:$C,FALSE)),"") -> 45507 | AL68: =INDEX($O:$O,MATCH(AF68,$N:$N,FALSE),"") -> DONE FROM BC | AM68: =INDEX($Y:$Y,MATCH(AB68,$C:$C,FALSE)) -> 45555
A69: =A68+1 -> 62 | B69: 24 Juli 2024 | C69: GMIAMMPIK/2024/07/063 | D69: 11L-1290-ARW | E69: =VLOOKUP(D69,MP!$A$1:$C$14184,2,0) -> LED Combination Lamp Amber Red White | F69: 2 | G69: PCS | H69: LT52501 | I69: =IFERROR(INDEX(POP!$I:$I,MATCH(H69,POP!$G:$G,0)),"general") -> general | J69: =IFERROR(INDEX(POP!$E:$E,MATCH(H69,POP!$G:$G,0)),"general") -> general | K69: REPLACE WORKLAMP | L69: FANDY | M69: RESTU | N69: 200000722669 | O69: DONE FROM BC | P69: =B69 -> 24 Juli 2024 | Q69: 9200014468 | R69: 45497 | T69: 45498 | U69: DO 25600 | V69: 30/7/2024 | W69: GMI-0021663 | X69: 45507 | Y69: 45555 | AA69: =AA68+1 -> 62 | AB69: GMIAMMPIK/2024/07/063 | AC69: =IFERROR(INDEX($B:$B,MATCH(AB69,$C:$C,FALSE)),"") -> 24 Juli 2024 | AD69: =INDEX($U:$U,MATCH(AB69,$C:$C,FALSE)) -> DO 25600 | AE69: =IFERROR(INDEX($V:$V,MATCH(AB69,$C:$C,FALSE)),"") -> 30/7/2024 | AF69: =IFERROR(INDEX($N:$N,MATCH(AB69,$C:$C,FALSE)),"") -> 200000722669 | AG69: =INDEX($Q:$Q,MATCH(AB69,$C:$C,FALSE)) -> 9200014468 | AH69: =IFERROR(INDEX($S:$S,MATCH(AB69,$C:$C,FALSE)),"") | AI69: =IFERROR(INDEX($T:$T,MATCH(AB69,$C:$C,FALSE)),"") -> 45498 | AJ69: =INDEX($W:$W,MATCH(AB69,$C:$C,FALSE)) -> GMI-0021663 | AK69: =IFERROR(INDEX($X:$X,MATCH(AB69,$C:$C,FALSE)),"") -> 45507 | AL69: =INDEX($O:$O,MATCH(AF69,$N:$N,FALSE),"") -> DONE FROM BC | AM69: =INDEX($Y:$Y,MATCH(AB69,$C:$C,FALSE)) -> 45555
A70: =A69+1 -> 63 | B70: 24 Juli 2024 | C70: GMIAMMPIK/2024/07/064 | D70: 11L-3024 | E70: =VLOOKUP(D70,MP!$A$1:$C$14184,2,0) -> LED FLood Light 6 Eyes 18 Watt 10-30 VDC | F70: 4 | G70: PCS | H70: WT2522PPA | I70: =IFERROR(INDEX(POP!$I:$I,MATCH(H70,POP!$G:$G,0)),"general") -> general | J70: =IFERROR(INDEX(POP!$E:$E,MATCH(H70,POP!$G:$G,0)),"general") -> general | K70: REPLACE WORKLAMP | L70: FANDY | M70: WIWIK | N70: 200000722431 | O70: DONE FROM BC | P70: =B70 -> 24 Juli 2024 | Q70: 9200014481 | R70: 45497 | T70: 45498 | U70: DO 25512 | V70: 29/7/2024 | W70: GMI-0021657 | X70: 45507 | Y70: 45555 | AA70: =AA69+1 -> 63 | AB70: GMIAMMPIK/2024/07/064 | AC70: =IFERROR(INDEX($B:$B,MATCH(AB70,$C:$C,FALSE)),"") -> 24 Juli 2024 | AD70: =INDEX($U:$U,MATCH(AB70,$C:$C,FALSE)) -> DO 25512 | AE70: =IFERROR(INDEX($V:$V,MATCH(AB70,$C:$C,FALSE)),"") -> 29/7/2024 | AF70: =IFERROR(INDEX($N:$N,MATCH(AB70,$C:$C,FALSE)),"") -> 200000722431 | AG70: =INDEX($Q:$Q,MATCH(AB70,$C:$C,FALSE)) -> 9200014481 | AH70: =IFERROR(INDEX($S:$S,MATCH(AB70,$C:$C,FALSE)),"") | AI70: =IFERROR(INDEX($T:$T,MATCH(AB70,$C:$C,FALSE)),"") -> 45498 | AJ70: =INDEX($W:$W,MATCH(AB70,$C:$C,FALSE)) -> GMI-0021657 | AK70: =IFERROR(INDEX($X:$X,MATCH(AB70,$C:$C,FALSE)),"") -> 45507 | AL70: =INDEX($O:$O,MATCH(AF70,$N:$N,FALSE),"") -> DONE FROM BC | AM70: =INDEX($Y:$Y,MATCH(AB70,$C:$C,FALSE)) -> 45555
A71: =A70+1 -> 64 | B71: 24 Juli 2024 | C71: GMIAMMPIK/2024/07/065 | D71: 11L-3024 | E71: =VLOOKUP(D71,MP!$A$1:$C$14184,2,0) -> LED FLood Light 6 Eyes 18 Watt 10-30 VDC | F71: 1 | G71: PCS | H71: F54040 | I71: =IFERROR(INDEX(POP!$I:$I,MATCH(H71,POP!$G:$G,0)),"general") -> general | J71: =IFERROR(INDEX(POP!$E:$E,MATCH(H71,POP!$G:$G,0)),"general") -> general | K71: REPLACE WORKLAMP | L71: FANDY | M71: WIWIK | N71: 200000722909 | O71: DONE FROM BC | P71: =B71 -> 24 Juli 2024 | Q71: 9200014509 | R71: 45497 | T71: 45498 | U71: DO 25516 | V71: 29/7/2024 | W71: GMI-0021658 | X71: 45507 | Y71: 45555 | AA71: =AA70+1 -> 64 | AB71: GMIAMMPIK/2024/07/065 | AC71: =IFERROR(INDEX($B:$B,MATCH(AB71,$C:$C,FALSE)),"") -> 24 Juli 2024 | AD71: =INDEX($U:$U,MATCH(AB71,$C:$C,FALSE)) -> DO 25516 | AE71: =IFERROR(INDEX($V:$V,MATCH(AB71,$C:$C,FALSE)),"") -> 29/7/2024 | AF71: =IFERROR(INDEX($N:$N,MATCH(AB71,$C:$C,FALSE)),"") -> 200000722909 | AG71: =INDEX($Q:$Q,MATCH(AB71,$C:$C,FALSE)) -> 9200014509 | AH71: =IFERROR(INDEX($S:$S,MATCH(AB71,$C:$C,FALSE)),"") | AI71: =IFERROR(INDEX($T:$T,MATCH(AB71,$C:$C,FALSE)),"") -> 45498 | AJ71: =INDEX($W:$W,MATCH(AB71,$C:$C,FALSE)) -> GMI-0021658 | AK71: =IFERROR(INDEX($X:$X,MATCH(AB71,$C:$C,FALSE)),"") -> 45507 | AL71: =INDEX($O:$O,MATCH(AF71,$N:$N,FALSE),"") -> DONE FROM BC | AM71: =INDEX($Y:$Y,MATCH(AB71,$C:$C,FALSE)) -> 45555
A72: =A71+1 -> 65 | B72: 25 Juli 2024 | C72: GMIAMMPIK/2024/07/066 | D72: 11L-3024 | E72: =VLOOKUP(D72,MP!$A$1:$C$14184,2,0) -> LED FLood Light 6 Eyes 18 Watt 10-30 VDC | F72: 1 | G72: PCS | H72: WT2522PPA | I72: =IFERROR(INDEX(POP!$I:$I,MATCH(H72,POP!$G:$G,0)),"general") -> general | J72: =IFERROR(INDEX(POP!$E:$E,MATCH(H72,POP!$G:$G,0)),"general") -> general | K72: REPLACE WORKLAMP | L72: FANDY | M72: FAUZI | N72: 200000722895 | O72: DONE FROM BC | P72: =B72 -> 25 Juli 2024 | Q72: 9200014538 | R72: 45497 | T72: 45498 | U72: DO 25517 | V72: 29/7/2024 | W72: GMI-0021659 | X72: 45507 | Y72: 45555 | AA72: =AA71+1 -> 65 | AB72: GMIAMMPIK/2024/07/066 | AC72: =IFERROR(INDEX($B:$B,MATCH(AB72,$C:$C,FALSE)),"") -> 25 Juli 2024 | AD72: =INDEX($U:$U,MATCH(AB72,$C:$C,FALSE)) -> DO 25517 | AE72: =IFERROR(INDEX($V:$V,MATCH(AB72,$C:$C,FALSE)),"") -> 29/7/2024 | AF72: =IFERROR(INDEX($N:$N,MATCH(AB72,$C:$C,FALSE)),"") -> 200000722895 | AG72: =INDEX($Q:$Q,MATCH(AB72,$C:$C,FALSE)) -> 9200014538 | AH72: =IFERROR(INDEX($S:$S,MATCH(AB72,$C:$C,FALSE)),"") | AI72: =IFERROR(INDEX($T:$T,MATCH(AB72,$C:$C,FALSE)),"") -> 45498 | AJ72: =INDEX($W:$W,MATCH(AB72,$C:$C,FALSE)) -> GMI-0021659 | AK72: =IFERROR(INDEX($X:$X,MATCH(AB72,$C:$C,FALSE)),"") -> 45507 | AL72: =INDEX($O:$O,MATCH(AF72,$N:$N,FALSE),"") -> DONE FROM BC | AM72: =INDEX($Y:$Y,MATCH(AB72,$C:$C,FALSE)) -> 45555
A73: =A72+1 -> 66 | B73: 26 Juli 2024 | C73: GMIAMMPIK/2024/07/067 | D73: 11L-1290-ARW | E73: =VLOOKUP(D73,MP!$A$1:$C$14184,2,0) -> LED Combination Lamp Amber Red White | F73: 1 | G73: PCS | H73: DT3636PPA | I73: =IFERROR(INDEX(POP!$I:$I,MATCH(H73,POP!$G:$G,0)),"general") -> general | J73: =IFERROR(INDEX(POP!$E:$E,MATCH(H73,POP!$G:$G,0)),"general") -> general | K73: REPLACE WORKLAMP | L73: FANDY | M73: WIWIK | N73: 200000723063 | O73: DONE FROM BC | P73: =B73 -> 26 Juli 2024 | Q73: 9200014635 | R73: 45499 | T73: 45499 | U73: DO 25598 | V73: 30/7/2024 | W73: GMI-0021662 | X73: 45507 | Y73: 45555 | AA73: =AA72+1 -> 66 | AB73: GMIAMMPIK/2024/07/067 | AC73: =IFERROR(INDEX($B:$B,MATCH(AB73,$C:$C,FALSE)),"") -> 26 Juli 2024 | AD73: =INDEX($U:$U,MATCH(AB73,$C:$C,FALSE)) -> DO 25598 | AE73: =IFERROR(INDEX($V:$V,MATCH(AB73,$C:$C,FALSE)),"") -> 30/7/2024 | AF73: =IFERROR(INDEX($N:$N,MATCH(AB73,$C:$C,FALSE)),"") -> 200000723063 | AG73: =INDEX($Q:$Q,MATCH(AB73,$C:$C,FALSE)) -> 9200014635 | AH73: =IFERROR(INDEX($S:$S,MATCH(AB73,$C:$C,FALSE)),"") | AI73: =IFERROR(INDEX($T:$T,MATCH(AB73,$C:$C,FALSE)),"") -> 45499 | AJ73: =INDEX($W:$W,MATCH(AB73,$C:$C,FALSE)) -> GMI-0021662 | AK73: =IFERROR(INDEX($X:$X,MATCH(AB73,$C:$C,FALSE)),"") -> 45507 | AL73: =INDEX($O:$O,MATCH(AF73,$N:$N,FALSE),"") -> DONE FROM BC | AM73: =INDEX($Y:$Y,MATCH(AB73,$C:$C,FALSE)) -> 45555
A74: =A73+1 -> 67 | B74: 26 Juli 2024 | C74: GMIAMMPIK/2024/07/068 | D74: 11L-1290-ARW | E74: =VLOOKUP(D74,MP!$A$1:$C$14184,2,0) -> LED Combination Lamp Amber Red White | F74: 1 | G74: PCS | H74: DA4827PPA | I74: =IFERROR(INDEX(POP!$I:$I,MATCH(H74,POP!$G:$G,0)),"general") -> general | J74: =IFERROR(INDEX(POP!$E:$E,MATCH(H74,POP!$G:$G,0)),"general") -> general | K74: REPLACE WORKLAMP | L74: FANDY | M74: WIWIK | N74: 200000723794 | O74: DONE FROM BC | P74: =B74 -> 26 Juli 2024 | Q74: 9200014636 | R74: 45500 | T74: 45504 | U74: DO 25702 | V74: 45330 | W74: GMI-0021664 | X74: 45507 | Y74: 45555 | AA74: =AA73+1 -> 67 | AB74: GMIAMMPIK/2024/07/068 | AC74: =IFERROR(INDEX($B:$B,MATCH(AB74,$C:$C,FALSE)),"") -> 26 Juli 2024 | AD74: =INDEX($U:$U,MATCH(AB74,$C:$C,FALSE)) -> DO 25702 | AE74: =IFERROR(INDEX($V:$V,MATCH(AB74,$C:$C,FALSE)),"") -> 45330 | AF74: =IFERROR(INDEX($N:$N,MATCH(AB74,$C:$C,FALSE)),"") -> 200000723794 | AG74: =INDEX($Q:$Q,MATCH(AB74,$C:$C,FALSE)) -> 9200014636 | AH74: =IFERROR(INDEX($S:$S,MATCH(AB74,$C:$C,FALSE)),"") | AI74: =IFERROR(INDEX($T:$T,MATCH(AB74,$C:$C,FALSE)),"") -> 45504 | AJ74: =INDEX($W:$W,MATCH(AB74,$C:$C,FALSE)) -> GMI-0021664 | AK74: =IFERROR(INDEX($X:$X,MATCH(AB74,$C:$C,FALSE)),"") -> 45507 | AL74: =INDEX($O:$O,MATCH(AF74,$N:$N,FALSE),"") -> DONE FROM BC | AM74: =INDEX($Y:$Y,MATCH(AB74,$C:$C,FALSE)) -> 45555
A75: =A74+1 -> 68 | B75: 26 Juli 2024 | C75: GMIAMMPIK/2024/07/069 | D75: 11L-1290-ARW | E75: =VLOOKUP(D75,MP!$A$1:$C$14184,2,0) -> LED Combination Lamp Amber Red White | F75: 1 | G75: PCS | H75: F54060 | I75: =IFERROR(INDEX(POP!$I:$I,MATCH(H75,POP!$G:$G,0)),"general") -> general | J75: =IFERROR(INDEX(POP!$E:$E,MATCH(H75,POP!$G:$G,0)),"general") -> general | K75: REPLACE WORKLAMP | L75: FANDY | M75: WIWIK | N75: 200000723817 | O75: DONE FROM BC | P75: =B75 -> 26 Juli 2024 | Q75: 9200014637 | R75: 45500 | T75: 45504 | U75: DO 25703 | V75: 45330 | W75: GMI-0021665 | X75: 45507 | Y75: 45555 | AA75: =AA74+1 -> 68 | AB75: GMIAMMPIK/2024/07/069 | AC75: =IFERROR(INDEX($B:$B,MATCH(AB75,$C:$C,FALSE)),"") -> 26 Juli 2024 | AD75: =INDEX($U:$U,MATCH(AB75,$C:$C,FALSE)) -> DO 25703 | AE75: =IFERROR(INDEX($V:$V,MATCH(AB75,$C:$C,FALSE)),"") -> 45330 | AF75: =IFERROR(INDEX($N:$N,MATCH(AB75,$C:$C,FALSE)),"") -> 200000723817 | AG75: =INDEX($Q:$Q,MATCH(AB75,$C:$C,FALSE)) -> 9200014637 | AH75: =IFERROR(INDEX($S:$S,MATCH(AB75,$C:$C,FALSE)),"") | AI75: =IFERROR(INDEX($T:$T,MATCH(AB75,$C:$C,FALSE)),"") -> 45504 | AJ75: =INDEX($W:$W,MATCH(AB75,$C:$C,FALSE)) -> GMI-0021665 | AK75: =IFERROR(INDEX($X:$X,MATCH(AB75,$C:$C,FALSE)),"") -> 45507 | AL75: =INDEX($O:$O,MATCH(AF75,$N:$N,FALSE),"") -> DONE FROM BC | AM75: =INDEX($Y:$Y,MATCH(AB75,$C:$C,FALSE)) -> 45555
A76: =A75+1 -> 69 | B76: 28 Juli 2024 | C76: GMIAMMPIK/2024/07/070 | D76: 3L4-7ASA | E76: =VLOOKUP(D76,MP!$A$1:$C$14184,2,0) -> LED (SMD Led) Strobe Beacon Amber : 12-24VDC with Alumunium screw base | F76: 1 | G76: PCS | H76: PLTAM15 | I76: =IFERROR(INDEX(POP!$I:$I,MATCH(H76,POP!$G:$G,0)),"general") -> general | J76: =IFERROR(INDEX(POP!$E:$E,MATCH(H76,POP!$G:$G,0)),"general") -> general | K76: REPLACE WORKLAMP | L76: FANDY | M76: WIWIK | N76: 200000724738 | O76: DONE FROM BC | P76: =B76 -> 28 Juli 2024 | Q76: 9200014749 | R76: 45502 | T76: 45504 | U76: DO 25765 | V76: 45512 | W76: GMI-0021851 | X76: 45513 | Y76: 45555 | AA76: =AA75+1 -> 69 | AB76: GMIAMMPIK/2024/07/070 | AC76: =IFERROR(INDEX($B:$B,MATCH(AB76,$C:$C,FALSE)),"") -> 28 Juli 2024 | AD76: =INDEX($U:$U,MATCH(AB76,$C:$C,FALSE)) -> DO 25765 | AE76: =IFERROR(INDEX($V:$V,MATCH(AB76,$C:$C,FALSE)),"") -> 45512 | AF76: =IFERROR(INDEX($N:$N,MATCH(AB76,$C:$C,FALSE)),"") -> 200000724738 | AG76: =INDEX($Q:$Q,MATCH(AB76,$C:$C,FALSE)) -> 9200014749 | AH76: =IFERROR(INDEX($S:$S,MATCH(AB76,$C:$C,FALSE)),"") | AI76: =IFERROR(INDEX($T:$T,MATCH(AB76,$C:$C,FALSE)),"") -> 45504 | AJ76: =INDEX($W:$W,MATCH(AB76,$C:$C,FALSE)) -> GMI-0021851 | AK76: =IFERROR(INDEX($X:$X,MATCH(AB76,$C:$C,FALSE)),"") -> 45513 | AL76: =INDEX($O:$O,MATCH(AF76,$N:$N,FALSE),"") -> DONE FROM BC | AM76: =INDEX($Y:$Y,MATCH(AB76,$C:$C,FALSE)) -> 45555
A77: =A76+1 -> 70 | B77: 03 Agustus 2024 | C77: GMIAMMPIK/2024/08/071 | D77: 11L-3024 | E77: =VLOOKUP(D77,MP!$A$1:$C$14184,2,0) -> LED FLood Light 6 Eyes 18 Watt 10-30 VDC | F77: 2 | G77: PCS | H77: PLTAM15 | I77: =IFERROR(INDEX(POP!$I:$I,MATCH(H77,POP!$G:$G,0)),"general") -> general | J77: =IFERROR(INDEX(POP!$E:$E,MATCH(H77,POP!$G:$G,0)),"general") -> general | K77: REPLACE WORKLAMP | L77: FANDY | M77: WIWIK | N77: 200000727292 | O77: DONE FROM BC | P77: =B77 -> 03 Agustus 2024 | Q77: 9200015036 | R77: 45507 | T77: 45511 | U77: DO 25793 | V77: 45543 | W77: GMI-0021852 | X77: 45513 | Y77: 45555 | AA77: =AA76+1 -> 70 | AB77: GMIAMMPIK/2024/08/071 | AC77: =IFERROR(INDEX($B:$B,MATCH(AB77,$C:$C,FALSE)),"") -> 03 Agustus 2024 | AD77: =INDEX($U:$U,MATCH(AB77,$C:$C,FALSE)) -> DO 25793 | AE77: =IFERROR(INDEX($V:$V,MATCH(AB77,$C:$C,FALSE)),"") -> 45543 | AF77: =IFERROR(INDEX($N:$N,MATCH(AB77,$C:$C,FALSE)),"") -> 200000727292 | AG77: =INDEX($Q:$Q,MATCH(AB77,$C:$C,FALSE)) -> 9200015036 | AH77: =IFERROR(INDEX($S:$S,MATCH(AB77,$C:$C,FALSE)),"") | AI77: =IFERROR(INDEX($T:$T,MATCH(AB77,$C:$C,FALSE)),"") -> 45511 | AJ77: =INDEX($W:$W,MATCH(AB77,$C:$C,FALSE)) -> GMI-0021852 | AK77: =IFERROR(INDEX($X:$X,MATCH(AB77,$C:$C,FALSE)),"") -> 45513 | AL77: =INDEX($O:$O,MATCH(AF77,$N:$N,FALSE),"") -> DONE FROM BC | AM77: =INDEX($Y:$Y,MATCH(AB77,$C:$C,FALSE)) -> 45555
A78: =A77+1 -> 71 | B78: 04 Agustus 2024 | C78: GMIAMMPIK/2024/08/072 | D78: 11L-3024 | E78: =VLOOKUP(D78,MP!$A$1:$C$14184,2,0) -> LED FLood Light 6 Eyes 18 Watt 10-30 VDC | F78: 1 | G78: PCS | H78: H57076 | I78: =IFERROR(INDEX(POP!$I:$I,MATCH(H78,POP!$G:$G,0)),"general") -> general | J78: =IFERROR(INDEX(POP!$E:$E,MATCH(H78,POP!$G:$G,0)),"general") -> general | K78: REPLACE WORKLAMP | L78: FANDY | M78: NUGROHO | N78: 200000727922 | O78: DONE FROM BC | P78: =B78 -> 04 Agustus 2024 | Q78: 9200015083 | R78: 45507 | T78: 45511 | U78: DO 25797 | V78: 45543 | W78: GMI-0021853 | X78: 45513 | Y78: 45555 | AA78: =AA77+1 -> 71 | AB78: GMIAMMPIK/2024/08/072 | AC78: =IFERROR(INDEX($B:$B,MATCH(AB78,$C:$C,FALSE)),"") -> 04 Agustus 2024 | AD78: =INDEX($U:$U,MATCH(AB78,$C:$C,FALSE)) -> DO 25797 | AE78: =IFERROR(INDEX($V:$V,MATCH(AB78,$C:$C,FALSE)),"") -> 45543 | AF78: =IFERROR(INDEX($N:$N,MATCH(AB78,$C:$C,FALSE)),"") -> 200000727922 | AG78: =INDEX($Q:$Q,MATCH(AB78,$C:$C,FALSE)) -> 9200015083 | AH78: =IFERROR(INDEX($S:$S,MATCH(AB78,$C:$C,FALSE)),"") | AI78: =IFERROR(INDEX($T:$T,MATCH(AB78,$C:$C,FALSE)),"") -> 45511 | AJ78: =INDEX($W:$W,MATCH(AB78,$C:$C,FALSE)) -> GMI-0021853 | AK78: =IFERROR(INDEX($X:$X,MATCH(AB78,$C:$C,FALSE)),"") -> 45513 | AL78: =INDEX($O:$O,MATCH(AF78,$N:$N,FALSE),"") -> DONE FROM BC | AM78: =INDEX($Y:$Y,MATCH(AB78,$C:$C,FALSE)) -> 45555
A79: =A78+1 -> 72 | B79: 07 Agustus 2024 | C79: GMIAMMPIK/2024/08/073 | D79: 11L-3024 | E79: =VLOOKUP(D79,MP!$A$1:$C$14184,2,0) -> LED FLood Light 6 Eyes 18 Watt 10-30 VDC | F79: 1 | G79: PCS | H79: PLTAM15 | I79: =IFERROR(INDEX(POP!$I:$I,MATCH(H79,POP!$G:$G,0)),"general") -> general | J79: =IFERROR(INDEX(POP!$E:$E,MATCH(H79,POP!$G:$G,0)),"general") -> general | K79: REPLACE WORKLAMP | L79: FANDY | M79: NUGROHO | N79: 200000729298 | O79: DONE FROM BC | P79: =B79 -> 07 Agustus 2024 | Q79: 9200015252 | R79: 45511 | T79: 45513 | U79: DO 25871 | V79: 13/8/2024 | W79: GMI-0021983 | X79: 45519 | Y79: 45555 | AA79: =AA78+1 -> 72 | AB79: GMIAMMPIK/2024/08/073 | AC79: =IFERROR(INDEX($B:$B,MATCH(AB79,$C:$C,FALSE)),"") -> 07 Agustus 2024 | AD79: =INDEX($U:$U,MATCH(AB79,$C:$C,FALSE)) -> DO 25871 | AE79: =IFERROR(INDEX($V:$V,MATCH(AB79,$C:$C,FALSE)),"") -> 13/8/2024 | AF79: =IFERROR(INDEX($N:$N,MATCH(AB79,$C:$C,FALSE)),"") -> 200000729298 | AG79: =INDEX($Q:$Q,MATCH(AB79,$C:$C,FALSE)) -> 9200015252 | AH79: =IFERROR(INDEX($S:$S,MATCH(AB79,$C:$C,FALSE)),"") | AI79: =IFERROR(INDEX($T:$T,MATCH(AB79,$C:$C,FALSE)),"") -> 45513 | AJ79: =INDEX($W:$W,MATCH(AB79,$C:$C,FALSE)) -> GMI-0021983 | AK79: =IFERROR(INDEX($X:$X,MATCH(AB79,$C:$C,FALSE)),"") -> 45519 | AL79: =INDEX($O:$O,MATCH(AF79,$N:$N,FALSE),"") -> DONE FROM BC | AM79: =INDEX($Y:$Y,MATCH(AB79,$C:$C,FALSE)) -> 45555
A80: =A79+1 -> 73 | B80: 07 Agustus 2024 | C80: GMIAMMPIK/2024/08/074 | D80: 11L-3024 | E80: =VLOOKUP(D80,MP!$A$1:$C$14184,2,0) -> LED FLood Light 6 Eyes 18 Watt 10-30 VDC | F80: 1 | G80: PCS | H80: DA4827PPA | I80: =IFERROR(INDEX(POP!$I:$I,MATCH(H80,POP!$G:$G,0)),"general") -> general | J80: =IFERROR(INDEX(POP!$E:$E,MATCH(H80,POP!$G:$G,0)),"general") -> general | K80: REPLACE WORKLAMP | L80: FANDY | M80: NUGROHO | N80: 200000729221 | O80: DONE FROM BC | P80: =B80 -> 07 Agustus 2024 | Q80: 9200015253 | R80: 45511 | T80: 45513 | U80: DO 25874 | V80: 13/8/2024 | W80: GMI-0021984 | X80: 45519 | Y80: 45555 | AA80: =AA79+1 -> 73 | AB80: GMIAMMPIK/2024/08/074 | AC80: =IFERROR(INDEX($B:$B,MATCH(AB80,$C:$C,FALSE)),"") -> 07 Agustus 2024 | AD80: =INDEX($U:$U,MATCH(AB80,$C:$C,FALSE)) -> DO 25874 | AE80: =IFERROR(INDEX($V:$V,MATCH(AB80,$C:$C,FALSE)),"") -> 13/8/2024 | AF80: =IFERROR(INDEX($N:$N,MATCH(AB80,$C:$C,FALSE)),"") -> 200000729221 | AG80: =INDEX($Q:$Q,MATCH(AB80,$C:$C,FALSE)) -> 9200015253 | AH80: =IFERROR(INDEX($S:$S,MATCH(AB80,$C:$C,FALSE)),"") | AI80: =IFERROR(INDEX($T:$T,MATCH(AB80,$C:$C,FALSE)),"") -> 45513 | AJ80: =INDEX($W:$W,MATCH(AB80,$C:$C,FALSE)) -> GMI-0021984 | AK80: =IFERROR(INDEX($X:$X,MATCH(AB80,$C:$C,FALSE)),"") -> 45519 | AL80: =INDEX($O:$O,MATCH(AF80,$N:$N,FALSE),"") -> DONE FROM BC | AM80: =INDEX($Y:$Y,MATCH(AB80,$C:$C,FALSE)) -> 45555
A81: =A80+1 -> 74 | B81: 08 Agustus 2024 | C81: GMIAMMPIK/2024/08/075 | D81: 11L-3024 | E81: =VLOOKUP(D81,MP!$A$1:$C$14184,2,0) -> LED FLood Light 6 Eyes 18 Watt 10-30 VDC | F81: 2 | G81: PCS | H81: E51219 | I81: =IFERROR(INDEX(POP!$I:$I,MATCH(H81,POP!$G:$G,0)),"general") -> general | J81: =IFERROR(INDEX(POP!$E:$E,MATCH(H81,POP!$G:$G,0)),"general") -> general | K81: REPLACE WORKLAMP | L81: FANDY | M81: NUGROHO | N81: 200000729883 | O81: DONE FROM BC | P81: =B81 -> 08 Agustus 2024 | Q81: 9200015358 | R81: 45511 | T81: 45513 | U81: DO 25875 | V81: 13/8/2024 | W81: GMI-0021985 | X81: 45519 | Y81: 45555 | AA81: =AA80+1 -> 74 | AB81: GMIAMMPIK/2024/08/075 | AC81: =IFERROR(INDEX($B:$B,MATCH(AB81,$C:$C,FALSE)),"") -> 08 Agustus 2024 | AD81: =INDEX($U:$U,MATCH(AB81,$C:$C,FALSE)) -> DO 25875 | AE81: =IFERROR(INDEX($V:$V,MATCH(AB81,$C:$C,FALSE)),"") -> 13/8/2024 | AF81: =IFERROR(INDEX($N:$N,MATCH(AB81,$C:$C,FALSE)),"") -> 200000729883 | AG81: =INDEX($Q:$Q,MATCH(AB81,$C:$C,FALSE)) -> 9200015358 | AH81: =IFERROR(INDEX($S:$S,MATCH(AB81,$C:$C,FALSE)),"") | AI81: =IFERROR(INDEX($T:$T,MATCH(AB81,$C:$C,FALSE)),"") -> 45513 | AJ81: =INDEX($W:$W,MATCH(AB81,$C:$C,FALSE)) -> GMI-0021985 | AK81: =IFERROR(INDEX($X:$X,MATCH(AB81,$C:$C,FALSE)),"") -> 45519 | AL81: =INDEX($O:$O,MATCH(AF81,$N:$N,FALSE),"") -> DONE FROM BC | AM81: =INDEX($Y:$Y,MATCH(AB81,$C:$C,FALSE)) -> 45555
A82: =A81+1 -> 75 | B82: 12 Agustus 2024 | C82: GMIAMMPIK/2024/08/077 | D82: 11L-3024 | E82: =VLOOKUP(D82,MP!$A$1:$C$14184,2,0) -> LED FLood Light 6 Eyes 18 Watt 10-30 VDC | F82: 2 | G82: PCS | H82: DT3631PPA | I82: =IFERROR(INDEX(POP!$I:$I,MATCH(H82,POP!$G:$G,0)),"general") -> general | J82: =IFERROR(INDEX(POP!$E:$E,MATCH(H82,POP!$G:$G,0)),"general") -> general | K82: REPLACE WORKLAMP | L82: FANDY | M82: NUGROHO | N82: 200000731700 | O82: DONE FROM BC | P82: =B82 -> 12 Agustus 2024 | Q82: 9200015638 | R82: 45518 | T82: 45518 | U82: DO 25933 | V82: 15/8/2024 | W82: GMI-0021986 | X82: 45519 | Y82: 45555 | AA82: =AA81+1 -> 75 | AB82: GMIAMMPIK/2024/08/077 | AC82: =IFERROR(INDEX($B:$B,MATCH(AB82,$C:$C,FALSE)),"") -> 12 Agustus 2024 | AD82: =INDEX($U:$U,MATCH(AB82,$C:$C,FALSE)) -> DO 25933 | AE82: =IFERROR(INDEX($V:$V,MATCH(AB82,$C:$C,FALSE)),"") -> 15/8/2024 | AF82: =IFERROR(INDEX($N:$N,MATCH(AB82,$C:$C,FALSE)),"") -> 200000731700 | AG82: =INDEX($Q:$Q,MATCH(AB82,$C:$C,FALSE)) -> 9200015638 | AH82: =IFERROR(INDEX($S:$S,MATCH(AB82,$C:$C,FALSE)),"") | AI82: =IFERROR(INDEX($T:$T,MATCH(AB82,$C:$C,FALSE)),"") -> 45518 | AJ82: =INDEX($W:$W,MATCH(AB82,$C:$C,FALSE)) -> GMI-0021986 | AK82: =IFERROR(INDEX($X:$X,MATCH(AB82,$C:$C,FALSE)),"") -> 45519 | AL82: =INDEX($O:$O,MATCH(AF82,$N:$N,FALSE),"") -> DONE FROM BC | AM82: =INDEX($Y:$Y,MATCH(AB82,$C:$C,FALSE)) -> 45555
A83: =A82+1 -> 76 | B83: 14 Agustus 2024 | C83: GMIAMMPIK/2024/08/078 | D83: 11L-3024 | E83: =VLOOKUP(D83,MP!$A$1:$C$14184,2,0) -> LED FLood Light 6 Eyes 18 Watt 10-30 VDC | F83: 2 | G83: PCS | H83: TH5DS01 | I83: =IFERROR(INDEX(POP!$I:$I,MATCH(H83,POP!$G:$G,0)),"general") -> general | J83: =IFERROR(INDEX(POP!$E:$E,MATCH(H83,POP!$G:$G,0)),"general") -> general | K83: REPLACE WORKLAMP | L83: FANDY | M83: NUGROHO | N83: 200000732501 | O83: DONE FROM BC | P83: =B83 -> 14 Agustus 2024 | Q83: 9200015748 | R83: 45518 | T83: 45518 | U83: DO 34490 | V83: 24/4/2025 | W83: INV-2025-IV-GMI-0030179 | X83: 45771 | Y83: 45838 | AA83: =AA82+1 -> 76 | AB83: GMIAMMPIK/2024/08/078 | AC83: =IFERROR(INDEX($B:$B,MATCH(AB83,$C:$C,FALSE)),"") -> 14 Agustus 2024 | AD83: =INDEX($U:$U,MATCH(AB83,$C:$C,FALSE)) -> DO 34490 | AE83: =IFERROR(INDEX($V:$V,MATCH(AB83,$C:$C,FALSE)),"") -> 24/4/2025 | AF83: =IFERROR(INDEX($N:$N,MATCH(AB83,$C:$C,FALSE)),"") -> 200000732501 | AG83: =INDEX($Q:$Q,MATCH(AB83,$C:$C,FALSE)) -> 9200015748 | AH83: =IFERROR(INDEX($S:$S,MATCH(AB83,$C:$C,FALSE)),"") | AI83: =IFERROR(INDEX($T:$T,MATCH(AB83,$C:$C,FALSE)),"") -> 45518 | AJ83: =INDEX($W:$W,MATCH(AB83,$C:$C,FALSE)) -> INV-2025-IV-GMI-0030179 | AK83: =IFERROR(INDEX($X:$X,MATCH(AB83,$C:$C,FALSE)),"") -> 45771 | AL83: =INDEX($O:$O,MATCH(AF83,$N:$N,FALSE),"") -> DONE FROM BC | AM83: =INDEX($Y:$Y,MATCH(AB83,$C:$C,FALSE)) -> 45838
A84: =A83+1 -> 77 | B84: 16 Agustus 2024 | C84: GMIAMMPIK/2024/08/079 | D84: 11L-3024 | E84: =VLOOKUP(D84,MP!$A$1:$C$14184,2,0) -> LED FLood Light 6 Eyes 18 Watt 10-30 VDC | F84: 2 | G84: PCS | H84: DA4827PPA | I84: =IFERROR(INDEX(POP!$I:$I,MATCH(H84,POP!$G:$G,0)),"general") -> general | J84: =IFERROR(INDEX(POP!$E:$E,MATCH(H84,POP!$G:$G,0)),"general") -> general | K84: REPLACE WORKLAMP | L84: FANDY | M84: NUGROHO | N84: 200000730356 | O84: DONE FROM BC | P84: =B84 -> 16 Agustus 2024 | Q84: 9200015536 | R84: 45514 | T84: 45527 | U84: DO 26339 | V84: 45331 | W84: GMI-0022364 | X84: 45538 | Y84: 45590 | AA84: =AA83+1 -> 77 | AB84: GMIAMMPIK/2024/08/079 | AC84: =IFERROR(INDEX($B:$B,MATCH(AB84,$C:$C,FALSE)),"") -> 16 Agustus 2024 | AD84: =INDEX($U:$U,MATCH(AB84,$C:$C,FALSE)) -> DO 26339 | AE84: =IFERROR(INDEX($V:$V,MATCH(AB84,$C:$C,FALSE)),"") -> 45331 | AF84: =IFERROR(INDEX($N:$N,MATCH(AB84,$C:$C,FALSE)),"") -> 200000730356 | AG84: =INDEX($Q:$Q,MATCH(AB84,$C:$C,FALSE)) -> 9200015536 | AH84: =IFERROR(INDEX($S:$S,MATCH(AB84,$C:$C,FALSE)),"") | AI84: =IFERROR(INDEX($T:$T,MATCH(AB84,$C:$C,FALSE)),"") -> 45527 | AJ84: =INDEX($W:$W,MATCH(AB84,$C:$C,FALSE)) -> GMI-0022364 | AK84: =IFERROR(INDEX($X:$X,MATCH(AB84,$C:$C,FALSE)),"") -> 45538 | AL84: =INDEX($O:$O,MATCH(AF84,$N:$N,FALSE),"") -> DONE FROM BC | AM84: =INDEX($Y:$Y,MATCH(AB84,$C:$C,FALSE)) -> 45590
A85: =A84+1 -> 78 | B85: 19 Agustus 2024 | C85: GMIAMMPIK/2024/08/080 | D85: 11L-3024 | E85: =VLOOKUP(D85,MP!$A$1:$C$14184,2,0) -> LED FLood Light 6 Eyes 18 Watt 10-30 VDC | F85: 2 | G85: PCS | H85: DA54807 | I85: =IFERROR(INDEX(POP!$I:$I,MATCH(H85,POP!$G:$G,0)),"general") -> general | J85: =IFERROR(INDEX(POP!$E:$E,MATCH(H85,POP!$G:$G,0)),"general") -> general | K85: REPLACE WORKLAMP | L85: FANDY | M85: NUGROHO | N85: 200000734619 | O85: DONE FROM BC | P85: =B85 -> 19 Agustus 2024 | Q85: 9200016013 | R85: 45523 | T85: 45524 | U85: DO 26297 | V85: 30/8/2024 | W85: GMI-0022307 | X85: 45535 | Y85: 45590 | AA85: =AA84+1 -> 78 | AB85: GMIAMMPIK/2024/08/080 | AC85: =IFERROR(INDEX($B:$B,MATCH(AB85,$C:$C,FALSE)),"") -> 19 Agustus 2024 | AD85: =INDEX($U:$U,MATCH(AB85,$C:$C,FALSE)) -> DO 26297 | AE85: =IFERROR(INDEX($V:$V,MATCH(AB85,$C:$C,FALSE)),"") -> 30/8/2024 | AF85: =IFERROR(INDEX($N:$N,MATCH(AB85,$C:$C,FALSE)),"") -> 200000734619 | AG85: =INDEX($Q:$Q,MATCH(AB85,$C:$C,FALSE)) -> 9200016013 | AH85: =IFERROR(INDEX($S:$S,MATCH(AB85,$C:$C,FALSE)),"") | AI85: =IFERROR(INDEX($T:$T,MATCH(AB85,$C:$C,FALSE)),"") -> 45524 | AJ85: =INDEX($W:$W,MATCH(AB85,$C:$C,FALSE)) -> GMI-0022307 | AK85: =IFERROR(INDEX($X:$X,MATCH(AB85,$C:$C,FALSE)),"") -> 45535 | AL85: =INDEX($O:$O,MATCH(AF85,$N:$N,FALSE),"") -> DONE FROM BC | AM85: =INDEX($Y:$Y,MATCH(AB85,$C:$C,FALSE)) -> 45590
A86: =A85+1 -> 79 | B86: 22 Agustus 2024 | C86: GMIAMMPIK/2024/08/081 | D86: 11L-3024 | E86: =VLOOKUP(D86,MP!$A$1:$C$14184,2,0) -> LED FLood Light 6 Eyes 18 Watt 10-30 VDC | F86: 1 | G86: PCS | H86: DA54830 | I86: =IFERROR(INDEX(POP!$I:$I,MATCH(H86,POP!$G:$G,0)),"general") -> general | J86: =IFERROR(INDEX(POP!$E:$E,MATCH(H86,POP!$G:$G,0)),"general") -> general | K86: REPLACE WORKLAMP | L86: FANDY | M86: NUGROHO | N86: 200000735969 | O86: DONE FROM BC | P86: =B86 -> 22 Agustus 2024 | Q86: 9200016219 | R86: 45526 | T86: 45527 | U86: DO 26336 | V86: 45331 | W86: GMI-0022363 | X86: 45538 | Y86: 45590 | AA86: =AA85+1 -> 79 | AB86: GMIAMMPIK/2024/08/081 | AC86: =IFERROR(INDEX($B:$B,MATCH(AB86,$C:$C,FALSE)),"") -> 22 Agustus 2024 | AD86: =INDEX($U:$U,MATCH(AB86,$C:$C,FALSE)) -> DO 26336 | AE86: =IFERROR(INDEX($V:$V,MATCH(AB86,$C:$C,FALSE)),"") -> 45331 | AF86: =IFERROR(INDEX($N:$N,MATCH(AB86,$C:$C,FALSE)),"") -> 200000735969 | AG86: =INDEX($Q:$Q,MATCH(AB86,$C:$C,FALSE)) -> 9200016219 | AH86: =IFERROR(INDEX($S:$S,MATCH(AB86,$C:$C,FALSE)),"") | AI86: =IFERROR(INDEX($T:$T,MATCH(AB86,$C:$C,FALSE)),"") -> 45527 | AJ86: =INDEX($W:$W,MATCH(AB86,$C:$C,FALSE)) -> GMI-0022363 | AK86: =IFERROR(INDEX($X:$X,MATCH(AB86,$C:$C,FALSE)),"") -> 45538 | AL86: =INDEX($O:$O,MATCH(AF86,$N:$N,FALSE),"") -> DONE FROM BC | AM86: =INDEX($Y:$Y,MATCH(AB86,$C:$C,FALSE)) -> 45590
A87: =A86+1 -> 80 | B87: 26 Agustus 2024 | C87: GMIAMMPIK/2024/08/082 | D87: 3L4-7ASA | E87: =VLOOKUP(D87,MP!$A$1:$C$14184,2,0) -> LED (SMD Led) Strobe Beacon Amber : 12-24VDC with Alumunium screw base | F87: 1 | G87: PCS | H87: LV12 | I87: =IFERROR(INDEX(POP!$I:$I,MATCH(H87,POP!$G:$G,0)),"general") -> general | J87: =IFERROR(INDEX(POP!$E:$E,MATCH(H87,POP!$G:$G,0)),"general") -> general | K87: REPLACE WORKLAMP | L87: FANDY | M87: FAUZI | N87: 1628200 | O87: DONE FROM BC | P87: =B87 -> 26 Agustus 2024 | Q87: 9200016439 | R87: 45530 | T87: 45531 | U87: DO 26507 | V87: 45452 | W87: GMI-0022501 | X87: 45544 | Y87: 45590 | AA87: =AA86+1 -> 80 | AB87: GMIAMMPIK/2024/08/082 | AC87: =IFERROR(INDEX($B:$B,MATCH(AB87,$C:$C,FALSE)),"") -> 26 Agustus 2024 | AD87: =INDEX($U:$U,MATCH(AB87,$C:$C,FALSE)) -> DO 26507 | AE87: =IFERROR(INDEX($V:$V,MATCH(AB87,$C:$C,FALSE)),"") -> 45452 | AF87: =IFERROR(INDEX($N:$N,MATCH(AB87,$C:$C,FALSE)),"") -> 1628200 | AG87: =INDEX($Q:$Q,MATCH(AB87,$C:$C,FALSE)) -> 9200016439 | AH87: =IFERROR(INDEX($S:$S,MATCH(AB87,$C:$C,FALSE)),"") | AI87: =IFERROR(INDEX($T:$T,MATCH(AB87,$C:$C,FALSE)),"") -> 45531 | AJ87: =INDEX($W:$W,MATCH(AB87,$C:$C,FALSE)) -> GMI-0022501 | AK87: =IFERROR(INDEX($X:$X,MATCH(AB87,$C:$C,FALSE)),"") -> 45544 | AL87: =INDEX($O:$O,MATCH(AF87,$N:$N,FALSE),"") -> DONE FROM BC | AM87: =INDEX($Y:$Y,MATCH(AB87,$C:$C,FALSE)) -> 45590
A88: =A87+1 -> 81 | B88: 45537 | C88: GMIAMMPIK/2024/09/083 | D88: 11L-3024 | E88: =VLOOKUP(D88,MP!$A$1:$C$14184,2,0) -> LED FLood Light 6 Eyes 18 Watt 10-30 VDC | F88: 3 | G88: PCS | H88: FT2532PPA | I88: =IFERROR(INDEX(POP!$I:$I,MATCH(H88,POP!$G:$G,0)),"general") -> general | J88: =IFERROR(INDEX(POP!$E:$E,MATCH(H88,POP!$G:$G,0)),"general") -> general | K88: REPLACE WORKLAMP | L88: FANDY | M88: FAUZI | N88: 200000740676 | O88: DONE FROM BC | P88: =B88 -> 45537 | Q88: 9200016818 | R88: 45538 | T88: 45540 | U88: DO 26658 | V88: 13/9/2024 | W88: GMI-0022713 | X88: 45553 | Y88: 45590 | AA88: =AA87+1 -> 81 | AB88: GMIAMMPIK/2024/09/083 | AC88: =IFERROR(INDEX($B:$B,MATCH(AB88,$C:$C,FALSE)),"") -> 45537 | AD88: =INDEX($U:$U,MATCH(AB88,$C:$C,FALSE)) -> DO 26658 | AE88: =IFERROR(INDEX($V:$V,MATCH(AB88,$C:$C,FALSE)),"") -> 13/9/2024 | AF88: =IFERROR(INDEX($N:$N,MATCH(AB88,$C:$C,FALSE)),"") -> 200000740676 | AG88: =INDEX($Q:$Q,MATCH(AB88,$C:$C,FALSE)) -> 9200016818 | AH88: =IFERROR(INDEX($S:$S,MATCH(AB88,$C:$C,FALSE)),"") | AI88: =IFERROR(INDEX($T:$T,MATCH(AB88,$C:$C,FALSE)),"") -> 45540 | AJ88: =INDEX($W:$W,MATCH(AB88,$C:$C,FALSE)) -> GMI-0022713 | AK88: =IFERROR(INDEX($X:$X,MATCH(AB88,$C:$C,FALSE)),"") -> 45553 | AL88: =INDEX($O:$O,MATCH(AF88,$N:$N,FALSE),"") -> DONE FROM BC | AM88: =INDEX($Y:$Y,MATCH(AB88,$C:$C,FALSE)) -> 45590
A89: =A88+1 -> 82 | B89: 45539 | C89: GMIAMMPIK/2024/09/084 | D89: 3L4-7ASB | E89: =VLOOKUP(D89,MP!$A$1:$C$14184,2,0) -> LED (SMD Led) Strobe Beacon Blue : 12-24VDC with Alumunium screw base | F89: 1 | G89: PCS | H89: VS25PPA | I89: =IFERROR(INDEX(POP!$I:$I,MATCH(H89,POP!$G:$G,0)),"general") -> general | J89: =IFERROR(INDEX(POP!$E:$E,MATCH(H89,POP!$G:$G,0)),"general") -> general | K89: REPLACE WORKLAMP | L89: FANDY | M89: FAUZI | N89: 200000741150 | O89: DONE FROM BC | P89: =B89 -> 45539 | Q89: 9200016906 | R89: 45538 | T89: 45540 | U89: DO 26694 | V89: 17/9/2024 | W89: GMI-0022716 | X89: 45553 | Y89: 45625 | AA89: =AA88+1 -> 82 | AB89: GMIAMMPIK/2024/09/084 | AC89: =IFERROR(INDEX($B:$B,MATCH(AB89,$C:$C,FALSE)),"") -> 45539 | AD89: =INDEX($U:$U,MATCH(AB89,$C:$C,FALSE)) -> DO 26694 | AE89: =IFERROR(INDEX($V:$V,MATCH(AB89,$C:$C,FALSE)),"") -> 17/9/2024 | AF89: =IFERROR(INDEX($N:$N,MATCH(AB89,$C:$C,FALSE)),"") -> 200000741150 | AG89: =INDEX($Q:$Q,MATCH(AB89,$C:$C,FALSE)) -> 9200016906 | AH89: =IFERROR(INDEX($S:$S,MATCH(AB89,$C:$C,FALSE)),"") | AI89: =IFERROR(INDEX($T:$T,MATCH(AB89,$C:$C,FALSE)),"") -> 45540 | AJ89: =INDEX($W:$W,MATCH(AB89,$C:$C,FALSE)) -> GMI-0022716 | AK89: =IFERROR(INDEX($X:$X,MATCH(AB89,$C:$C,FALSE)),"") -> 45553 | AL89: =INDEX($O:$O,MATCH(AF89,$N:$N,FALSE),"") -> DONE FROM BC | AM89: =INDEX($Y:$Y,MATCH(AB89,$C:$C,FALSE)) -> 45625
A90: =A89+1 -> 83 | B90: 45539 | C90: GMIAMMPIK/2024/09/085 | D90: 11L-3024 | E90: =VLOOKUP(D90,MP!$A$1:$C$14184,2,0) -> LED FLood Light 6 Eyes 18 Watt 10-30 VDC | F90: 1 | G90: PCS | H90: E426PPA | I90: =IFERROR(INDEX(POP!$I:$I,MATCH(H90,POP!$G:$G,0)),"general") -> general | J90: =IFERROR(INDEX(POP!$E:$E,MATCH(H90,POP!$G:$G,0)),"general") -> general | K90: REPLACE WORKLAMP | L90: FANDY | M90: FAUZI | N90: 200000741215 | O90: DONE FROM BC | P90: =B90 -> 45539 | Q90: 9200016917 | R90: 45538 | T90: 45540 | U90: DO 26662 | V90: 13/9/2024 | W90: GMI-0022714 | X90: 45553 | Y90: 45590 | AA90: =AA89+1 -> 83 | AB90: GMIAMMPIK/2024/09/085 | AC90: =IFERROR(INDEX($B:$B,MATCH(AB90,$C:$C,FALSE)),"") -> 45539 | AD90: =INDEX($U:$U,MATCH(AB90,$C:$C,FALSE)) -> DO 26662 | AE90: =IFERROR(INDEX($V:$V,MATCH(AB90,$C:$C,FALSE)),"") -> 13/9/2024 | AF90: =IFERROR(INDEX($N:$N,MATCH(AB90,$C:$C,FALSE)),"") -> 200000741215 | AG90: =INDEX($Q:$Q,MATCH(AB90,$C:$C,FALSE)) -> 9200016917 | AH90: =IFERROR(INDEX($S:$S,MATCH(AB90,$C:$C,FALSE)),"") | AI90: =IFERROR(INDEX($T:$T,MATCH(AB90,$C:$C,FALSE)),"") -> 45540 | AJ90: =INDEX($W:$W,MATCH(AB90,$C:$C,FALSE)) -> GMI-0022714 | AK90: =IFERROR(INDEX($X:$X,MATCH(AB90,$C:$C,FALSE)),"") -> 45553 | AL90: =INDEX($O:$O,MATCH(AF90,$N:$N,FALSE),"") -> DONE FROM BC | AM90: =INDEX($Y:$Y,MATCH(AB90,$C:$C,FALSE)) -> 45590
A91: =A90+1 -> 84 | B91: 45539 | C91: GMIAMMPIK/2024/09/086 | D91: 3L4-7ASA | E91: =VLOOKUP(D91,MP!$A$1:$C$14184,2,0) -> LED (SMD Led) Strobe Beacon Amber : 12-24VDC with Alumunium screw base | F91: 1 | G91: PCS | H91: PLTAM15 | I91: =IFERROR(INDEX(POP!$I:$I,MATCH(H91,POP!$G:$G,0)),"general") -> general | J91: =IFERROR(INDEX(POP!$E:$E,MATCH(H91,POP!$G:$G,0)),"general") -> general | K91: REPLACE WORKLAMP | L91: FANDY | M91: FAUZI | N91: 200000741419 | O91: DONE FROM BC | P91: =B91 -> 45539 | Q91: 9200016923 | R91: 45538 | T91: 45540 | U91: DO 26663 | V91: 13/9/2024 | W91: GMI-0022715 | X91: 45553 | Y91: 45590 | AA91: =AA90+1 -> 84 | AB91: GMIAMMPIK/2024/09/086 | AC91: =IFERROR(INDEX($B:$B,MATCH(AB91,$C:$C,FALSE)),"") -> 45539 | AD91: =INDEX($U:$U,MATCH(AB91,$C:$C,FALSE)) -> DO 26663 | AE91: =IFERROR(INDEX($V:$V,MATCH(AB91,$C:$C,FALSE)),"") -> 13/9/2024 | AF91: =IFERROR(INDEX($N:$N,MATCH(AB91,$C:$C,FALSE)),"") -> 200000741419 | AG91: =INDEX($Q:$Q,MATCH(AB91,$C:$C,FALSE)) -> 9200016923 | AH91: =IFERROR(INDEX($S:$S,MATCH(AB91,$C:$C,FALSE)),"") | AI91: =IFERROR(INDEX($T:$T,MATCH(AB91,$C:$C,FALSE)),"") -> 45540 | AJ91: =INDEX($W:$W,MATCH(AB91,$C:$C,FALSE)) -> GMI-0022715 | AK91: =IFERROR(INDEX($X:$X,MATCH(AB91,$C:$C,FALSE)),"") -> 45553 | AL91: =INDEX($O:$O,MATCH(AF91,$N:$N,FALSE),"") -> DONE FROM BC | AM91: =INDEX($Y:$Y,MATCH(AB91,$C:$C,FALSE)) -> 45590
A92: =A91+1 -> 85 | B92: 45539 | C92: GMIAMMPIK/2024/09/086 | D92: 11L-3024 | E92: =VLOOKUP(D92,MP!$A$1:$C$14184,2,0) -> LED FLood Light 6 Eyes 18 Watt 10-30 VDC | F92: 2 | G92: PCS | H92: PLTAM15 | I92: =IFERROR(INDEX(POP!$I:$I,MATCH(H92,POP!$G:$G,0)),"general") -> general | J92: =IFERROR(INDEX(POP!$E:$E,MATCH(H92,POP!$G:$G,0)),"general") -> general | K92: REPLACE WORKLAMP | L92: FANDY | M92: FAUZI | N92: 200000741419 | O92: DONE FROM BC | P92: =B92 -> 45539 | Q92: 9200016923 | R92: 45538 | T92: 45540 | U92: DO 26663 | V92: 13/9/2024 | W92: GMI-0022715 | X92: 45553 | Y92: 45590 | AA92: =AA91+1 -> 85 | AB92: GMIAMMPIK/2024/09/086 | AC92: =IFERROR(INDEX($B:$B,MATCH(AB92,$C:$C,FALSE)),"") -> 45539 | AD92: =INDEX($U:$U,MATCH(AB92,$C:$C,FALSE)) -> DO 26663 | AE92: =IFERROR(INDEX($V:$V,MATCH(AB92,$C:$C,FALSE)),"") -> 13/9/2024 | AF92: =IFERROR(INDEX($N:$N,MATCH(AB92,$C:$C,FALSE)),"") -> 200000741419 | AG92: =INDEX($Q:$Q,MATCH(AB92,$C:$C,FALSE)) -> 9200016923 | AH92: =IFERROR(INDEX($S:$S,MATCH(AB92,$C:$C,FALSE)),"") | AI92: =IFERROR(INDEX($T:$T,MATCH(AB92,$C:$C,FALSE)),"") -> 45540 | AJ92: =INDEX($W:$W,MATCH(AB92,$C:$C,FALSE)) -> GMI-0022715 | AK92: =IFERROR(INDEX($X:$X,MATCH(AB92,$C:$C,FALSE)),"") -> 45553 | AL92: =INDEX($O:$O,MATCH(AF92,$N:$N,FALSE),"") -> DONE FROM BC | AM92: =INDEX($Y:$Y,MATCH(AB92,$C:$C,FALSE)) -> 45590
A93: =A92+1 -> 86 | B93: 45543 | C93: GMIAMMPIK/2024/09/087 | D93: 3L3-8AB | E93: =VLOOKUP(D93,MP!$A$1:$C$14184,2,0) -> Blue Xenon Beacon Light 12-24VDC with alumunium screw base | F93: 1 | G93: PCS | H93: D5108 | I93: =IFERROR(INDEX(POP!$I:$I,MATCH(H93,POP!$G:$G,0)),"general") -> general | J93: =IFERROR(INDEX(POP!$E:$E,MATCH(H93,POP!$G:$G,0)),"general") -> general | K93: REPLACE WORKLAMP | L93: FANDY | M93: FAUZI | N93: 200000741448 | O93: DONE FROM BC | P93: =B93 -> 45543 | Q93: 9200016956 | R93: CANCEL | T93: CANCEL | U93: CANCEL | V93: CANCEL | W93: CANCEL | X93: CANCEL | Y93: CANCEL | AA93: =AA92+1 -> 86 | AB93: GMIAMMPIK/2024/09/087 | AC93: =IFERROR(INDEX($B:$B,MATCH(AB93,$C:$C,FALSE)),"") -> 45543 | AD93: =IFERROR(INDEX($V:$V,MATCH(AA93,$C:$C,FALSE)),"") | AE93: =IFERROR(INDEX($V:$V,MATCH(AB93,$C:$C,FALSE)),"") -> CANCEL | AF93: =IFERROR(INDEX($N:$N,MATCH(AB93,$C:$C,FALSE)),"") -> 200000741448 | AG93: =INDEX($Q:$Q,MATCH(AB93,$C:$C,FALSE)) -> 9200016956 | AH93: =IFERROR(INDEX($S:$S,MATCH(AB93,$C:$C,FALSE)),"") | AI93: =IFERROR(INDEX($T:$T,MATCH(AB93,$C:$C,FALSE)),"") -> CANCEL | AK93: =IFERROR(INDEX($X:$X,MATCH(AB93,$C:$C,FALSE)),"") -> CANCEL | AL93: =INDEX($O:$O,MATCH(AF93,$N:$N,FALSE),"") -> DONE FROM BC | AM93: =INDEX($Y:$Y,MATCH(AB93,$C:$C,FALSE)) -> CANCEL
A94: =A93+1 -> 87 | B94: 45544 | C94: GMIAMMPIK/2024/09/088 | D94: 11L-3024 | E94: =VLOOKUP(D94,MP!$A$1:$C$14184,2,0) -> LED FLood Light 6 Eyes 18 Watt 10-30 VDC | F94: 1 | G94: PCS | H94: E3903PPA | I94: =IFERROR(INDEX(POP!$I:$I,MATCH(H94,POP!$G:$G,0)),"general") -> general | J94: =IFERROR(INDEX(POP!$E:$E,MATCH(H94,POP!$G:$G,0)),"general") -> general | K94: REPLACE WORKLAMP | L94: FANDY | M94: FAUZI | N94: 200000743953 | O94: DONE FROM BC | P94: =B94 -> 45544 | Q94: 9200017298 | R94: 45544 | T94: 45555 | U94: DO 27092 | V94: 45332 | W94: GMI-0023107 | X94: 45568 | Y94: 45625 | AA94: =AA93+1 -> 87 | AB94: GMIAMMPIK/2024/09/088 | AC94: =IFERROR(INDEX($B:$B,MATCH(AB94,$C:$C,FALSE)),"") -> 45544 | AD94: =INDEX($U:$U,MATCH(AB94,$C:$C,FALSE)) -> DO 27092 | AE94: =IFERROR(INDEX($V:$V,MATCH(AB94,$C:$C,FALSE)),"") -> 45332 | AF94: =IFERROR(INDEX($N:$N,MATCH(AB94,$C:$C,FALSE)),"") -> 200000743953 | AG94: =INDEX($Q:$Q,MATCH(AB94,$C:$C,FALSE)) -> 9200017298 | AH94: =IFERROR(INDEX($S:$S,MATCH(AB94,$C:$C,FALSE)),"") | AI94: =IFERROR(INDEX($T:$T,MATCH(AB94,$C:$C,FALSE)),"") -> 45555 | AJ94: =INDEX($W:$W,MATCH(AB94,$C:$C,FALSE)) -> GMI-0023107 | AK94: =IFERROR(INDEX($X:$X,MATCH(AB94,$C:$C,FALSE)),"") -> 45568 | AL94: =INDEX($O:$O,MATCH(AF94,$N:$N,FALSE),"") -> DONE FROM BC | AM94: =INDEX($Y:$Y,MATCH(AB94,$C:$C,FALSE)) -> 45625
A95: =A94+1 -> 88 | B95: 45545 | C95: GMIAMMPIK/2024/09/089 | D95: 11L-3024 | E95: =VLOOKUP(D95,MP!$A$1:$C$14184,2,0) -> LED FLood Light 6 Eyes 18 Watt 10-30 VDC | F95: 4 | G95: PCS | H95: WA52516 | I95: =IFERROR(INDEX(POP!$I:$I,MATCH(H95,POP!$G:$G,0)),"general") -> general | J95: =IFERROR(INDEX(POP!$E:$E,MATCH(H95,POP!$G:$G,0)),"general") -> general | K95: REPLACE WORKLAMP | L95: FANDY | M95: FAUZI | N95: 200000744859 | O95: DONE FROM BC | P95: =B95 -> 45545 | Q95: 9200017388 | R95: 45545 | T95: 45555 | U95: DO 27094 | V95: 45332 | W95: GMI-0023108 | X95: 45568 | Y95: 45625 | AA95: =AA94+1 -> 88 | AB95: GMIAMMPIK/2024/09/089 | AC95: =IFERROR(INDEX($B:$B,MATCH(AB95,$C:$C,FALSE)),"") -> 45545 | AD95: =INDEX($U:$U,MATCH(AB95,$C:$C,FALSE)) -> DO 27094 | AE95: =IFERROR(INDEX($V:$V,MATCH(AB95,$C:$C,FALSE)),"") -> 45332 | AF95: =IFERROR(INDEX($N:$N,MATCH(AB95,$C:$C,FALSE)),"") -> 200000744859 | AG95: =INDEX($Q:$Q,MATCH(AB95,$C:$C,FALSE)) -> 9200017388 | AH95: =IFERROR(INDEX($S:$S,MATCH(AB95,$C:$C,FALSE)),"") | AI95: =IFERROR(INDEX($T:$T,MATCH(AB95,$C:$C,FALSE)),"") -> 45555 | AJ95: =INDEX($W:$W,MATCH(AB95,$C:$C,FALSE)) -> GMI-0023108 | AK95: =IFERROR(INDEX($X:$X,MATCH(AB95,$C:$C,FALSE)),"") -> 45568 | AL95: =INDEX($O:$O,MATCH(AF95,$N:$N,FALSE),"") -> DONE FROM BC | AM95: =INDEX($Y:$Y,MATCH(AB95,$C:$C,FALSE)) -> 45625
A96: =A95+1 -> 89 | B96: 45546 | C96: GMIAMMPIK/2024/09/090 | D96: 11L-3024 | E96: =VLOOKUP(D96,MP!$A$1:$C$14184,2,0) -> LED FLood Light 6 Eyes 18 Watt 10-30 VDC | F96: 2 | G96: PCS | H96: EH53602 | I96: =IFERROR(INDEX(POP!$I:$I,MATCH(H96,POP!$G:$G,0)),"general") -> general | J96: =IFERROR(INDEX(POP!$E:$E,MATCH(H96,POP!$G:$G,0)),"general") -> general | K96: REPLACE WORKLAMP | L96: FANDY | M96: FAUZI | N96: 200000743888 | O96: DONE FROM BC | P96: =B96 -> 45546 | Q96: 9200017254 | R96: 45543 | T96: 45555 | U96: DO 27091 | V96: 45332 | W96: GMI-0023106 | X96: 45568 | Y96: 45625 | AA96: =AA95+1 -> 89 | AB96: GMIAMMPIK/2024/09/090 | AC96: =IFERROR(INDEX($B:$B,MATCH(AB96,$C:$C,FALSE)),"") -> 45546 | AD96: =INDEX($U:$U,MATCH(AB96,$C:$C,FALSE)) -> DO 27091 | AE96: =IFERROR(INDEX($V:$V,MATCH(AB96,$C:$C,FALSE)),"") -> 45332 | AF96: =IFERROR(INDEX($N:$N,MATCH(AB96,$C:$C,FALSE)),"") -> 200000743888 | AG96: =INDEX($Q:$Q,MATCH(AB96,$C:$C,FALSE)) -> 9200017254 | AH96: =IFERROR(INDEX($S:$S,MATCH(AB96,$C:$C,FALSE)),"") | AI96: =IFERROR(INDEX($T:$T,MATCH(AB96,$C:$C,FALSE)),"") -> 45555 | AJ96: =INDEX($W:$W,MATCH(AB96,$C:$C,FALSE)) -> GMI-0023106 | AK96: =IFERROR(INDEX($X:$X,MATCH(AB96,$C:$C,FALSE)),"") -> 45568 | AL96: =INDEX($O:$O,MATCH(AF96,$N:$N,FALSE),"") -> DONE FROM BC | AM96: =INDEX($Y:$Y,MATCH(AB96,$C:$C,FALSE)) -> 45625
A97: =A96+1 -> 90 | B97: 45546 | C97: GMIAMMPIK/2024/09/091 | D97: 11L-3024 | E97: =VLOOKUP(D97,MP!$A$1:$C$14184,2,0) -> LED FLood Light 6 Eyes 18 Watt 10-30 VDC | F97: 1 | G97: PCS | H97: WT2522PPA | I97: =IFERROR(INDEX(POP!$I:$I,MATCH(H97,POP!$G:$G,0)),"general") -> general | J97: =IFERROR(INDEX(POP!$E:$E,MATCH(H97,POP!$G:$G,0)),"general") -> general | K97: REPLACE WORKLAMP | L97: FANDY | M97: FAUZI | N97: 200000745064 | O97: DONE FROM BC | P97: =B97 -> 45546 | Q97: 9200017434 | R97: 45546 | T97: 45555 | U97: DO 27101 | V97: 45332 | W97: GMI-0023110 | X97: 45568 | Y97: 45625 | AA97: =AA96+1 -> 90 | AB97: GMIAMMPIK/2024/09/091 | AC97: =IFERROR(INDEX($B:$B,MATCH(AB97,$C:$C,FALSE)),"") -> 45546 | AD97: =INDEX($U:$U,MATCH(AB97,$C:$C,FALSE)) -> DO 27101 | AE97: =IFERROR(INDEX($V:$V,MATCH(AB97,$C:$C,FALSE)),"") -> 45332 | AF97: =IFERROR(INDEX($N:$N,MATCH(AB97,$C:$C,FALSE)),"") -> 200000745064 | AG97: =INDEX($Q:$Q,MATCH(AB97,$C:$C,FALSE)) -> 9200017434 | AH97: =IFERROR(INDEX($S:$S,MATCH(AB97,$C:$C,FALSE)),"") | AI97: =IFERROR(INDEX($T:$T,MATCH(AB97,$C:$C,FALSE)),"") -> 45555 | AJ97: =INDEX($W:$W,MATCH(AB97,$C:$C,FALSE)) -> GMI-0023110 | AK97: =IFERROR(INDEX($X:$X,MATCH(AB97,$C:$C,FALSE)),"") -> 45568 | AL97: =INDEX($O:$O,MATCH(AF97,$N:$N,FALSE),"") -> DONE FROM BC | AM97: =INDEX($Y:$Y,MATCH(AB97,$C:$C,FALSE)) -> 45625
A98: =A97+1 -> 91 | B98: 45550 | C98: GMIAMMPIK/2024/09/092 | D98: 11L-1290-ARW | E98: =VLOOKUP(D98,MP!$A$1:$C$14184,2,0) -> LED Combination Lamp Amber Red White | F98: 2 | G98: PCS | H98: F54033 | I98: =IFERROR(INDEX(POP!$I:$I,MATCH(H98,POP!$G:$G,0)),"general") -> general | J98: =IFERROR(INDEX(POP!$E:$E,MATCH(H98,POP!$G:$G,0)),"general") -> general | K98: REPLACE WORKLAMP | L98: FANDY | M98: FAUZI | N98: 200000746714 | O98: DONE FROM BC | P98: =B98 -> 45550 | Q98: 9200017722 | R98: 45549 | T98: 45555 | U98: DO 27100 | V98: 45332 | W98: GMI-0023109 | X98: 45568 | Y98: 45625 | AA98: =AA97+1 -> 91 | AB98: GMIAMMPIK/2024/09/092 | AC98: =IFERROR(INDEX($B:$B,MATCH(AB98,$C:$C,FALSE)),"") -> 45550 | AD98: =INDEX($U:$U,MATCH(AB98,$C:$C,FALSE)) -> DO 27100 | AE98: =IFERROR(INDEX($V:$V,MATCH(AB98,$C:$C,FALSE)),"") -> 45332 | AF98: =IFERROR(INDEX($N:$N,MATCH(AB98,$C:$C,FALSE)),"") -> 200000746714 | AG98: =INDEX($Q:$Q,MATCH(AB98,$C:$C,FALSE)) -> 9200017722 | AH98: =IFERROR(INDEX($S:$S,MATCH(AB98,$C:$C,FALSE)),"") | AI98: =IFERROR(INDEX($T:$T,MATCH(AB98,$C:$C,FALSE)),"") -> 45555 | AJ98: =INDEX($W:$W,MATCH(AB98,$C:$C,FALSE)) -> GMI-0023109 | AK98: =IFERROR(INDEX($X:$X,MATCH(AB98,$C:$C,FALSE)),"") -> 45568 | AL98: =INDEX($O:$O,MATCH(AF98,$N:$N,FALSE),"") -> DONE FROM BC | AM98: =INDEX($Y:$Y,MATCH(AB98,$C:$C,FALSE)) -> 45625
A99: =A98+1 -> 92 | B99: 45550 | C99: GMIAMMPIK/2024/09/093 | D99: 11L-3024 | E99: =VLOOKUP(D99,MP!$A$1:$C$14184,2,0) -> LED FLood Light 6 Eyes 18 Watt 10-30 VDC | F99: 2 | G99: PCS | H99: W52611 | I99: =IFERROR(INDEX(POP!$I:$I,MATCH(H99,POP!$G:$G,0)),"general") -> general | J99: =IFERROR(INDEX(POP!$E:$E,MATCH(H99,POP!$G:$G,0)),"general") -> general | K99: REPLACE WORKLAMP | L99: FANDY | M99: FAUZI | N99: 200000747263 | O99: DONE FROM BC | P99: =B99 -> 45550 | Q99: 9200017817 | R99: 45550 | T99: 45555 | U99: DO 27109 | V99: 45361 | W99: GMI-0023124 | X99: 45568 | Y99: 45625 | AA99: =AA98+1 -> 92 | AB99: GMIAMMPIK/2024/09/093 | AC99: =IFERROR(INDEX($B:$B,MATCH(AB99,$C:$C,FALSE)),"") -> 45550 | AD99: =INDEX($U:$U,MATCH(AB99,$C:$C,FALSE)) -> DO 27109 | AE99: =IFERROR(INDEX($V:$V,MATCH(AB99,$C:$C,FALSE)),"") -> 45361 | AF99: =IFERROR(INDEX($N:$N,MATCH(AB99,$C:$C,FALSE)),"") -> 200000747263 | AG99: =INDEX($Q:$Q,MATCH(AB99,$C:$C,FALSE)) -> 9200017817 | AH99: =IFERROR(INDEX($S:$S,MATCH(AB99,$C:$C,FALSE)),"") | AI99: =IFERROR(INDEX($T:$T,MATCH(AB99,$C:$C,FALSE)),"") -> 45555 | AJ99: =INDEX($W:$W,MATCH(AB99,$C:$C,FALSE)) -> GMI-0023124 | AK99: =IFERROR(INDEX($X:$X,MATCH(AB99,$C:$C,FALSE)),"") -> 45568 | AL99: =INDEX($O:$O,MATCH(AF99,$N:$N,FALSE),"") -> DONE FROM BC | AM99: =INDEX($Y:$Y,MATCH(AB99,$C:$C,FALSE)) -> 45625
A100: =A99+1 -> 93 | B100: 45552 | C100: GMIAMMPIK/2024/09/094 | D100: 11L-3024 | E100: =VLOOKUP(D100,MP!$A$1:$C$14184,2,0) -> LED FLood Light 6 Eyes 18 Watt 10-30 VDC | F100: 6 | G100: PCS | H100: W52611 | I100: =IFERROR(INDEX(POP!$I:$I,MATCH(H100,POP!$G:$G,0)),"general") -> general | J100: =IFERROR(INDEX(POP!$E:$E,MATCH(H100,POP!$G:$G,0)),"general") -> general | K100: REPLACE WORKLAMP | L100: FANDY | M100: FAUZI | N100: 200000747432 | O100: DONE FROM BC | P100: =B100 -> 45552 | Q100: 9200017842 | R100: 45551 | T100: 45555 | U100: DO 27111 | V100: 45361 | W100: GMI-0023125 | X100: 45568 | Y100: 45625 | AA100: =AA99+1 -> 93 | AB100: GMIAMMPIK/2024/09/094 | AC100: =IFERROR(INDEX($B:$B,MATCH(AB100,$C:$C,FALSE)),"") -> 45552 | AD100: =INDEX($U:$U,MATCH(AB100,$C:$C,FALSE)) -> DO 27111 | AE100: =IFERROR(INDEX($V:$V,MATCH(AB100,$C:$C,FALSE)),"") -> 45361 | AF100: =IFERROR(INDEX($N:$N,MATCH(AB100,$C:$C,FALSE)),"") -> 200000747432 | AG100: =INDEX($Q:$Q,MATCH(AB100,$C:$C,FALSE)) -> 9200017842 | AH100: =IFERROR(INDEX($S:$S,MATCH(AB100,$C:$C,FALSE)),"") | AI100: =IFERROR(INDEX($T:$T,MATCH(AB100,$C:$C,FALSE)),"") -> 45555 | AJ100: =INDEX($W:$W,MATCH(AB100,$C:$C,FALSE)) -> GMI-0023125 | AK100: =IFERROR(INDEX($X:$X,MATCH(AB100,$C:$C,FALSE)),"") -> 45568 | AL100: =INDEX($O:$O,MATCH(AF100,$N:$N,FALSE),"") -> DONE FROM BC | AM100: =INDEX($Y:$Y,MATCH(AB100,$C:$C,FALSE)) -> 45625
...

Sheet AMM PIK 2026
D1: WAREHOUSE | Q1: MARKETING | U1: LOGISTICS | W1: FINANCE | AB1: DATA TABLE DASHBOARD SPB | AO1: DASHBOARD SPB GMI AMM PIK
A2: NO | B2: TANGGAL SPB | C2: NO SPB | D2: PART NUMBER | E2: PART NAME | F2: QTY | G2: UOM | H2: UNIT CODE | I2: TYPE UNIT | J2: BRAND | K2: PROBLEM | L2: PIC GMI | M2: PIC PPA | N2: NO WO | O2: STATUS WO | P2: WO DATE | Q2: NO PO | R2: PO DATE | S2: NO SO | T2: SO DATE | U2: NO DO | V2: DO DATE | W2: NO INVOICE | X2: TANGGAL KIRIM | Y2: STATUS PAYMENT | AA2: NO | AB2: NO SPB | AC2: TGL SPB | AD2: NO DO | AE2: TGL DO | AF2: NO WO | AG2: NO PO | AH2: NO SO | AI2: TGL so | AJ2: NO INVOICE | AK2: TANGAL INVOICE | AL2: STATUS SPB | AM2: STATUS PAYMENT | AO2: NO | AP2: DESCRIPTION | AQ2: DONE | AR2: WAITING | AS2: TOTAL
A3: 1 | B3: 5 Januari 2026 | C3: GMIAMMPIK/2026/1/0308 | D3: 11L-3024 | E3: =VLOOKUP(D3,MP!$A$1:$C$14184,2,0) -> LED FLood Light 6 Eyes 18 Watt 10-30 VDC | F3: 1 | G3: PCS | H3: FT52513 | I3: general | J3: general | K3: REPLACE WORKLAMP | L3: DIMAS | M3: WIWIK | N3: 200000982891 | O3: DONE FROM BC | P3: 46027 | Q3: 9200065726 | R3: 46025 | S3: 41663 | T3: 46028 | U3: DO 45471 | V3: 46030 | W3: GMI26-0044453 | X3: 46030
A4: 2 | B4: 5 Januari 2026 | C4: GMIAMMPIK/2026/1/0308 | D4: 11L-3024 | E4: =VLOOKUP(D4,MP!$A$1:$C$14184,2,0) -> LED FLood Light 6 Eyes 18 Watt 10-30 VDC | F4: 1 | G4: PCS | H4: FL08PPA | I4: general | J4: general | K4: REPLACE WORKLAMP | L4: DIMAS | M4: WIWIK | N4: 200000982984 | O4: DONE FROM BC | P4: 46027 | Q4: 9200065726 | R4: 46025 | S4: 41663 | T4: 46028 | U4: DO 45471 | V4: 46030 | W4: GMI26-0044453 | X4: 46030
A5: 3 | B5: 5 Januari 2026 | C5: GMIAMMPIK/2026/1/0309 | D5: 11L-1290-ARW | E5: =VLOOKUP(D5,MP!$A$1:$C$14184,2,0) -> LED Combination Lamp Amber Red White | F5: 1 | G5: PCS | H5: F54441 | I5: general | J5: general | K5: REPLACE WORKLAMP | L5: DIMAS | M5: WIWIK | N5: 200000984490 | O5: DONE FROM BC | P5: 46027 | Q5: 9200065877 | R5: 46026 | S5: 41664 | T5: 46028 | U5: DO 45644 | V5: 46035 | W5: GMI26-0044734 | X5: 46037
A6: 4 | B6: 5 Januari 2026 | C6: GMIAMMPIK/2026/1/0309 | D6: 11L-3024 | E6: =VLOOKUP(D6,MP!$A$1:$C$14184,2,0) -> LED FLood Light 6 Eyes 18 Watt 10-30 VDC | F6: 3 | G6: PCS | H6: F54441 | I6: general | J6: general | K6: REPLACE WORKLAMP | L6: DIMAS | M6: WIWIK | N6: 200000984490 | O6: DONE FROM BC | P6: 46027 | Q6: 9200065877 | R6: 46026 | S6: 41664 | T6: 46028 | U6: DO 45644 | V6: 46035 | W6: GMI26-0044734 | X6: 46037
A7: 5 | B7: 5 Januari 2026 | C7: GMIAMMPIK/2026/1/0309 | D7: 3L4-7ASB | E7: =VLOOKUP(D7,MP!$A$1:$C$14184,2,0) -> LED (SMD Led) Strobe Beacon Blue : 12-24VDC with Alumunium screw base | F7: 2 | G7: PCS | H7: F54441 | I7: general | J7: general | K7: REPLACE WORKLAMP | L7: DIMAS | M7: WIWIK | N7: 200000984490 | O7: DONE FROM BC | P7: 46027 | Q7: 9200065877 | R7: 46026 | S7: 41664 | T7: 46028 | U7: DO 45644 | V7: 46035 | W7: GMI26-0044734 | X7: 46037
A8: 6 | B8: 5 Januari 2026 | C8: GMIAMMPIK/2026/1/0310 | D8: 11L-1290-ARW | E8: =VLOOKUP(D8,MP!$A$1:$C$14184,2,0) -> LED Combination Lamp Amber Red White | F8: 1 | G8: PCS | H8: DA48127PPA | I8: general | J8: general | K8: REPLACE WORKLAMP | L8: DIMAS | M8: WIWIK | N8: 200000985605 | O8: DONE FROM BC | P8: 46027 | Q8: 9200065980 | R8: 46027 | S8: 41665 | T8: 46028 | U8: DO 45472 | V8: 46030 | W8: GMI26-0044452 | X8: 46030
A9: 7 | B9: 9 Januari 2026 | C9: GMIAMMPIK/2026/1/0311 | D9: 3L4-7ASA | E9: =VLOOKUP(D9,MP!$A$1:$C$14184,2,0) -> LED (SMD Led) Strobe Beacon Amber : 12-24VDC with Alumunium screw base | F9: 1 | G9: PCS | H9: D5859 | I9: general | J9: general | K9: REPLACE WORKLAMP | L9: DIMAS | M9: WIWIK | N9: 200000987466 | O9: DONE FROM BC | P9: 46031 | Q9: 9200066710 | R9: 46031 | S9: 41886 | T9: 46034 | U9: DO 45724 | V9: 46036 | W9: GMI26-0044733 | X9: 46037
A10: 8 | B10: 12 Januari 2026 | C10: GMIAMMPIK/2026/1/0312 | D10: 11L-3024 | E10: =VLOOKUP(D10,MP!$A$1:$C$14184,2,0) -> LED FLood Light 6 Eyes 18 Watt 10-30 VDC | F10: 6 | G10: PCS | H10: PLTAM15 | I10: general | J10: general | K10: REPLACE WORKLAMP | L10: DIMAS | M10: WIWIK | N10: 200000986910 | O10: DONE FROM BC | P10: 46034 | Q10: 9200067070 | R10: 46034 | S10: 41887 | T10: 46034 | U10: DO 45725 | V10: 46036 | W10: GMI26-0044732 | X10: 46037
A11: 9 | B11: 12 Januari 2026 | C11: GMIAMMPIK/2026/1/0312 | D11: 3L3-8AB | E11: =VLOOKUP(D11,MP!$A$1:$C$14184,2,0) -> Blue Xenon Beacon Light 12-24VDC with alumunium screw base | F11: 1 | G11: PCS | H11: PLTAM15 | I11: general | J11: general | K11: REPLACE WORKLAMP | L11: DIMAS | M11: WIWIK | N11: 200000986910 | O11: DONE FROM BC | P11: 46034 | Q11: 9200067070 | R11: 46034 | S11: 41887 | T11: 46034 | U11: DO 45725 | V11: 46036 | W11: GMI26-0044732 | X11: 46037
A12: 10 | B12: 20 Januari 2026 | C12: GMIAMMPIK/2026/1/0313 | D12: 11L-3024 | E12: =VLOOKUP(D12,MP!$A$1:$C$14184,2,0) -> LED FLood Light 6 Eyes 18 Watt 10-30 VDC | F12: 16 | G12: PCS | H12: FT52527 | I12: general | J12: general | K12: REPLACE WORKLAMP | L12: DIMAS | M12: WIWIK | N12: 200000989610 | O12: DONE FROM BC | P12: 46042 | Q12: 9200068303 | R12: 46042 | S12: 42118 | T12: 46043 | U12: DO 45955 | V12: 46043 | W12: GMI26-0044919 | X12: 46043
A13: 11 | B13: 20 Januari 2026 | C13: GMIAMMPIK/2026/1/0313 | D13: 3L3-8AA | E13: =VLOOKUP(D13,MP!$A$1:$C$14184,2,0) -> Amber Xenon Beacon Light 12-24VDC with alumunium screw base | F13: 3 | G13: PCS | H13: FT52527 | I13: general | J13: general | K13: REPLACE WORKLAMP | L13: DIMAS | M13: WIWIK | N13: 200000989610 | O13: DONE FROM BC | P13: 46042 | Q13: 9200068303 | R13: 46042 | S13: 42118 | T13: 46043 | U13: DO 45955 | V13: 46043 | W13: GMI26-0044919 | X13: 46043
A14: 12 | B14: 20 Januari 2026 | C14: GMIAMMPIK/2026/1/0313 | D14: 3L4-7ASA | E14: =VLOOKUP(D14,MP!$A$1:$C$14184,2,0) -> LED (SMD Led) Strobe Beacon Amber : 12-24VDC with Alumunium screw base | F14: 4 | G14: PCS | H14: FT52527 | I14: general | J14: general | K14: REPLACE WORKLAMP | L14: DIMAS | M14: WIWIK | N14: 200000989610 | O14: DONE FROM BC | P14: 46042 | Q14: 9200068303 | R14: 46042 | S14: 42118 | T14: 46043 | U14: DO 45955 | V14: 46043 | W14: GMI26-0044919 | X14: 46043
... A23: 21 | B23: 9 Februari 2026 | C23: GMIAMMPIK/2026/2/0319 | D23: 11L-1290-ARW | E23: =VLOOKUP(D23,MP!$A$1:$C$14184,2,0) -> LED Combination Lamp Amber Red White | F23: 3 | G23: PCS | H23: DA48122PPA | I23: general | J23: general | K23: REPLACE WORKLAMP | L23: DIMAS | M23: WIWIK | N23: 200001003486 | O23: DONE FROM BC | P23: 46062 | Q23: 9200071172 | R23: 46062 | S23: 42653 | T23: 46061 | U23: DO 46551 | V23: 46063 | W23: GMI26-0045461 | X23: 46063
A24: 22 | B24: 18 Februari 2026 | C24: GMIAMMPIK/2026/2/0320 | D24: 3L3-8AB | E24: =VLOOKUP(D24,MP!$A$1:$C$14184,2,0) -> Blue Xenon Beacon Light 12-24VDC with alumunium screw base | F24: 1 | G24: PCS | H24: D5863 | I24: general | J24: general | K24: REPLACE WORKLAMP | L24: DIMAS | M24: WIWIK | N24: 200001009857 | O24: DONE FROM BC | P24: 46071 | Q24: 9200072643 | R24: 46070 | S24: 43028 | T24: 46072 | U24: DO 46968 | V24: 46072
A25: 23 | B25: 18 Februari 2026 | C25: GMIAMMPIK/2026/2/0320 | D25: 3L4-7ASA | E25: =VLOOKUP(D25,MP!$A$1:$C$14184,2,0) -> LED (SMD Led) Strobe Beacon Amber : 12-24VDC with Alumunium screw base | F25: 1 | G25: PCS | H25: D5863 | I25: general | J25: general | K25: REPLACE WORKLAMP | L25: DIMAS | M25: WIWIK | N25: 200001009857 | O25: DONE FROM BC | P25: 46071 | Q25: 9200072643 | R25: 46070 | S25: 43028 | T25: 46072 | U25: DO 46968 | V25: 46072
A26: 24 | B26: 18 Februari 2026 | C26: GMIAMMPIK/2026/2/0320 | D26: 3L4-7ASB | E26: =VLOOKUP(D26,MP!$A$1:$C$14184,2,0) -> LED (SMD Led) Strobe Beacon Blue : 12-24VDC with Alumunium screw base | F26: 1 | G26: PCS | H26: D5863 | I26: general | J26: general | K26: REPLACE WORKLAMP | L26: DIMAS | M26: WIWIK | N26: 200001009857 | O26: DONE FROM BC | P26: 46071 | Q26: 9200072643 | R26: 46070 | S26: 43028 | T26: 46072 | U26: DO 46968 | V26: 46072
A27: 25 | B27: 25 Februari 2026 | C27: GMIAMMPIK/2026/2/0321 | D27: 11L-3024 | E27: =VLOOKUP(D27,MP!$A$1:$C$14184,2,0) -> LED FLood Light 6 Eyes 18 Watt 10-30 VDC | F27: 2 | G27: PCS | H27: DA54242 | I27: general | J27: general | K27: REPLACE WORKLAMP | L27: DIMAS | M27: WIWIK | N27: 200001012068 | O27: DONE FROM BC | P27: 46078 | Q27: 9200074085 | R27: 46078 | S27: 43370 | T27: 46080 | U27: DO 47328 | V27: 46080
A28: 26 | B28: 25 Februari 2026 | C28: GMIAMMPIK/2026/2/0321 | D28: 11L-1290-ARW | E28: =VLOOKUP(D28,MP!$A$1:$C$14184,2,0) -> LED Combination Lamp Amber Red White | F28: 1 | G28: PCS | H28: DA54242 | I28: general | J28: general | K28: REPLACE WORKLAMP | L28: DIMAS | M28: WIWIK | N28: 200001012068 | O28: DONE FROM BC | P28: 46078 | Q28: 9200074085 | R28: 46078 | S28: 43370 | T28: 46080 | U28: DO 47328 | V28: 46080
A29: 27 | B29: 2 Maret 2026 | C29: GMIAMMPIK/2026/3/0322 | D29: 11L-3024 | E29: =VLOOKUP(D29,MP!$A$1:$C$14184,2,0) -> LED FLood Light 6 Eyes 18 Watt 10-30 VDC | F29: 4 | G29: PCS | H29: D5871 | I29: general | J29: general | K29: REPLACE WORKLAMP | L29: DIMAS | M29: WIWIK | N29: 200001016403 | O29: DONE FROM BC | P29: 46083 | Q29: 9200074794 | R29: 46082 | S29: 43497 | T29: 46084 | U29: DO 47362 | V29: 46086
A30: 28 | B30: 2 Maret 2026 | C30: GMIAMMPIK/2026/3/0322 | D30: 3L4-7ASA | E30: =VLOOKUP(D30,MP!$A$1:$C$14184,2,0) -> LED (SMD Led) Strobe Beacon Amber : 12-24VDC with Alumunium screw base | F30: 4 | G30: PCS | H30: D5871 | I30: general | J30: general | K30: REPLACE WORKLAMP | L30: DIMAS | M30: WIWIK | N30: 200001016403 | O30: DONE FROM BC | P30: 46083 | Q30: 9200074794 | R30: 46082 | S30: 43497 | T30: 46084 | U30: DO 47362 | V30: 46086
A31: 29 | B31: 2 Maret 2026 | C31: GMIAMMPIK/2026/3/0322 | D31: 3L4-7ASB | E31: =VLOOKUP(D31,MP!$A$1:$C$14184,2,0) -> LED (SMD Led) Strobe Beacon Blue : 12-24VDC with Alumunium screw base | F31: 1 | G31: PCS | H31: D5871 | I31: general | J31: general | K31: REPLACE WORKLAMP | L31: DIMAS | M31: WIWIK | N31: 200001016403 | O31: DONE FROM BC | P31: 46083 | Q31: 9200074794 | R31: 46082 | S31: 43497 | T31: 46084 | U31: DO 47362 | V31: 46086
A32: 30 | B32: 2 Maret 2026 | C32: GMIAMMPIK/2026/3/0323 | D32: 1L35-ADB-I | E32: =VLOOKUP(D32,MP!$A$1:$C$14184,2,0) -> ADBLUE EMULATOR BOX V2 CONSUMABLE | F32: 1 | G32: SET | H32: FT52513 | I32: general | J32: general | K32: ATTCH TOOL NON ACTIVE ADBLUE | L32: DIMAS | M32: WIWIK | N32: 200001002201 | O32: DONE FROM BC | P32: 46083 | Q32: 9200073067 | R32: 46072 | S32: 43407 | T32: 46083 | U32: DO 47374 | V32: 46084
A33: 31 | B33: 2 Maret 2026 | C33: GMIAMMPIK/2026/3/0324 | D33: 1L35-ADB-I | E33: =VLOOKUP(D33,MP!$A$1:$C$14184,2,0) -> ADBLUE EMULATOR BOX V2 CONSUMABLE | F33: 1 | G33: SET | H33: LT52501 | I33: general | J33: general | K33: ATTCH TOOL NON ACTIVE ADBLUE | L33: DIMAS | M33: WIWIK | N33: 200001002205 | O33: DONE FROM BC | P33: 46083 | Q33: 9200073068 | R33: 46072 | S33: 43406 | T33: 46083 | U33: DO 47373 | V33: 46084
A34: 32 | B34: 2 Maret 2026 | C34: GMIAMMPIK/2026/3/0325 | D34: 1L35-ADB-I | E34: =VLOOKUP(D34,MP!$A$1:$C$14184,2,0) -> ADBLUE EMULATOR BOX V2 CONSUMABLE | F34: 1 | G34: SET | H34: FT52527 | I34: general | J34: general | K34: ATTCH TOOL NON ACTIVE ADBLUE | L34: DIMAS | M34: WIWIK | N34: 200001002204 | O34: DONE FROM BC | P34: 46083 | Q34: 9200073069 | R34: 46072 | S34: 43408 | T34: 46083 | U34: DO 47375 | V34: 46084
A35: 33 | B35: 2 Maret 2026 | C35: GMIAMMPIK/2026/3/0326 | D35: 1L35-ADB-I | E35: =VLOOKUP(D35,MP!$A$1:$C$14184,2,0) -> ADBLUE EMULATOR BOX V2 CONSUMABLE | F35: 1 | G35: SET | H35: FT52526 | I35: general | J35: general | K35: ATTCH TOOL NON ACTIVE ADBLUE | L35: DIMAS | M35: WIWIK | N35: 200001002203 | O35: DONE FROM BC | P35: 46083 | Q35: 9200073070 | R35: 46072 | S35: 43410 | T35: 46083 | U35: DO 47377 | V35: 46084
... A53: 51 | B53: 31 Maret 2026 | C53: GMIAMMPIK/2026/3/0333 | D53: 11L-1290-ARW | E53: =VLOOKUP(D53,MP!$A$1:$C$14184,2,0) -> LED Combination Lamp Amber Red White | F53: 1 | G53: PCS | H53: FT52527 | I53: general | J53: general | K53: REPLACE WORKLAMP | L53: DIMAS | M53: WIWIK | N53: 200001029782 | O53: DONE FROM BC | P53: 46112 | Q53: 9200079303 | R53: 46112 | S53: 44379 | T53: 46112 | U53: DO 48299 | V53: 46112
A54: 52 | B54: 46122 | C54: GMIAMMPIK/2026/4/0334 | D54: 3L3-8AA | E54: =VLOOKUP(D54,MP!$A$1:$C$14184,2,0) -> Amber Xenon Beacon Light 12-24VDC with alumunium screw base | F54: 1 | G54: PCS | H54: FT52521 | I54: general | J54: general | K54: REPLACE WORKLAMP | L54: DIMAS | M54: WIWIK | N54: 200001034903 | O54: DONE FROM BC | P54: 46122 | Q54: 9200080412 | R54: 46117 | S54: 44575 | T54: 46122 | U54: DO 48599 | V54: 46127
A55: 53 | B55: 46122 | C55: GMIAMMPIK/2026/4/0334 | D55: 3L3-8AB | E55: =VLOOKUP(D55,MP!$A$1:$C$14184,2,0) -> Blue Xenon Beacon Light 12-24VDC with alumunium screw base | F55: 3 | G55: PCS | H55: FT52521 | I55: general | J55: general | K55: REPLACE WORKLAMP | L55: DIMAS | M55: WIWIK | N55: 200001034903 | O55: DONE FROM BC | P55: 46122 | Q55: 9200080412 | R55: 46117 | S55: 44575 | T55: 46122 | U55: DO 48599 | V55: 46127
A56: 54 | B56: 46122 | C56: GMIAMMPIK/2026/4/0334 | D56: 11L-3024 | E56: =VLOOKUP(D56,MP!$A$1:$C$14184,2,0) -> LED FLood Light 6 Eyes 18 Watt 10-30 VDC | F56: 5 | G56: PCS | H56: FT52521 | I56: general | J56: general | K56: REPLACE WORKLAMP | L56: DIMAS | M56: WIWIK | N56: 200001034903 | O56: DONE FROM BC | P56: 46122 | Q56: 9200080412 | R56: 46117 | S56: 44575 | T56: 46122 | U56: DO 48599 | V56: 46127
A57: 55 | B57: 46122 | C57: GMIAMMPIK/2026/4/0334 | D57: 11L-1290-ARW | E57: =VLOOKUP(D57,MP!$A$1:$C$14184,2,0) -> LED Combination Lamp Amber Red White | F57: 2 | G57: PCS | H57: FT52521 | I57: general | J57: general | K57: REPLACE WORKLAMP | L57: DIMAS | M57: WIWIK | N57: 200001034903 | O57: DONE FROM BC | P57: 46122 | Q57: 9200080412 | R57: 46117 | S57: 44575 | T57: 46122 | U57: DO 48599 | V57: 46127
A58: 56 | B58: 46125 | C58: GMIAMMPIK/2026/4/0335 | D58: 3L3-8AA | E58: =VLOOKUP(D58,MP!$A$1:$C$14184,2,0) -> Amber Xenon Beacon Light 12-24VDC with alumunium screw base | F58: 1 | G58: PCS | H58: FT52529 | I58: general | J58: general | K58: REPLACE WORKLAMP | L58: DIMAS | M58: WIWIK | N58: 200001040624 | O58: DONE FROM BC | P58: 46125 | Q58: 9200081330 | R58: 46124 | S58: 44716 | T58: 46129 | U58: 48722 | V58: 46129
A59: 57 | B59: 46129 | C59: GMIAMMPIK/2026/4/0336 | D59: 11L-3024 | E59: =VLOOKUP(D59,MP!$A$1:$C$14184,2,0) -> LED FLood Light 6 Eyes 18 Watt 10-30 VDC | F59: 3 | G59: PCS | H59: MF1203PPA | I59: general | J59: general | K59: REPLACE WORKLAMP | L59: DIMAS | M59: WIWIK | N59: 200001040911 | O59: DONE FROM BC | P59: 46129 | Q59: 9200081758 | R59: 46126 | S59: 44798 | T59: 46129 | U59: DO 48769 | V59: 46129
A60: 58 | B60: 46129 | C60: GMIAMMPIK/2026/4/0336 | D60: 3L4-7ASB | E60: =VLOOKUP(D60,MP!$A$1:$C$14184,2,0) -> LED (SMD Led) Strobe Beacon Blue : 12-24VDC with Alumunium screw base | F60: 4 | G60: PCS | H60: MF1203PPA | I60: general | J60: general | K60: REPLACE WORKLAMP | L60: DIMAS | M60: WIWIK | N60: 200001040911 | O60: DONE FROM BC | P60: 46129 | Q60: 9200081758 | R60: 46126 | S60: 44798 | T60: 46129 | U60: DO 48769 | V60: 46129
A61: 59 | B61: 46129 | C61: GMIAMMPIK/2026/4/0336 | D61: 3L3-8AA | E61: =VLOOKUP(D61,MP!$A$1:$C$14184,2,0) -> Amber Xenon Beacon Light 12-24VDC with alumunium screw base | F61: 1 | G61: PCS | H61: MF1203PPA | I61: general | J61: general | K61: REPLACE WORKLAMP | L61: DIMAS | M61: WIWIK | N61: 200001040911 | O61: DONE FROM BC | P61: 46129 | Q61: 9200081758 | R61: 46126 | S61: 44798 | T61: 46129 | U61: DO 48769 | V61: 46129
A62: 60 | B62: 46133 | C62: GMIAMMPIK/2026/4/0337 | D62: 11L-1290-ARW | E62: =VLOOKUP(D62,MP!$A$1:$C$14184,2,0) -> LED Combination Lamp Amber Red White | F62: 2 | G62: PCS | H62: DA54825 | I62: general | J62: general | K62: REPLACE WORKLAMP | L62: DIMAS | M62: WIWIK | N62: 200001044526 | O62: DONE FROM BC | P62: 46133 | Q62: 9200082849 | R62: 46132 | S62: 44938 | T62: 46137 | U62: 49015 | V62: 46140
A63: 61 | B63: 46133 | C63: GMIAMMPIK/2026/4/0337 | D63: 11L-3024 | E63: =VLOOKUP(D63,MP!$A$1:$C$14184,2,0) -> LED FLood Light 6 Eyes 18 Watt 10-30 VDC | F63: 2 | G63: PCS | H63: DA54825 | I63: general | J63: general | K63: REPLACE WORKLAMP | L63: DIMAS | M63: WIWIK | N63: 200001044526 | O63: DONE FROM BC | P63: 46133 | Q63: 9200082849 | R63: 46132 | S63: 44938 | T63: 46137 | U63: 49015 | V63: 46140
A64: 62 | B64: 46133 | C64: GMIAMMPIK/2026/4/0337 | D64: 3L4-7ASA | E64: =VLOOKUP(D64,MP!$A$1:$C$14184,2,0) -> LED (SMD Led) Strobe Beacon Amber : 12-24VDC with Alumunium screw base | F64: 1 | G64: PCS | H64: DA54825 | I64: general | J64: general | K64: REPLACE WORKLAMP | L64: DIMAS | M64: WIWIK | N64: 200001044526 | O64: DONE FROM BC | P64: 46133 | Q64: 9200082849 | R64: 46132 | S64: 44938 | T64: 46137 | U64: 49015 | V64: 46140
A65: 63 | B65: 46141 | C65: GMIAMMPIK/2026/4/0338 | D65: 11L-1290-ARW | E65: =VLOOKUP(D65,MP!$A$1:$C$14184,2,0) -> LED Combination Lamp Amber Red White | F65: 1 | G65: PCS | H65: general | I65: general | J65: general | K65: REPLACE WORKLAMP | L65: DIMAS | M65: WIWIK | O65: DONE FROM BC | P65: 46141 | Q65: 9200084156 | R65: 46140 | S65: 45219 | T65: 46141 | U65: 49192 | V65: 46142
A66: 64 | B66: 46141 | C66: GMIAMMPIK/2026/4/0338 | D66: 3L3-8AA | E66: =VLOOKUP(D66,MP!$A$1:$C$14184,2,0) -> Amber Xenon Beacon Light 12-24VDC with alumunium screw base | F66: 3 | G66: PCS | H66: general | I66: general | J66: general | K66: REPLACE WORKLAMP | L66: DIMAS | M66: WIWIK | O66: DONE FROM BC | P66: 46141 | Q66: 9200084156 | R66: 46140 | S66: 45219 | T66: 46141 | U66: 49192 | V66: 46142
A67: 65 | B67: 46141 | C67: GMIAMMPIK/2026/4/0338 | D67: 3L3-8AB | E67: =VLOOKUP(D67,MP!$A$1:$C$14184,2,0) -> Blue Xenon Beacon Light 12-24VDC with alumunium screw base | F67: 1 | G67: PCS | H67: general | I67: general | J67: general | K67: REPLACE WORKLAMP | L67: DIMAS | M67: WIWIK | O67: DONE FROM BC | P67: 46141 | Q67: 9200084156 | R67: 46140 | S67: 45219 | T67: 46141 | U67: 49192 | V67: 46142
A68: 66 | B68: 46141 | C68: GMIAMMPIK/2026/4/0338 | D68: 11L-3024 | E68: =VLOOKUP(D68,MP!$A$1:$C$14184,2,0) -> LED FLood Light 6 Eyes 18 Watt 10-30 VDC | F68: 6 | G68: PCS | H68: general | I68: general | J68: general | K68: REPLACE WORKLAMP | L68: DIMAS | M68: WIWIK | O68: DONE FROM BC | P68: 46141 | Q68: 9200084156 | R68: 46140 | S68: 45219 | T68: 46141 | U68: 49192 | V68: 46142
A69: 67 | B69: 46141 | C69: GMIAMMPIK/2026/4/0338 | D69: 3L4-7ASA | E69: =VLOOKUP(D69,MP!$A$1:$C$14184,2,0) -> LED (SMD Led) Strobe Beacon Amber : 12-24VDC with Alumunium screw base | F69: 2 | G69: PCS | H69: general | I69: general | J69: general | K69: REPLACE WORKLAMP | L69: DIMAS | M69: WIWIK | O69: DONE FROM BC | P69: 46141 | Q69: 9200084156 | R69: 46140 | S69: 45219 | T69: 46141 | U69: 49192 | V69: 46142
A70: 68 | B70: 46142 | C70: GMIAMMPIK/2026/4/0339 | D70: 3L4-7ASA | E70: =VLOOKUP(D70,MP!$A$1:$C$14184,2,0) -> LED (SMD Led) Strobe Beacon Amber : 12-24VDC with Alumunium screw base | F70: 1 | G70: SET | H70: E53905 | I70: general | J70: general | K70: REPLACE WORKLAMP | L70: DIMAS | M70: WIWIK | N70: 200001051992 | O70: DONE FROM BC | P70: 46142 | Q70: 9200084624 | R70: 46142 | S70: 45480 | T70: 46150 | U70: 49523 | V70: 11 Mei 2026
A71: 69 | B71: 46142 | C71: GMIAMMPIK/2026/4/0340 | D71: 1L35-ADB-I | E71: =VLOOKUP(D71,MP!$A$1:$C$14184,2,0) -> ADBLUE EMULATOR BOX V2 CONSUMABLE | F71: 1 | G71: SET | H71: WA52520 | I71: general | J71: general | K71: ATTCH TOOL NON ACTIVE ADBLUE | L71: DIMAS | M71: WIWIK | N71: 200001043402 | O71: DONE FROM BC | P71: 46142 | Q71: 9200082430 | R71: 46130 | S71: 45478 | T71: 46150 | U71: 49521 | V71: 11 Mei 2026
A72: 70 | B72: 46142 | C72: GMIAMMPIK/2026/4/0341 | D72: 1L35-ADB-I | E72: =VLOOKUP(D72,MP!$A$1:$C$14184,2,0) -> ADBLUE EMULATOR BOX V2 CONSUMABLE | F72: 1 | G72: SET | H72: WA52516 | I72: general | J72: general | K72: ATTCH TOOL NON ACTIVE ADBLUE | L72: DIMAS | M72: WIWIK | N72: 200001043404 | O72: DONE FROM BC | P72: 46142 | Q72: 9200082431 | R72: 46130 | S72: 45479 | T72: 46150 | U72: 49522 | V72: 11 Mei 2026
A73: 71 | B73: 46148 | C73: GMIAMMPIK/2026/5/0342 | D73: 11L-3024 | E73: =VLOOKUP(D73,MP!$A$1:$C$14184,2,0) -> LED FLood Light 6 Eyes 18 Watt 10-30 VDC | F73: 4 | G73: PCS | H73: H57122 | I73: general | J73: general | K73: REPLACE WORKLAMP | L73: DIMAS | M73: WIWIK | N73: 200001052706 | O73: DONE FROM BC | P73: 46148 | Q73: 9200084820 | R73: 46143 | S73: 45481 | T73: 46150 | U73: 49524 | V73: 11 Mei 2026
A74: 72 | B74: 46148 | C74: GMIAMMPIK/2026/5/0342 | D74: 3L3-8AB | E74: =VLOOKUP(D74,MP!$A$1:$C$14184,2,0) -> Blue Xenon Beacon Light 12-24VDC with alumunium screw base | F74: 1 | G74: PCS | H74: H57122 | I74: general | J74: general | K74: REPLACE WORKLAMP | L74: DIMAS | M74: WIWIK | N74: 200001052706 | O74: DONE FROM BC | P74: 46148 | Q74: 9200084820 | R74: 46143 | S74: 45481 | T74: 46150 | U74: 49524 | V74: 11 Mei 2026
A75: 73 | B75: 46148 | C75: GMIAMMPIK/2026/5/0343 | D75: 11L-1290-ARW | E75: =VLOOKUP(D75,MP!$A$1:$C$14184,2,0) -> LED Combination Lamp Amber Red White | F75: 1 | G75: PCS | H75: P54609 | I75: general | J75: general | K75: REPLACE WORKLAMP | L75: DIMAS | M75: WIWIK | N75: 200001053449 | O75: DONE FROM BC | P75: 46148 | Q75: 9200084967 | R75: 46144 | S75: 45482 | T75: 46150 | U75: 49525 | V75: 11 Mei 2026
A76: 74 | B76: 46148 | C76: GMIAMMPIK/2026/5/0343 | D76: 3L4-7ASA | E76: =VLOOKUP(D76,MP!$A$1:$C$14184,2,0) -> LED (SMD Led) Strobe Beacon Amber : 12-24VDC with Alumunium screw base | F76: 1 | G76: PCS | H76: P54609 | I76: general | J76: general | K76: REPLACE WORKLAMP | L76: DIMAS | M76: WIWIK | N76: 200001053449 | O76: DONE FROM BC | P76: 46148 | Q76: 9200084967 | R76: 46144 | S76: 45482 | T76: 46150 | U76: 49525 | V76: 11 Mei 2026
A77: 75 | B77: 46148 | C77: GMIAMMPIK/2026/5/0344 | D77: 11L-3024 | E77: =VLOOKUP(D77,MP!$A$1:$C$14184,2,0) -> LED FLood Light 6 Eyes 18 Watt 10-30 VDC | F77: 1 | G77: PCS | H77: FT52521 | I77: general | J77: general | K77: REPLACE WORKLAMP | L77: DIMAS | M77: WIWIK | N77: 200001054092 | O77: DONE FROM BC | P77: 46148 | Q77: 9200085491 | R77: 46146 | S77: 45483 | T77: 46150 | U77: 49526 | V77: 11 Mei 2026
A78: 76 | B78: 46148 | C78: GMIAMMPIK/2026/5/0344 | D78: 3L4-7ASA | E78: =VLOOKUP(D78,MP!$A$1:$C$14184,2,0) -> LED (SMD Led) Strobe Beacon Amber : 12-24VDC with Alumunium screw base | F78: 1 | G78: PCS | H78: FT52521 | I78: general | J78: general | K78: REPLACE WORKLAMP | L78: DIMAS | M78: WIWIK | N78: 200001054092 | O78: DONE FROM BC | P78: 46148 | Q78: 9200085491 | R78: 46146 | S78: 45483 | T78: 46150 | U78: 49526 | V78: 11 Mei 2026
A79: 77 | B79: 46154 | C79: GMIAMMPIK/2026/5/0345 | D79: 3L4-7ASA | E79: =VLOOKUP(D79,MP!$A$1:$C$14184,2,0) -> LED (SMD Led) Strobe Beacon Amber : 12-24VDC with Alumunium screw base | F79: 1 | G79: PCS | H79: FT52521 | I79: general | J79: general | K79: REPLACE WORKLAMP | L79: DIMAS | M79: WIWIK | N79: 200001056936 | O79: DONE FROM BC | P79: 46154 | Q79: 9200086750 | R79: 46152 | S79: 45927 | T79: 46163 | U79: 50010 | V79: 22 Mei 2026
A80: 78 | B80: 46154 | C80: GMIAMMPIK/2026/5/0346 | D80: 11L-3204 | E80: =VLOOKUP(D80,MP!$A$1:$C$14184,2,0) -> Head Unit Radio Orca | F80: 6 | G80: PCS | H80: WT2532PPA | I80: general | J80: general | K80: REPLACE WORKLAMP | L80: DIMAS | M80: WIWIK | N80: 200001058797 | O80: DONE FROM BC | P80: 46154 | Q80: 9200087191 | R80: 46154 | S80: 45928 | T80: 46163 | U80: 50059 | V80: 22 Mei 2026
A81: 79 | B81: 46154 | C81: GMIAMMPIK/2026/5/0346 | D81: 11L-1290-ARW | E81: =VLOOKUP(D81,MP!$A$1:$C$14184,2,0) -> LED Combination Lamp Amber Red White | F81: 2 | G81: PCS | H81: WT2532PPA | I81: general | J81: general | K81: REPLACE WORKLAMP | L81: DIMAS | M81: WIWIK | N81: 200001058797 | O81: DONE FROM BC | P81: 46154 | Q81: 9200087191 | R81: 46154 | S81: 45928 | T81: 46163 | U81: 50059 | V81: 22 Mei 2026
... A89: 87 | B89: 46162 | C89: GMIAMMPIK/2026/5/0350 | D89: 11L-3024 | E89: =VLOOKUP(D89,MP!$A$1:$C$14184,2,0) -> LED FLood Light 6 Eyes 18 Watt 10-30 VDC | F89: 1 | G89: PCS | H89: D5871 | I89: general | J89: general | K89: REPLACE WORKLAMP | L89: DIMAS | M89: WIWIK | N89: 200001063780 | O89: DONE FROM BC | P89: 46162 | Q89: 9200088825 | R89: 46162 | S89: 45932 | T89: 46163 | U89: 50069 | V89: 22 Mei 2026
A90: 88 | B90: 46176 | C90: GMIAMMPIK/2026/6/0351 | D90: 11L-3024 | E90: =VLOOKUP(D90,MP!$A$1:$C$14184,2,0) -> LED FLood Light 6 Eyes 18 Watt 10-30 VDC | F90: 2 | G90: PCS | H90: WT2522PPA | I90: general | J90: general | K90: REPLACE WORKLAMP | L90: DIMAS | M90: WIWIK | N90: 200001065638 | O90: DONE FROM BC | P90: 46176 | Q90: 9200089489 | R90: 46164 | S90: 46372 | T90: 46181 | U90: 50453 | V90: 46182
A91: 89 | B91: 46176 | C91: GMIAMMPIK/2026/6/0351 | D91: 11L-1290-ARW | E91: =VLOOKUP(D91,MP!$A$1:$C$14184,2,0) -> LED Combination Lamp Amber Red White | F91: 1 | G91: PCS | H91: WT2522PPA | I91: general | J91: general | K91: REPLACE WORKLAMP | L91: DIMAS | M91: WIWIK | N91: 200001065638 | O91: DONE FROM BC | P91: 46176 | Q91: 9200089489 | R91: 46164 | S91: 46372 | T91: 46181 | U91: 50453 | V91: 46182
A92: 90 | B92: 46176 | C92: GMIAMMPIK/2026/6/0351 | D92: 3L4-7ASA | E92: =VLOOKUP(D92,MP!$A$1:$C$14184,2,0) -> LED (SMD Led) Strobe Beacon Amber : 12-24VDC with Alumunium screw base | F92: 1 | G92: PCS | H92: WT2522PPA | I92: general | J92: general | K92: REPLACE WORKLAMP | L92: DIMAS | M92: WIWIK | N92: 200001065638 | O92: DONE FROM BC | P92: 46176 | Q92: 9200089489 | R92: 46164 | S92: 46372 | T92: 46181 | U92: 50453 | V92: 46182
A93: 91 | B93: 46176 | C93: GMIAMMPIK/2026/6/0352 | D93: 3L3-8AA | E93: =VLOOKUP(D93,MP!$A$1:$C$14184,2,0) -> Amber Xenon Beacon Light 12-24VDC with alumunium screw base | F93: 2 | G93: PCS | H93: H57082 | I93: general | J93: general | K93: REPLACE WORKLAMP | L93: DIMAS | M93: WIWIK | N93: 200001066370 | O93: DONE FROM BC | P93: 46176 | Q93: 9200089828 | R93: 46166 | S93: 46373 | T93: 46181 | U93: 50454 | V93: 46182
A94: 92 | B94: 46176 | C94: GMIAMMPIK/2026/6/0352 | D94: 3L3-8AB | E94: =VLOOKUP(D94,MP!$A$1:$C$14184,2,0) -> Blue Xenon Beacon Light 12-24VDC with alumunium screw base | F94: 1 | G94: PCS | H94: H57082 | I94: general | J94: general | K94: REPLACE WORKLAMP | L94: DIMAS | M94: WIWIK | N94: 200001066370 | O94: DONE FROM BC | P94: 46176 | Q94: 9200089828 | R94: 46166 | S94: 46373 | T94: 46181 | U94: 50454 | V94: 46182
A95: 93 | B95: 46176 | C95: GMIAMMPIK/2026/6/0353 | D95: 11L-3024 | E95: =VLOOKUP(D95,MP!$A$1:$C$14184,2,0) -> LED FLood Light 6 Eyes 18 Watt 10-30 VDC | F95: 1 | G95: PCS | H95: D5871 | I95: general | J95: general | K95: REPLACE WORKLAMP | L95: DIMAS | M95: WIWIK | N95: 200001067859 | O95: DONE FROM BC | P95: 46176 | Q95: 9200090095 | R95: 46168 | S95: 46376 | T95: 46181 | U95: 50455 | V95: 46182
A96: 94 | B96: 46176 | C96: GMIAMMPIK/2026/6/0354 | D96: 11L-3024 | E96: =VLOOKUP(D96,MP!$A$1:$C$14184,2,0) -> LED FLood Light 6 Eyes 18 Watt 10-30 VDC | F96: 3 | G96: PCS | H96: WT2522PPA | I96: general | J96: general | K96: REPLACE WORKLAMP | L96: DIMAS | M96: WIWIK | N96: 200001068379 | O96: DONE FROM BC | P96: 46176 | Q96: 9200090413 | R96: 46171 | S96: 46377 | T96: 46181 | U96: 50456 | V96: 46182
A97: 95 | B97: 46176 | C97: GMIAMMPIK/2026/6/0355 | D97: 11L-3024 | E97: =VLOOKUP(D97,MP!$A$1:$C$14184,2,0) -> LED FLood Light 6 Eyes 18 Watt 10-30 VDC | F97: 1 | G97: PCS | H97: DA2505PPA | I97: general | J97: general | K97: REPLACE WORKLAMP | L97: DIMAS | M97: WIWIK | N97: 200001069845 | O97: DONE FROM BC | P97: 46176 | Q97: 9200090774 | R97: 46171 | S97: 46378 | T97: 46181 | U97: 50457 | V97: 46182
A98: 96 | B98: 46176 | C98: GMIAMMPIK/2026/6/0356 | D98: 3L4-7ASA | E98: =VLOOKUP(D98,MP!$A$1:$C$14184,2,0) -> LED (SMD Led) Strobe Beacon Amber : 12-24VDC with Alumunium screw base | F98: 1 | G98: PCS | H98: H57134 | I98: general | J98: general | K98: REPLACE WORKLAMP | L98: DIMAS | M98: WIWIK | N98: 200001069733 | O98: DONE FROM BC | P98: 46176 | Q98: 9200090816 | R98: 46172 | S98: 46379 | T98: 46181 | U98: 50459 | V98: 46182
A99: 97 | B99: 46176 | C99: GMIAMMPIK/2026/6/0357 | D99: 11L-1290-ARW | E99: =VLOOKUP(D99,MP!$A$1:$C$14184,2,0) -> LED Combination Lamp Amber Red White | F99: 1 | G99: PCS | H99: PLTAM15 | I99: general | J99: general | K99: REPLACE WORKLAMP | L99: DIMAS | M99: WIWIK | N99: 260000035923 | O99: DONE FROM BC | P99: 46176 | Q99: 9200090909 | R99: 46174 | S99: 46381 | T99: 46181 | U99: 50460 | V99: 46182
A100: 98 | B100: 46176 | C100: GMIAMMPIK/2026/6/0358 | D100: 3L3-8AA | E100: =VLOOKUP(D100,MP!$A$1:$C$14184,2,0) -> Amber Xenon Beacon Light 12-24VDC with alumunium screw base | F100: 1 | G100: PCS | H100: E508PPA | I100: general | J100: general | K100: REPLACE WORKLAMP | L100: DIMAS | M100: WIWIK | N100: 200001071903 | O100: DONE FROM BC | P100: 46176 | Q100: 9200091319 | R100: 46175 | S100: 46382 | T100: 46181 | U100: 50461 | V100: 46182
A101: 99 | B101: 46176 | C101: GMIAMMPIK/2026/6/0359 | D101: 11L-3024 | E101: =VLOOKUP(D101,MP!$A$1:$C$14184,2,0) -> LED FLood Light 6 Eyes 18 Watt 10-30 VDC | F101: 2 | G101: PCS | H101: H57081 | I101: general | J101: general | K101: REPLACE WORKLAMP | L101: DIMAS | M101: WIWIK | N101: 200001072943 | O101: DONE FROM BC | P101: 46176 | Q101: 9200091486 | R101: 46175 | S101: 46382 | T101: 46181 | U101: 50462 | V101: 46182
... A133: 131 | B133: 46220 | C133: GMIAMMPIK/2026/7/0377 | D133: 11L-1290-ARW | E133: =VLOOKUP(D133,MP!$A$1:$C$14184,2,0) -> LED Combination Lamp Amber Red White | F133: 2 | G133: PCS | H133: FT52530 | I133: general | J133: general | K133: REPLACE WORKLAMP | L133: NOVI | M133: WIWIK | N133: 20001100950 | O133: DONE FROM BC | P133: 46220 | Q133: 9200100461 | R133: 46218 | S133: 48149 | T133: 46223 | U133: 52310 | V133: 46223
A134: 132 | B134: 46227 | C134: GMIAMMPIK/2026/7/0378 | D134: 3L4-7ASB | E134: =VLOOKUP(D134,MP!$A$1:$C$14184,2,0) -> LED (SMD Led) Strobe Beacon Blue : 12-24VDC with Alumunium screw base | F134: 2 | G134: PCS | H134: D5860 | I134: general | J134: general | K134: REPLACE WORKLAMP | L134: NOVI | M134: WIWIK | N134: 200001104796 | O134: DONE FROM BC | P134: 46227 | Q134: 9200101734 | R134: 21/07/2026 | S134: 48862 | T134: 46234 | U134: 52962 | V134: 46234
A135: 133 | B135: 46227 | C135: GMIAMMPIK/2026/7/0378 | D135: 11L-1290-ARW | E135: =VLOOKUP(D135,MP!$A$1:$C$14184,2,0) -> LED Combination Lamp Amber Red White | F135: 1 | G135: PCS | H135: D5860 | I135: general | J135: general | K135: REPLACE WORKLAMP | L135: NOVI | M135: WIWIK | N135: 200001104796 | O135: DONE FROM BC | P135: 46227 | Q135: 9200101734 | R135: 21/07/2026 | S135: 48862 | T135: 46234 | U135: 52962 | V135: 46234
A136: 134 | B136: 46227 | C136: GMIAMMPIK/2026/7/0378 | D136: 11L-3024 | E136: =VLOOKUP(D136,MP!$A$1:$C$14184,2,0) -> LED FLood Light 6 Eyes 18 Watt 10-30 VDC | F136: 1 | G136: PCS | H136: D5860 | I136: general | J136: general | K136: REPLACE WORKLAMP | L136: NOVI | M136: WIWIK | N136: 200001104796 | O136: DONE FROM BC | P136: 46227 | Q136: 9200101734 | R136: 21/07/2026 | S136: 48862 | T136: 46234 | U136: 52962 | V136: 46234
A137: 135 | B137: 46227 | C137: GMIAMMPIK/2026/7/0379 | D137: 11L-3024 | E137: =VLOOKUP(D137,MP!$A$1:$C$14184,2,0) -> LED FLood Light 6 Eyes 18 Watt 10-30 VDC | F137: 2 | G137: PCS | H137: E423PPA | I137: general | J137: general | K137: REPLACE WORKLAMP | L137: NOVI | M137: WIWIK | N137: 200001107097 | O137: DONE FROM BC | P137: 46227 | Q137: 9200102270 | R137: 46226 | S137: 48858 | T137: 46234 | U137: 52941 | V137: 46234
A138: 136 | B138: 46227 | C138: GMIAMMPIK/2026/7/0380 | D138: 11L-1290-ARW | E138: =VLOOKUP(D138,MP!$A$1:$C$14184,2,0) -> LED Combination Lamp Amber Red White | F138: 2 | G138: PCS | H138: DA54816 | I138: general | J138: general | K138: REPLACE WORKLAMP | L138: NOVI | M138: WIWIK | N138: 200001107546 | O138: DONE FROM BC | P138: 46227 | Q138: 9200102529 | R138: 46227 | S138: 48859 | T138: 46234 | U138: 52942 | V138: 46234
A139: 137 | B139: 46227 | C139: GMIAMMPIK/2026/7/0381 | D139: 11L-3024 | E139: =VLOOKUP(D139,MP!$A$1:$C$14184,2,0) -> LED FLood Light 6 Eyes 18 Watt 10-30 VDC | F139: 1 | G139: PCS | H139: P54606 | I139: general | J139: general | K139: REPLACE WORKLAMP | L139: NOVI | M139: WIWIK | N139: 200001108696 | O139: DONE FROM BC | P139: 46227 | Q139: 9200102898 | R139: 46229 | S139: 48860 | T139: 46234 | U139: 52943 | V139: 46234
A140: 138 | B140: 46232 | C140: GMIAMMPIK/2026/7/0382 | D140: 11L-3024 | E140: =VLOOKUP(D140,MP!$A$1:$C$14184,2,0) -> LED FLood Light 6 Eyes 18 Watt 10-30 VDC | F140: 1 | G140: PCS | H140: WA52520 | I140: general | J140: general | K140: REPLACE WORKLAMP | L140: NOVI | M140: WIWIK | N140: 200001110482 | O140: DONE FROM BC | P140: 46232 | Q140: 9200103559 | R140: 46232 | S140: 48861 | T140: 46234 | U140: 52944 | V140: 46234
A141: 139 | B141: 46233 | C141: GMIAMMPIK/2026/7/0383 | D141: 11L-3024 | E141: =VLOOKUP(D141,MP!$A$1:$C$14184,2,0) -> LED FLood Light 6 Eyes 18 Watt 10-30 VDC | F141: 3 | G141: PCS | H141: SV508 | I141: general | J141: general | K141: REPLACE WORKLAMP | L141: NOVI | M141: WIWIK | N141: 200001111644 | O141: DONE FROM BC | P141: 46233 | Q141: 9200103877 | R141: 46233 | S141: 48863 | T141: 46234 | U141: 52963 | V141: 46234
A142: 140 | B142: 46234 | C142: GMIAMMPIK/2026/7/0384 | D142: 3L3-8AB | E142: =VLOOKUP(D142,MP!$A$1:$C$14184,2,0) -> Blue Xenon Beacon Light 12-24VDC with alumunium screw base | F142: 1 | G142: PCS | H142: D5860 | I142: general | J142: general | K142: REPLACE WORKLAMP | L142: NOVI | M142: WIWIK | N142: 200001112474 | O142: DONE FROM BC | P142: 46234 | Q142: 9200104162 | R142: 46234 | S142: 48986 | T142: 46240 | U142: 53169 | V142: 46240
A143: 141 | B143: 46234 | C143: GMIAMMPIK/2026/7/0384 | D143: 11L-3024 | E143: =VLOOKUP(D143,MP!$A$1:$C$14184,2,0) -> LED FLood Light 6 Eyes 18 Watt 10-30 VDC | F143: 1 | G143: PCS | H143: D5860 | I143: general | J143: general | K143: REPLACE WORKLAMP | L143: NOVI | M143: WIWIK | N143: 200001112474 | O143: DONE FROM BC | P143: 46234 | Q143: 9200104162 | R143: 46234 | S143: 48986 | T143: 46240 | U143: 53169 | V143: 46240
A144: 142 | B144: 46234 | C144: GMIAMMPIK/2026/7/0384 | D144: 11L-1290-ARW | E144: =VLOOKUP(D144,MP!$A$1:$C$14184,2,0) -> LED Combination Lamp Amber Red White | F144: 1 | G144: PCS | H144: D5860 | I144: general | J144: general | K144: REPLACE WORKLAMP | L144: NOVI | M144: WIWIK | N144: 200001112474 | O144: DONE FROM BC | P144: 46234 | Q144: 9200104162 | R144: 46234 | S144: 48986 | T144: 46240 | U144: 53169 | V144: 46240
A145: 143 | B145: 46235 | C145: GMIAMMPIK/2026/7/0385 | D145: 11L-3024 | E145: =VLOOKUP(D145,MP!$A$1:$C$14184,2,0) -> LED FLood Light 6 Eyes 18 Watt 10-30 VDC | F145: 4 | G145: PCS | H145: DA25034PPA | I145: general | J145: general | K145: REPLACE WORKLAMP | L145: NOVI | M145: WIWIK | N145: 2000001113175 | O145: DONE FROM BC | P145: 46235 | Q145: 9200104251 | R145: 46235 | S145: 48988 | T145: 46240 | U145: 53170 | V145: 46240
A146: 144 | B146: 46235 | C146: GMIAMMPIK/2026/7/0385 | D146: 3L3-8AA | E146: =VLOOKUP(D146,MP!$A$1:$C$14184,2,0) -> Amber Xenon Beacon Light 12-24VDC with alumunium screw base | F146: 1 | G146: PCS | H146: DA25034PPA | I146: general | J146: general | K146: REPLACE WORKLAMP | L146: NOVI | M146: WIWIK | N146: 2000001113175 | O146: DONE FROM BC | P146: 46235 | Q146: 9200104251 | R146: 46235 | S146: 48988 | T146: 46240 | U146: 53170 | V146: 46240
A147: 145 | B147: 46235 | C147: GMIAMMPIK/2026/7/0386 | D147: 3L4-7ASA | E147: =VLOOKUP(D147,MP!$A$1:$C$14184,2,0) -> LED (SMD Led) Strobe Beacon Amber : 12-24VDC with Alumunium screw base | F147: 1 | G147: PCS | H147: DA52535 | I147: general | J147: general | K147: REPLACE WORKLAMP | L147: NOVI | M147: WIWIK | N147: 200001113591 | O147: DONE FROM BC | P147: 46235 | Q147: 9200104310 | R147: 46236 | S147: 48989 | T147: 46240 | U147: 53171 | V147: 46240
A148: 146 | B148: 46235 | C148: GMIAMMPIK/2026/7/0386 | D148: 11L-3024 | E148: =VLOOKUP(D148,MP!$A$1:$C$14184,2,0) -> LED FLood Light 6 Eyes 18 Watt 10-30 VDC | F148: 2 | G148: PCS | H148: DA52535 | I148: general | J148: general | K148: REPLACE WORKLAMP | L148: NOVI | M148: WIWIK | N148: 200001113591 | O148: DONE FROM BC | P148: 46235 | Q148: 9200104310 | R148: 46236 | S148: 48989 | T148: 46240 | U148: 53171 | V148: 46240
... A180: 179 | B180: 46295 | C180: GMIAMMPIK/2026/9/0405 | D180: 3L3-8AB | E180: =VLOOKUP(D180,MP!$A$1:$C$14184,2,0) -> Blue Xenon Beacon Light 12-24VDC with alumunium screw base | F180: 1 | G180: PCS | H180: D5860 | I180: general | J180: general | K180: REPLACE WORKLAMP | L180: NOVI | M180: WIWIK | N180: 200001152038 | O180: DONE FROM BC | P180: 46295 | Q180: 9200114664 | R180: 46294 | S180: 51589 | T180: 46295 | U180: 55673 | V180: 46295

Sheet MP
A1: Part_No | B1: Part_Name | C1: Satuan
A2: 14L-0093 | B2: Receiver Drier | C2: Ea
A3: 14L-0094-F | B3: Thermostat Fujin 10A | C3: Ea
A4: 10L111 | B4: 24V Electric Fan | C4: Ea
A5: 10L112 | B5: 12V Electric Fan | C5: Ea
A6: 10L113 | B6: 24V Electric Fan | C6: Ea
A7: 10L114 | B7: 12V Electric Fan | C7: Ea
A8: 10L115 | B8: 24V Electric Fan | C8: Ea
A9: 10L116 | B9: 12V Electric Fan | C9: Ea
A10: 10L117 | B10: 24V Electric Fan | C10: Ea
A11: 10L118 | B11: 12V Electric Fan | C11: Ea
A12: 10L119 | B12: 24V Electric Fan | C12: Ea
... A386: 10L285-ND60 | B386: Bracket ND60F TIDAK COAK | C386: Ea
A387: 10L285-ND60-C | B387: BRACKET ND60F COAK
A388: 10L285-ND60-PC1250 | B388: Bracket ND60F With Baseplat Siku | C388: Ea
A389: 10L285-ND-GD755 | B389: Bracket Foglamp GD755 Set (2 pcs) | C389: Set
A390: 10L285-PC210 | B390: Bracket Work Lamp 2L3-2S for PC210 (Counterweight) | C390: Ea
A391: 10L285-SCGE | B391: Bracket Revese Lamp For CGE | C391: Ea
A392: 10L286 | B392: Bracket For Indicator Lamp 9L-SM02/03 | C392: Ea
A393: 10L286-2 | B393: Bracket For Indicator Lamp 9L-SM03-1 Pipih | C393: Ea
A394: 10L289-APDUHD785 | B394: Bracket Modul APDU HD785 | C394: Set
A395: 10L289-D375 | B395: Bracket Module SPMC for D375 | C395: Ea
A396: 10L289-HD | B396: Bracket Module SPMC for HD785 | C396: Ea
A397: 10L289-HD785-8R-MD | B397: Bracket Modul HD785-8R Modif | C397: Ea
A398: 10L289-HD8R | B398: Bracket Modul SPMC HD 785-8R | C398: Ea
A399: 10L289-HD8R-v2 | B399: Bracket Modul SPMC HD 785-8R Versi 2 | C399: Set
... A5295: 11L-3923-G380 | B5295: Sticker vessel & logo KPP CISS for Genset EGS380 | C5295: Set
A5296: 11L-3923-G380-I | B5296: Sticker set for Genset EGS380 (Vessel & Logo)
A5297: 11L-3923-G460 | B5297: Sticker set for G460 (No Lambung & Logo KPP) | C5297: Set
A5298: 11L-3923-G460-I | B5298: Sticker Logo & Vessel for G460 | C5298: Set
A5299: 11L-3923-G630 | B5299: Sticker vessel & logo KPP for Genset G630 | C5299: Set
A5300: 11L-3923-GD705 | B5300: Sticker logo & vessel for GD705 | C5300: Set
A5301: 11L-3923-GD705-I | B5301: Sticker set for GD705 (Vessel & Logo KPP) | C5301: Set
A5302: 11L-3923-GD825 | B5302: Sticker vessel & logo KPP GD825 | C5302: Set
A5303: 11L-3923-GD825-I | B5303: Sticker Set for GD825A-2A (Vessel & Logo KPP) | C5303: Set
A5304: 11L-3923-HB365 | B5304: Sticker Logo & Vessel for HB365 | C5304: Set
A5305: 11L-3923-HB365-I | B5305: Sticker Set for HB365 (Vessel & Logo KPP) | C5305: Set
A5306: 11L-3923-HD785 | B5306: Sticker Logo & Vessel for HD785-7 | C5306: Set
A5307: 11L-3923-HD785-I | B5307: Sticker set for HD785-7 (Vessel & Logo KPP) | C5307: Set
A5308: 11L-3923-HM400 | B5308: Sticker vessel & logo for HM400 | C5308: Set
... A5815: 11L-5839 | B5815: ROUND HEAD FOR PUSHBUTTON SPRING RETURN XAC-A BLACK BOOTED | C5815: EA
A5816: 11L-5985 | B5816: Push button station dengan pilot lamp fort
A5817: 11L-6054 | B5817: Digital Clamp Meter Value VMC-1 | C5817: Ea
A5818: 11L-6055 | B5818: Multimeter Digital Avometer Sanwa | C5818: Ea
A5819: 11L-61-55021 | B5819: SWITCH ON OFF | C5819: Ea
A5820: 11L-616-1498 | B5820: ADVANCED MODERN DIGITAL | C5820: Ea
A5821: 11L620200 | B5821: FOR HEATER AC | C5821: Ea
A5822: 11L-7013 | B5822: INDICATOR LUBE SYSTEM | C5822: Ea
A5823: 11L-75904 | B5823: SWITCH:SELECTOR BATTERY SWITCH | C5823: Ea
A5824: 11L-75907 | B5824: HEAVY DUTY FOR 50AMP | C5824: Ea
A5825: 11L-7ASAPC200300400-IP | B5825: LED Strobe Amber PC 200, 300, 400, HM400 Instalation Part | C5825: Set
A5826: 11L-7ASBPC200300400-IP | B5826: LED Strobe Blue PC 200, 300, 400, HM400 Instalation Part | C5826: Set
A5827: 11L-90030 | B5827: SWITCH | C5827: Ea
A5828: 11L-92420 | B5828: BLANKING | C5828: Ea
... A6211: 12L-BAUT-M4X30 | B6211: Baut 8.8 M4 x 30 full drat | C6211: Set
A6212: 12L-BAUT-M4X5 | B6212: Baut Set 8.8 M4X5 (Baut, Ring, Per, Ring, Plat, Mur)
A6213: 12L-BautM5-3 | B6213: Baut M5 x 3 cm 8.8 with Ring, Mur, Nut | C6213: Set
A6214: 12L-BAUT-M5X10 | B6214: Baut M5 X 10, 8.8 Plat+Nut+Washer+Spring | C6214: Ea
A6215: 12L-BAUT-M5X10-NP | B6215: Baut M5 X 10, JP Plat+Nut+Washer+Spring | C6215: Set
A6216: 12L-BAUT-M5X15 | B6216: Baut Set 8.8 (Baja) - M5 X 15 | C6216: Set
A6217: 12L-BAUT-M5X15-B | B6217: Baut Set JP - M5 X 15 (Baut, Ring Per, Ring Plat, Mur) | C6217: Set
A6218: 12L-BAUT-M5X15-NP | B6218: Baut Set JP - M5 X 15 (Baut, Ring Per, Ring Plat, Mur)
A6219: 12L-BAUT-M5X15-S | B6219: Baut Set 8.8 (Mur+Ring) - M5 X 15 Stainless | C6219: Ea
A6220: 12L-BAUT-M5X20-B | B6220: Baut set M5 x 20 Kepala Bulat | C6220: Set
A6221: 12L-BAUT-M5X20-NP | B6221: Baut Set 8.8 (Baja) - M5 X 20 (Baut, Ring Per, Ring Plat, Mur) | C6221: Set
A6222: 12L-BAUTM5X25 | B6222: Baut set, Stainless M5X25 | C6222: Set
A6223: 12L-BAUT-M5X25 | B6223: Baut set, Stainless M5X25
A6224: 12L-BAUT-M5X3 | B6224: Baut Set 8.8 (Baja) M5X3 | C6224: Ea
A6225: 12L-BAUT-M5X3,5 | B6225: Baut Set 8.8 (Baja) M5X3,5 | C6225: Ea
A6226: 12L-BAUT-M5X30 | B6226: Baut Set 8.8 (Baja) - M5 X 30 | C6226: Set
A6227: 12L-BAUT-M5X30-B | B6227: Baut Set JP-M5X3 (Baut, Ring, Per, Ring Plat, Mur) | C6227: Set
A6228: 12L-BAUT-M5X30-NP | B6228: Baut Set 8.8 (Baja) - M5 X 30 (Baut, Ring Per, Ring Plat, Mur) | C6228: Set
A6229: 12L-BAUT-M5X30S | B6229: Baut, ring plat M5X30 Stainless | C6229: Set
A6230: 12L-BAUT-M5X35 | B6230: Baut Set JP-M5X3,5 (Baut, Ring, Per, Ring Plat, Mur) | C6230: EA
A6231: 12L-BAUT-M5X60 | B6231: Baut Set 8.8 M5X60 (Baut, Ring, Per, Ring, Plat, Mur)
A6232: 12L-Baut-M620 | B6232: Baut M6 x 20 cm | C6232: Set
A6233: 12L-Baut-M640 | B6233: Baut Mur Ring Baja 8.8 M6 x 40 cm | C6233: Set
A6234: 12L-BAUT-M6X10 | B6234: Baut 8.8 set M6X10 | C6234: Set
A6235: 12L-BAUT-M6X10-NP | B6235: Baut 8.8 set M6X10 (Baut, Ring Plat, Ring Ver, Mur) | C6235: Set
A6236: 12L-BAUT-M6X10S | B6236: Baut, ring plat M6X10 Stainless | C6236: Set
A6237: 12L-BAUT-M6X15 | B6237: Baut Set 8.8 (Baja) - M6 X 15 | C6237: Set
A6238: 12L-BAUT-M6X20-B | B6238: Baut Set JP - M6 X 20 (Baut, Ring Per, Ring Plat, Mur) | C6238: Set
A6239: 12L-BAUT-M6X20S | B6239: Baut, ring plat M6X20 Stainless | C6239: Set
A6240: 12L-BAUT-M6X25-NP | B6240: Baut Set 8.8 (Baja) - M6 X 25 (Baut, Ring Per, Ring Plat, Mur) | C6240: Set
A6241: 12L-BAUT-M6X25-R | B6241: Baut Set (Baja) - M6 X 25 ( kepala rata)
A6242: 12L-BAUT-M6x2CM | B6242: Baut Bolt Service Valve Denso M6x2Cm | C6242: Ea
A6243: 12L-BAUT-M6X3 | B6243: Baut Set 8.8 (Baja) M6X3 | C6243: Ea
A6244: 12L-BAUT-M6X30-NP | B6244: Baut Set 8.8 (Baja) - M6 x 30 (Baut, Ring Per, Ring Plat, Mur) | C6244: Set
A6245: 12L-BAUT-M6X30-R | B6245: Baut Set M6X30 Kepala Rata | C6245: Set
A6246: 12L-BAUT-M6X40 | B6246: Baut Set 8.8 (Baja) M6X40 | C6246: Ea
A6247: 12L-BAUT-M6X41 | B6247: Baut Set 8.8 (Baja) M6X40 | C6247: Ea
A6248: 12L-BAUT-M6X50 | B6248: Baut M6X50, 8.8 Plat+Nut+Washer+Spring | C6248: Set
A6249: 12L-BAUT-M6X70 | B6249: Baut M6X70, 8.8 Plat+Nut+Washer+Spring | C6249: Set
A6250: 12L-BAUT-M6x80 | B6250: Baut Set Baja 8.8 M6x80 | C6250: Set
A6251: 12L-BAUT-M8X1.9-R | B6251: Baut Roofing Ring M8x1.9cm | C6251: Ea
A6252: 12L-BAUT-M8X10 | B6252: Baut Set 8.8 (Baja) - M8 X 10 (Baut, Ring Per, Ring Plat, Mur) | C6252: Set
A6253: 12L-BAUT-M8X100 | B6253: Baut M8X100, 8.8 Plat+Nut+Washer+Spring | C6253: Set
... A6414: 12L-PlatGIS8x3 | B6414: Name Plat GIS HO | C6414: Ea
A6415: 12L-PlatGIS8x3-S | B6415: Name Plat GIS HO 8x3cm Stainless
A6416: 12L-PlatGIS-B | B6416: Plat Global Inti Sejati besar | C6416: Ea
...
